Workbook

Sheet Pricing Piso Chile
A1: TABLA DE PRECIOS PISO — CHILE 2026 | AGROVECA GRUPO LATAM
A2: ⚙️ Celda B3 = margen objetivo (recalcula columnas E-K automáticamente). Celda azul = editable. Celda verde = precio propuesto por Gerencia.
A3: MARGEN OBJETIVO → | B3: 0.45 | C3: ← Cambia este % y todo se recalcula
A5: PRODUCTO | B5: FORMATO | C5: COSTO FÁBRICA (PKG) | D5: TAMAÑO FMT | E5: COSTO $/UNIDAD | F5: PRECIO PISO (CALCULADO) | G5: MARGEN CALC % | H5: PRECIO PROM REAL | I5: NUEVO PRECIO PISO PROPUESTO | J5: MARGEN PROPUESTO % | K5: GAP PROP. vs CALC % | L5: VAR $ (Prop - Real) | M5: CLASIF. PROPUESTO | N5: ORDEN FMT
A6: AV ALGAP 30 | B6: 1 L | C6: 3715 | D6: 1 | E6: =C6/D6 -> 3715 | F6: =E6/(1-$B$3) -> 6754.5455 | G6: =$B$3 -> 0.45 | I6: 6800 | J6: =IF(I6="","",(I6-E6)/I6) -> 0.45367647 | K6: =IF(I6="","",(I6-F6)/F6) -> 0.0067294751 | L6: =IF(OR(I6="",H6=""),"",I6-H6) | M6: =IF(I6="","⚪ SIN PROPUESTA",IF(I6<F6*0.95,"🔴 BAJO PISO",IF(I6>F6*1.05,"🟢 SOBRE PISO","🟡 EN PISO"))) -> 🟡 EN PISO | N6: {=IFERROR(_xlfn.SWITCH(B6,"1 L",1,"5 L",2,"5 L (VECA)",2.5,"20 L",3,"200 L",4,"250 GR",5,"500 GR",6,"1000 L",7),99)} -> 1
A7: AV ALGAP 30 | B7: 5 L | C7: 12996 | D7: 5 | E7: =C7/D7 -> 2599.2 | F7: =E7/(1-$B$3) -> 4725.8182 | G7: =$B$3 -> 0.45 | I7: 5000 | J7: =IF(I7="","",(I7-E7)/I7) -> 0.48016 | K7: =IF(I7="","",(I7-F7)/F7) -> 0.058017852 | L7: =IF(OR(I7="",H7=""),"",I7-H7) | M7: =IF(I7="","⚪ SIN PROPUESTA",IF(I7<F7*0.95,"🔴 BAJO PISO",IF(I7>F7*1.05,"🟢 SOBRE PISO","🟡 EN PISO"))) -> 🟢 SOBRE PISO | N7: {=IFERROR(_xlfn.SWITCH(B7,"1 L",1,"5 L",2,"5 L (VECA)",2.5,"20 L",3,"200 L",4,"250 GR",5,"500 GR",6,"1000 L",7),99)} -> 2
A8: AV ALGAP 30 | B8: 20 L | C8: 37644 | D8: 20 | E8: =IF(C8="","",C8/D8) -> 1882.2 | F8: =IF(E8="","",E8/(1-$B$3)) -> 3422.1818 | G8: =$B$3 -> 0.45 | I8: 4000 | J8: =IF(I8="","",(I8-E8)/I8) -> 0.52945 | K8: =IF(I8="","",(I8-F8)/F8) -> 0.16884497 | L8: =IF(OR(I8="",H8=""),"",I8-H8) | M8: =IF(I8="","⚪ SIN PROPUESTA",IF(I8<F8*0.95,"🔴 BAJO PISO",IF(I8>F8*1.05,"🟢 SOBRE PISO","🟡 EN PISO"))) -> 🟢 SOBRE PISO | N8: {=IFERROR(_xlfn.SWITCH(B8,"1 L",1,"5 L",2,"5 L (VECA)",2.5,"20 L",3,"200 L",4,"250 GR",5,"500 GR",6,"1000 L",7),99)} -> 3
A9: AV ALGAP 30 | B9: 200 L | C9: 320130 | D9: 200 | E9: =IF(C9="","",C9/D9) -> 1600.65 | F9: =IF(E9="","",E9/(1-$B$3)) -> 2910.2727 | G9: =$B$3 -> 0.45 | I9: 3500 | J9: =IF(I9="","",(I9-E9)/I9) -> 0.54267143 | K9: =IF(I9="","",(I9-F9)/F9) -> 0.20263643 | L9: =IF(OR(I9="",H9=""),"",I9-H9) | M9: =IF(I9="","⚪ SIN PROPUESTA",IF(I9<F9*0.95,"🔴 BAJO PISO",IF(I9>F9*1.05,"🟢 SOBRE PISO","🟡 EN PISO"))) -> 🟢 SOBRE PISO | N9: {=IFERROR(_xlfn.SWITCH(B9,"1 L",1,"5 L",2,"5 L (VECA)",2.5,"20 L",3,"200 L",4,"250 GR",5,"500 GR",6,"1000 L",7),99)} -> 4
A10: AV ALGAP 30 | B10: 1000 L | C10: 1537520 | D10: 1000 | E10: =IF(C10="","",C10/D10) -> 1537.52 | F10: =IF(E10="","",E10/(1-$B$3)) -> 2795.4909 | G10: =$B$3 -> 0.45 | I10: 3000 | J10: =IF(I10="","",(I10-E10)/I10) -> 0.48749333 | K10: =IF(I10="","",(I10-F10)/F10) -> 0.073156772 | L10: =IF(OR(I10="",H10=""),"",I10-H10) | M10: =IF(I10="","⚪ SIN PROPUESTA",IF(I10<F10*0.95,"🔴 BAJO PISO",IF(I10>F10*1.05,"🟢 SOBRE PISO","🟡 EN PISO"))) -> 🟢 SOBRE PISO | N10: {=IFERROR(_xlfn.SWITCH(B10,"1 L",1,"5 L",2,"5 L (VECA)",2.5,"20 L",3,"200 L",4,"250 GR",5,"500 GR",6,"1000 L",7),99)} -> 7
A11: AV AMIN | B11: 1 L | C11: 3669 | D11: 1 | E11: =C11/D11 -> 3669 | F11: =E11/(1-$B$3) -> 6670.9091 | G11: =$B$3 -> 0.45 | H11: 6602 | I11: 7800 | J11: =IF(I11="","",(I11-E11)/I11) -> 0.52961538 | K11: =IF(I11="","",(I11-F11)/F11) -> 0.16925593 | L11: =IF(OR(I11="",H11=""),"",I11-H11) -> 1198 | M11: =IF(I11="","⚪ SIN PROPUESTA",IF(I11<F11*0.95,"🔴 BAJO PISO",IF(I11>F11*1.05,"🟢 SOBRE PISO","🟡 EN PISO"))) -> 🟢 SOBRE PISO | N11: {=IFERROR(_xlfn.SWITCH(B11,"1 L",1,"5 L",2,"5 L (VECA)",2.5,"20 L",3,"200 L",4,"250 GR",5,"500 GR",6,"1000 L",7),99)} -> 1
A12: AV AMIN | B12: 5 L | C12: 12765 | D12: 5 | E12: =C12/D12 -> 2553 | F12: =E12/(1-$B$3) -> 4641.8182 | G12: =$B$3 -> 0.45 | H12: 7500 | I12: 7000 | J12: =IF(I12="","",(I12-E12)/I12) -> 0.63528571 | K12: =IF(I12="","",(I12-F12)/F12) -> 0.50802977 | L12: =IF(OR(I12="",H12=""),"",I12-H12) -> -500 | M12: =IF(I12="","⚪ SIN PROPUESTA",IF(I12<F12*0.95,"🔴 BAJO PISO",IF(I12>F12*1.05,"🟢 SOBRE PISO","🟡 EN PISO"))) -> 🟢 SOBRE PISO | N12: {=IFERROR(_xlfn.SWITCH(B12,"1 L",1,"5 L",2,"5 L (VECA)",2.5,"20 L",3,"200 L",4,"250 GR",5,"500 GR",6,"1000 L",7),99)} -> 2
A13: AV AMIN | B13: 20 L | C13: 36718 | D13: 20 | E13: =C13/D13 -> 1835.9 | F13: =E13/(1-$B$3) -> 3338 | G13: =$B$3 -> 0.45 | H13: 5008 | I13: 5500 | J13: =IF(I13="","",(I13-E13)/I13) -> 0.6662 | K13: =IF(I13="","",(I13-F13)/F13) -> 0.64769323 | L13: =IF(OR(I13="",H13=""),"",I13-H13) -> 492 | M13: =IF(I13="","⚪ SIN PROPUESTA",IF(I13<F13*0.95,"🔴 BAJO PISO",IF(I13>F13*1.05,"🟢 SOBRE PISO","🟡 EN PISO"))) -> 🟢 SOBRE PISO | N13: {=IFERROR(_xlfn.SWITCH(B13,"1 L",1,"5 L",2,"5 L (VECA)",2.5,"20 L",3,"200 L",4,"250 GR",5,"500 GR",6,"1000 L",7),99)} -> 3
A14: AV AMIN | B14: 200 L | C14: 254381 | D14: 200 | E14: =IF(C14="","",C14/D14) -> 1271.905 | F14: =IF(E14="","",E14/(1-$B$3)) -> 2312.5545 | G14: =$B$3 -> 0.45 | I14: 3500 | J14: =IF(I14="","",(I14-E14)/I14) -> 0.63659857 | K14: =IF(I14="","",(I14-F14)/F14) -> 0.51347781 | L14: =IF(OR(I14="",H14=""),"",I14-H14) | M14: =IF(I14="","⚪ SIN PROPUESTA",IF(I14<F14*0.95,"🔴 BAJO PISO",IF(I14>F14*1.05,"🟢 SOBRE PISO","🟡 EN PISO"))) -> 🟢 SOBRE PISO | N14: {=IFERROR(_xlfn.SWITCH(B14,"1 L",1,"5 L",2,"5 L (VECA)",2.5,"20 L",3,"200 L",4,"250 GR",5,"500 GR",6,"1000 L",7),99)} -> 4
A15: AV AMIN | B15: 1000 L | C15: 1491220 | D15: 1000 | E15: =IF(C15="","",C15/D15) -> 1491.22 | F15: =IF(E15="","",E15/(1-$B$3)) -> 2711.3091 | G15: =$B$3 -> 0.45 | I15: 3000 | J15: =IF(I15="","",(I15-E15)/I15) -> 0.50292667 | K15: =IF(I15="","",(I15-F15)/F15) -> 0.10647658 | L15: =IF(OR(I15="",H15=""),"",I15-H15) | M15: =IF(I15="","⚪ SIN PROPUESTA",IF(I15<F15*0.95,"🔴 BAJO PISO",IF(I15>F15*1.05,"🟢 SOBRE PISO","🟡 EN PISO"))) -> 🟢 SOBRE PISO | N15: {=IFERROR(_xlfn.SWITCH(B15,"1 L",1,"5 L",2,"5 L (VECA)",2.5,"20 L",3,"200 L",4,"250 GR",5,"500 GR",6,"1000 L",7),99)} -> 7
A16: AV AMIN SUGAR | B16: 1 L | C16: 3589 | D16: 1 | E16: =C16/D16 -> 3589 | F16: =E16/(1-$B$3) -> 6525.4545 | G16: =$B$3 -> 0.45 | I16: 9000 | J16: =IF(I16="","",(I16-E16)/I16) -> 0.60122222 | K16: =IF(I16="","",(I16-F16)/F16) -> 0.37921427 | L16: =IF(OR(I16="",H16=""),"",I16-H16) | M16: =IF(I16="","⚪ SIN PROPUESTA",IF(I16<F16*0.95,"🔴 BAJO PISO",IF(I16>F16*1.05,"🟢 SOBRE PISO","🟡 EN PISO"))) -> 🟢 SOBRE PISO | N16: {=IFERROR(_xlfn.SWITCH(B16,"1 L",1,"5 L",2,"5 L (VECA)",2.5,"20 L",3,"200 L",4,"250 GR",5,"500 GR",6,"1000 L",7),99)} -> 1
A17: AV AMIN SUGAR | B17: 5 L | C17: 12367 | D17: 5 | E17: =C17/D17 -> 2473.4 | F17: =E17/(1-$B$3) -> 4497.0909 | G17: =$B$3 -> 0.45 | H17: 6004 | I17: 8000 | J17: =IF(I17="","",(I17-E17)/I17) -> 0.690825 | K17: =IF(I17="","",(I17-F17)/F17) -> 0.77892779 | L17: =IF(OR(I17="",H17=""),"",I17-H17) -> 1996 | M17: =IF(I17="","⚪ SIN PROPUESTA",IF(I17<F17*0.95,"🔴 BAJO PISO",IF(I17>F17*1.05,"🟢 SOBRE PISO","🟡 EN PISO"))) -> 🟢 SOBRE PISO | N17: {=IFERROR(_xlfn.SWITCH(B17,"1 L",1,"5 L",2,"5 L (VECA)",2.5,"20 L",3,"200 L",4,"250 GR",5,"500 GR",6,"1000 L",7),99)} -> 2
A18: AV AMIN SUGAR | B18: 20 L | C18: 35129 | D18: 20 | E18: =C18/D18 -> 1756.45 | F18: =E18/(1-$B$3) -> 3193.5455 | G18: =$B$3 -> 0.45 | H18: 5375 | I18: 6500 | J18: =IF(I18="","",(I18-E18)/I18) -> 0.72977692 | K18: =IF(I18="","",(I18-F18)/F18) -> 1.0353554 | L18: =IF(OR(I18="",H18=""),"",I18-H18) -> 1125 | M18: =IF(I18="","⚪ SIN PROPUESTA",IF(I18<F18*0.95,"🔴 BAJO PISO",IF(I18>F18*1.05,"🟢 SOBRE PISO","🟡 EN PISO"))) -> 🟢 SOBRE PISO | N18: {=IFERROR(_xlfn.SWITCH(B18,"1 L",1,"5 L",2,"5 L (VECA)",2.5,"20 L",3,"200 L",4,"250 GR",5,"500 GR",6,"1000 L",7),99)} -> 3
A19: AV AMIN SUGAR | B19: 200 L | C19: 238491 | D19: 200 | E19: =IF(C19="","",C19/D19) -> 1192.455 | F19: =IF(E19="","",E19/(1-$B$3)) -> 2168.1 | G19: =$B$3 -> 0.45 | H19: 4500 | I19: 5000 | J19: =IF(I19="","",(I19-E19)/I19) -> 0.761509 | K19: =IF(I19="","",(I19-F19)/F19) -> 1.3061667 | L19: =IF(OR(I19="",H19=""),"",I19-H19) -> 500 | M19: =IF(I19="","⚪ SIN PROPUESTA",IF(I19<F19*0.95,"🔴 BAJO PISO",IF(I19>F19*1.05,"🟢 SOBRE PISO","🟡 EN PISO"))) -> 🟢 SOBRE PISO | N19: {=IFERROR(_xlfn.SWITCH(B19,"1 L",1,"5 L",2,"5 L (VECA)",2.5,"20 L",3,"200 L",4,"250 GR",5,"500 GR",6,"1000 L",7),99)} -> 4
A20: AV AMIN SUGAR | B20: 1000 L | C20: 1411770 | D20: 1000 | E20: =IF(C20="","",C20/D20) -> 1411.77 | F20: =IF(E20="","",E20/(1-$B$3)) -> 2566.8545 | G20: =$B$3 -> 0.45 | I20: 4000 | J20: =IF(I20="","",(I20-E20)/I20) -> 0.6470575 | K20: =IF(I20="","",(I20-F20)/F20) -> 0.55832749 | L20: =IF(OR(I20="",H20=""),"",I20-H20) | M20: =IF(I20="","⚪ SIN PROPUESTA",IF(I20<F20*0.95,"🔴 BAJO PISO",IF(I20>F20*1.05,"🟢 SOBRE PISO","🟡 EN PISO"))) -> 🟢 SOBRE PISO | N20: {=IFERROR(_xlfn.SWITCH(B20,"1 L",1,"5 L",2,"5 L (VECA)",2.5,"20 L",3,"200 L",4,"250 GR",5,"500 GR",6,"1000 L",7),99)} -> 7
A21: AV BALANCE | B21: 1 L | C21: 4631 | D21: 1 | E21: =C21/D21 -> 4631 | F21: =E21/(1-$B$3) -> 8420 | G21: =$B$3 -> 0.45 | H21: 13661 | I21: 15000 | J21: =IF(I21="","",(I21-E21)/I21) -> 0.69126667 | K21: =IF(I21="","",(I21-F21)/F21) -> 0.78147268 | L21: =IF(OR(I21="",H21=""),"",I21-H21) -> 1339 | M21: =IF(I21="","⚪ SIN PROPUESTA",IF(I21<F21*0.95,"🔴 BAJO PISO",IF(I21>F21*1.05,"🟢 SOBRE PISO","🟡 EN PISO"))) -> 🟢 SOBRE PISO | N21: {=IFERROR(_xlfn.SWITCH(B21,"1 L",1,"5 L",2,"5 L (VECA)",2.5,"20 L",3,"200 L",4,"250 GR",5,"500 GR",6,"1000 L",7),99)} -> 1
A22: AV BALANCE | B22: 5 L | C22: 17574 | D22: 5 | E22: =C22/D22 -> 3514.8 | F22: =E22/(1-$B$3) -> 6390.5455 | G22: =$B$3 -> 0.45 | H22: 14239 | I22: 14000 | J22: =IF(I22="","",(I22-E22)/I22) -> 0.74894286 | K22: =IF(I22="","",(I22-F22)/F22) -> 1.1907363 | L22: =IF(OR(I22="",H22=""),"",I22-H22) -> -239 | M22: =IF(I22="","⚪ SIN PROPUESTA",IF(I22<F22*0.95,"🔴 BAJO PISO",IF(I22>F22*1.05,"🟢 SOBRE PISO","🟡 EN PISO"))) -> 🟢 SOBRE PISO | N22: {=IFERROR(_xlfn.SWITCH(B22,"1 L",1,"5 L",2,"5 L (VECA)",2.5,"20 L",3,"200 L",4,"250 GR",5,"500 GR",6,"1000 L",7),99)} -> 2
A23: AV BALANCE | B23: 20 L | C23: 55955 | D23: 20 | E23: =C23/D23 -> 2797.75 | F23: =E23/(1-$B$3) -> 5086.8182 | G23: =$B$3 -> 0.45 | H23: 13691 | I23: 13500 | J23: =IF(I23="","",(I23-E23)/I23) -> 0.79275926 | K23: =IF(I23="","",(I23-F23)/F23) -> 1.6539183 | L23: =IF(OR(I23="",H23=""),"",I23-H23) -> -191 | M23: =IF(I23="","⚪ SIN PROPUESTA",IF(I23<F23*0.95,"🔴 BAJO PISO",IF(I23>F23*1.05,"🟢 SOBRE PISO","🟡 EN PISO"))) -> 🟢 SOBRE PISO | N23: {=IFERROR(_xlfn.SWITCH(B23,"1 L",1,"5 L",2,"5 L (VECA)",2.5,"20 L",3,"200 L",4,"250 GR",5,"500 GR",6,"1000 L",7),99)} -> 3
A24: AV BALANCE | B24: 200 L | C24: 503237 | D24: 200 | E24: =IF(C24="","",C24/D24) -> 2516.185 | F24: =IF(E24="","",E24/(1-$B$3)) -> 4574.8818 | G24: =$B$3 -> 0.45 | I24: 11000 | J24: =IF(I24="","",(I24-E24)/I24) -> 0.77125591 | K24: =IF(I24="","",(I24-F24)/F24) -> 1.4044337 | L24: =IF(OR(I24="",H24=""),"",I24-H24) | M24: =IF(I24="","⚪ SIN PROPUESTA",IF(I24<F24*0.95,"🔴 BAJO PISO",IF(I24>F24*1.05,"🟢 SOBRE PISO","🟡 EN PISO"))) -> 🟢 SOBRE PISO | N24: {=IFERROR(_xlfn.SWITCH(B24,"1 L",1,"5 L",2,"5 L (VECA)",2.5,"20 L",3,"200 L",4,"250 GR",5,"500 GR",6,"1000 L",7),99)} -> 4
A25: AV BALANCE | B25: 1000 L | C25: 2453056 | D25: 1000 | E25: =IF(C25="","",C25/D25) -> 2453.056 | F25: =IF(E25="","",E25/(1-$B$3)) -> 4460.1018 | G25: =$B$3 -> 0.45 | I25: 10000 | J25: =IF(I25="","",(I25-E25)/I25) -> 0.7546944 | K25: =IF(I25="","",(I25-F25)/F25) -> 1.2421013 | L25: =IF(OR(I25="",H25=""),"",I25-H25) | M25: =IF(I25="","⚪ SIN PROPUESTA",IF(I25<F25*0.95,"🔴 BAJO PISO",IF(I25>F25*1.05,"🟢 SOBRE PISO","🟡 EN PISO"))) -> 🟢 SOBRE PISO | N25: {=IFERROR(_xlfn.SWITCH(B25,"1 L",1,"5 L",2,"5 L (VECA)",2.5,"20 L",3,"200 L",4,"250 GR",5,"500 GR",6,"1000 L",7),99)} -> 7
A26: AV BIOSOLARIS | B26: 1 L | C26: 4143 | D26: 1 | E26: =C26/D26 -> 4143 | F26: =E26/(1-$B$3) -> 7532.7273 | G26: =$B$3 -> 0.45 | H26: 12757 | I26: 16000 | J26: =IF(I26="","",(I26-E26)/I26) -> 0.7410625 | K26: =IF(I26="","",(I26-F26)/F26) -> 1.1240647 | L26: =IF(OR(I26="",H26=""),"",I26-H26) -> 3243 | M26: =IF(I26="","⚪ SIN PROPUESTA",IF(I26<F26*0.95,"🔴 BAJO PISO",IF(I26>F26*1.05,"🟢 SOBRE PISO","🟡 EN PISO"))) -> 🟢 SOBRE PISO | N26: {=IFERROR(_xlfn.SWITCH(B26,"1 L",1,"5 L",2,"5 L (VECA)",2.5,"20 L",3,"200 L",4,"250 GR",5,"500 GR",6,"1000 L",7),99)} -> 1
A27: AV BIOSOLARIS | B27: 5 L | C27: 15134 | D27: 5 | E27: =C27/D27 -> 3026.8 | F27: =E27/(1-$B$3) -> 5503.2727 | G27: =$B$3 -> 0.45 | I27: 15000 | J27: =IF(I27="","",(I27-E27)/I27) -> 0.79821333 | K27: =IF(I27="","",(I27-F27)/F27) -> 1.7256509 | L27: =IF(OR(I27="",H27=""),"",I27-H27) | M27: =IF(I27="","⚪ SIN PROPUESTA",IF(I27<F27*0.95,"🔴 BAJO PISO",IF(I27>F27*1.05,"🟢 SOBRE PISO","🟡 EN PISO"))) -> 🟢 SOBRE PISO | N27: {=IFERROR(_xlfn.SWITCH(B27,"1 L",1,"5 L",2,"5 L (VECA)",2.5,"20 L",3,"200 L",4,"250 GR",5,"500 GR",6,"1000 L",7),99)} -> 2
A28: AV BIOSOLARIS | B28: 20 L | C28: 46195 | D28: 20 | E28: =C28/D28 -> 2309.75 | F28: =E28/(1-$B$3) -> 4199.5455 | G28: =$B$3 -> 0.45 | H28: 14250 | I28: 14000 | J28: =IF(I28="","",(I28-E28)/I28) -> 0.83501786 | K28: =IF(I28="","",(I28-F28)/F28) -> 2.3336941 | L28: =IF(OR(I28="",H28=""),"",I28-H28) -> -250 | M28: =IF(I28="","⚪ SIN PROPUESTA",IF(I28<F28*0.95,"🔴 BAJO PISO",IF(I28>F28*1.05,"🟢 SOBRE PISO","🟡 EN PISO"))) -> 🟢 SOBRE PISO | N28: {=IFERROR(_xlfn.SWITCH(B28,"1 L",1,"5 L",2,"5 L (VECA)",2.5,"20 L",3,"200 L",4,"250 GR",5,"500 GR",6,"1000 L",7),99)} -> 3
A29: AV BIOSOLARIS | B29: 200 L | C29: 405640 | D29: 200 | E29: =IF(C29="","",C29/D29) -> 2028.2 | F29: =IF(E29="","",E29/(1-$B$3)) -> 3687.6364 | G29: =$B$3 -> 0.45 | I29: 13000 | J29: =IF(I29="","",(I29-E29)/I29) -> 0.84398462 | K29: =IF(I29="","",(I29-F29)/F29) -> 2.5252934 | L29: =IF(OR(I29="",H29=""),"",I29-H29) | M29: =IF(I29="","⚪ SIN PROPUESTA",IF(I29<F29*0.95,"🔴 BAJO PISO",IF(I29>F29*1.05,"🟢 SOBRE PISO","🟡 EN PISO"))) -> 🟢 SOBRE PISO | N29: {=IFERROR(_xlfn.SWITCH(B29,"1 L",1,"5 L",2,"5 L (VECA)",2.5,"20 L",3,"200 L",4,"250 GR",5,"500 GR",6,"1000 L",7),99)} -> 4
A30: AV BIOSOLARIS | B30: 1000 L | C30: 1965071 | D30: 1000 | E30: =IF(C30="","",C30/D30) -> 1965.071 | F30: =IF(E30="","",E30/(1-$B$3)) -> 3572.8564 | G30: =$B$3 -> 0.45 | I30: 10000 | J30: =IF(I30="","",(I30-E30)/I30) -> 0.8034929 | K30: =IF(I30="","",(I30-F30)/F30) -> 1.7988811 | L30: =IF(OR(I30="",H30=""),"",I30-H30) | M30: =IF(I30="","⚪ SIN PROPUESTA",IF(I30<F30*0.95,"🔴 BAJO PISO",IF(I30>F30*1.05,"🟢 SOBRE PISO","🟡 EN PISO"))) -> 🟢 SOBRE PISO | N30: {=IFERROR(_xlfn.SWITCH(B30,"1 L",1,"5 L",2,"5 L (VECA)",2.5,"20 L",3,"200 L",4,"250 GR",5,"500 GR",6,"1000 L",7),99)} -> 7
A31: AV BLOOM | B31: 1 L | C31: 4096 | D31: 1 | E31: =C31/D31 -> 4096 | F31: =E31/(1-$B$3) -> 7447.2727 | G31: =$B$3 -> 0.45 | H31: 9912 | I31: 11000 | J31: =IF(I31="","",(I31-E31)/I31) -> 0.62763636 | K31: =IF(I31="","",(I31-F31)/F31) -> 0.47705078 | L31: =IF(OR(I31="",H31=""),"",I31-H31) -> 1088 | M31: =IF(I31="","⚪ SIN PROPUESTA",IF(I31<F31*0.95,"🔴 BAJO PISO",IF(I31>F31*1.05,"🟢 SOBRE PISO","🟡 EN PISO"))) -> 🟢 SOBRE PISO | N31: {=IFERROR(_xlfn.SWITCH(B31,"1 L",1,"5 L",2,"5 L (VECA)",2.5,"20 L",3,"200 L",4,"250 GR",5,"500 GR",6,"1000 L",7),99)} -> 1
A32: AV BLOOM | B32: 5 L | C32: 14901 | D32: 5 | E32: =C32/D32 -> 2980.2 | F32: =E32/(1-$B$3) -> 5418.5455 | G32: =$B$3 -> 0.45 | H32: 8548 | I32: 9500 | J32: =IF(I32="","",(I32-E32)/I32) -> 0.68629474 | K32: =IF(I32="","",(I32-F32)/F32) -> 0.75323804 | L32: =IF(OR(I32="",H32=""),"",I32-H32) -> 952 | M32: =IF(I32="","⚪ SIN PROPUESTA",IF(I32<F32*0.95,"🔴 BAJO PISO",IF(I32>F32*1.05,"🟢 SOBRE PISO","🟡 EN PISO"))) -> 🟢 SOBRE PISO | N32: {=IFERROR(_xlfn.SWITCH(B32,"1 L",1,"5 L",2,"5 L (VECA)",2.5,"20 L",3,"200 L",4,"250 GR",5,"500 GR",6,"1000 L",7),99)} -> 2
A33: AV BLOOM | B33: 20 L | C33: 45266 | D33: 20 | E33: =C33/D33 -> 2263.3 | F33: =E33/(1-$B$3) -> 4115.0909 | G33: =$B$3 -> 0.45 | H33: 9300 | I33: 9000 | J33: =IF(I33="","",(I33-E33)/I33) -> 0.74852222 | K33: =IF(I33="","",(I33-F33)/F33) -> 1.187072 | L33: =IF(OR(I33="",H33=""),"",I33-H33) -> -300 | M33: =IF(I33="","⚪ SIN PROPUESTA",IF(I33<F33*0.95,"🔴 BAJO PISO",IF(I33>F33*1.05,"🟢 SOBRE PISO","🟡 EN PISO"))) -> 🟢 SOBRE PISO | N33: {=IFERROR(_xlfn.SWITCH(B33,"1 L",1,"5 L",2,"5 L (VECA)",2.5,"20 L",3,"200 L",4,"250 GR",5,"500 GR",6,"1000 L",7),99)} -> 3
A34: AV BLOOM | B34: 200 L | C34: 396347 | D34: 200 | E34: =IF(C34="","",C34/D34) -> 1981.735 | F34: =IF(E34="","",E34/(1-$B$3)) -> 3603.1545 | G34: =$B$3 -> 0.45 | I34: 8000 | J34: =IF(I34="","",(I34-E34)/I34) -> 0.75228313 | K34: =IF(I34="","",(I34-F34)/F34) -> 1.2202767 | L34: =IF(OR(I34="",H34=""),"",I34-H34) | M34: =IF(I34="","⚪ SIN PROPUESTA",IF(I34<F34*0.95,"🔴 BAJO PISO",IF(I34>F34*1.05,"🟢 SOBRE PISO","🟡 EN PISO"))) -> 🟢 SOBRE PISO | N34: {=IFERROR(_xlfn.SWITCH(B34,"1 L",1,"5 L",2,"5 L (VECA)",2.5,"20 L",3,"200 L",4,"250 GR",5,"500 GR",6,"1000 L",7),99)} -> 4
A35: AV BLOOM | B35: 1000 L | C35: 1918607 | D35: 1000 | E35: =IF(C35="","",C35/D35) -> 1918.607 | F35: =IF(E35="","",E35/(1-$B$3)) -> 3488.3764 | G35: =$B$3 -> 0.45 | I35: 7000 | J35: =IF(I35="","",(I35-E35)/I35) -> 0.72591329 | K35: =IF(I35="","",(I35-F35)/F35) -> 1.0066642 | L35: =IF(OR(I35="",H35=""),"",I35-H35) | M35: =IF(I35="","⚪ SIN PROPUESTA",IF(I35<F35*0.95,"🔴 BAJO PISO",IF(I35>F35*1.05,"🟢 SOBRE PISO","🟡 EN PISO"))) -> 🟢 SOBRE PISO | N35: {=IFERROR(_xlfn.SWITCH(B35,"1 L",1,"5 L",2,"5 L (VECA)",2.5,"20 L",3,"200 L",4,"250 GR",5,"500 GR",6,"1000 L",7),99)} -> 7
A36: AV CYTO PRIME | B36: 1 L | C36: 4500 | D36: 1 | E36: =C36/D36 -> 4500 | F36: =E36/(1-$B$3) -> 8181.8182 | G36: =$B$3 -> 0.45 | I36: 18000 | J36: =IF(I36="","",(I36-E36)/I36) -> 0.75 | K36: =IF(I36="","",(I36-F36)/F36) -> 1.2 | L36: =IF(OR(I36="",H36=""),"",I36-H36) | M36: =IF(I36="","⚪ SIN PROPUESTA",IF(I36<F36*0.95,"🔴 BAJO PISO",IF(I36>F36*1.05,"🟢 SOBRE PISO","🟡 EN PISO"))) -> 🟢 SOBRE PISO | N36: {=IFERROR(_xlfn.SWITCH(B36,"1 L",1,"5 L",2,"5 L (VECA)",2.5,"20 L",3,"200 L",4,"250 GR",5,"500 GR",6,"1000 L",7),99)} -> 1
A37: AV CYTO PRIME | B37: 5 L | C37: 16920 | D37: 5 | E37: =C37/D37 -> 3384 | F37: =E37/(1-$B$3) -> 6152.7273 | G37: =$B$3 -> 0.45 | H37: 16911 | I37: 17000 | J37: =IF(I37="","",(I37-E37)/I37) -> 0.80094118 | K37: =IF(I37="","",(I37-F37)/F37) -> 1.7630024 | L37: =IF(OR(I37="",H37=""),"",I37-H37) -> 89 | M37: =IF(I37="","⚪ SIN PROPUESTA",IF(I37<F37*0.95,"🔴 BAJO PISO",IF(I37>F37*1.05,"🟢 SOBRE PISO","🟡 EN PISO"))) -> 🟢 SOBRE PISO | N37: {=IFERROR(_xlfn.SWITCH(B37,"1 L",1,"5 L",2,"5 L (VECA)",2.5,"20 L",3,"200 L",4,"250 GR",5,"500 GR",6,"1000 L",7),99)} -> 2
A38: AV CYTO PRIME | B38: 20 L | C38: 53340 | D38: 20 | E38: =IF(C38="","",C38/D38) -> 2667 | F38: =IF(E38="","",E38/(1-$B$3)) -> 4849.0909 | G38: =$B$3 -> 0.45 | H38: 16000 | I38: 15800 | J38: =IF(I38="","",(I38-E38)/I38) -> 0.83120253 | K38: =IF(I38="","",(I38-F38)/F38) -> 2.2583427 | L38: =IF(OR(I38="",H38=""),"",I38-H38) -> -200 | M38: =IF(I38="","⚪ SIN PROPUESTA",IF(I38<F38*0.95,"🔴 BAJO PISO",IF(I38>F38*1.05,"🟢 SOBRE PISO","🟡 EN PISO"))) -> 🟢 SOBRE PISO | N38: {=IFERROR(_xlfn.SWITCH(B38,"1 L",1,"5 L",2,"5 L (VECA)",2.5,"20 L",3,"200 L",4,"250 GR",5,"500 GR",6,"1000 L",7),99)} -> 3
A39: AV CYTO PRIME | B39: 200 L | C39: 477086 | D39: 200 | E39: =IF(C39="","",C39/D39) -> 2385.43 | F39: =IF(E39="","",E39/(1-$B$3)) -> 4337.1455 | G39: =$B$3 -> 0.45 | I39: 14000 | J39: =IF(I39="","",(I39-E39)/I39) -> 0.82961214 | K39: =IF(I39="","",(I39-F39)/F39) -> 2.2279296 | L39: =IF(OR(I39="",H39=""),"",I39-H39) | M39: =IF(I39="","⚪ SIN PROPUESTA",IF(I39<F39*0.95,"🔴 BAJO PISO",IF(I39>F39*1.05,"🟢 SOBRE PISO","🟡 EN PISO"))) -> 🟢 SOBRE PISO | N39: {=IFERROR(_xlfn.SWITCH(B39,"1 L",1,"5 L",2,"5 L (VECA)",2.5,"20 L",3,"200 L",4,"250 GR",5,"500 GR",6,"1000 L",7),99)} -> 4
A40: AV CYTO PRIME | B40: 1000 L | C40: 2322301 | D40: 1000 | E40: =IF(C40="","",C40/D40) -> 2322.301 | F40: =IF(E40="","",E40/(1-$B$3)) -> 4222.3655 | G40: =$B$3 -> 0.45 | I40: 11000 | J40: =IF(I40="","",(I40-E40)/I40) -> 0.78888173 | K40: =IF(I40="","",(I40-F40)/F40) -> 1.6051748 | L40: =IF(OR(I40="",H40=""),"",I40-H40) | M40: =IF(I40="","⚪ SIN PROPUESTA",IF(I40<F40*0.95,"🔴 BAJO PISO",IF(I40>F40*1.05,"🟢 SOBRE PISO","🟡 EN PISO"))) -> 🟢 SOBRE PISO | N40: {=IFERROR(_xlfn.SWITCH(B40,"1 L",1,"5 L",2,"5 L (VECA)",2.5,"20 L",3,"200 L",4,"250 GR",5,"500 GR",6,"1000 L",7),99)} -> 7
A41: AV HUMIC ROOT | B41: 1 L | C41: 3338 | D41: 1 | E41: =C41/D41 -> 3338 | F41: =E41/(1-$B$3) -> 6069.0909 | G41: =$B$3 -> 0.45 | I41: 6500 | J41: =IF(I41="","",(I41-E41)/I41) -> 0.48646154 | K41: =IF(I41="","",(I41-F41)/F41) -> 0.071000599 | L41: =IF(OR(I41="",H41=""),"",I41-H41) | M41: =IF(I41="","⚪ SIN PROPUESTA",IF(I41<F41*0.95,"🔴 BAJO PISO",IF(I41>F41*1.05,"🟢 SOBRE PISO","🟡 EN PISO"))) -> 🟢 SOBRE PISO | N41: {=IFERROR(_xlfn.SWITCH(B41,"1 L",1,"5 L",2,"5 L (VECA)",2.5,"20 L",3,"200 L",4,"250 GR",5,"500 GR",6,"1000 L",7),99)} -> 1
A42: AV HUMIC ROOT | B42: 5 L | C42: 11108 | D42: 5 | E42: =C42/D42 -> 2221.6 | F42: =E42/(1-$B$3) -> 4039.2727 | G42: =$B$3 -> 0.45 | I42: 5800 | J42: =IF(I42="","",(I42-E42)/I42) -> 0.61696552 | K42: =IF(I42="","",(I42-F42)/F42) -> 0.43590205 | L42: =IF(OR(I42="",H42=""),"",I42-H42) | M42: =IF(I42="","⚪ SIN PROPUESTA",IF(I42<F42*0.95,"🔴 BAJO PISO",IF(I42>F42*1.05,"🟢 SOBRE PISO","🟡 EN PISO"))) -> 🟢 SOBRE PISO | N42: {=IFERROR(_xlfn.SWITCH(B42,"1 L",1,"5 L",2,"5 L (VECA)",2.5,"20 L",3,"200 L",4,"250 GR",5,"500 GR",6,"1000 L",7),99)} -> 2
A43: AV HUMIC ROOT | B43: 20 L | C43: 30072 | D43: 20 | E43: =IF(C43="","",C43/D43) -> 1503.6 | F43: =IF(E43="","",E43/(1-$B$3)) -> 2733.8182 | G43: =$B$3 -> 0.45 | H43: 4225 | I43: 4000 | J43: =IF(I43="","",(I43-E43)/I43) -> 0.6241 | K43: =IF(I43="","",(I43-F43)/F43) -> 0.46315509 | L43: =IF(OR(I43="",H43=""),"",I43-H43) -> -225 | M43: =IF(I43="","⚪ SIN PROPUESTA",IF(I43<F43*0.95,"🔴 BAJO PISO",IF(I43>F43*1.05,"🟢 SOBRE PISO","🟡 EN PISO"))) -> 🟢 SOBRE PISO | N43: {=IFERROR(_xlfn.SWITCH(B43,"1 L",1,"5 L",2,"5 L (VECA)",2.5,"20 L",3,"200 L",4,"250 GR",5,"500 GR",6,"1000 L",7),99)} -> 3
A44: AV HUMIC ROOT | B44: 200 L | C44: 244610 | D44: 200 | E44: =IF(C44="","",C44/D44) -> 1223.05 | F44: =IF(E44="","",E44/(1-$B$3)) -> 2223.7273 | G44: =$B$3 -> 0.45 | H44: 2300 | I44: 3200 | J44: =IF(I44="","",(I44-E44)/I44) -> 0.61779688 | K44: =IF(I44="","",(I44-F44)/F44) -> 0.43902539 | L44: =IF(OR(I44="",H44=""),"",I44-H44) -> 900 | M44: =IF(I44="","⚪ SIN PROPUESTA",IF(I44<F44*0.95,"🔴 BAJO PISO",IF(I44>F44*1.05,"🟢 SOBRE PISO","🟡 EN PISO"))) -> 🟢 SOBRE PISO | N44: {=IFERROR(_xlfn.SWITCH(B44,"1 L",1,"5 L",2,"5 L (VECA)",2.5,"20 L",3,"200 L",4,"250 GR",5,"500 GR",6,"1000 L",7),99)} -> 4
A45: AV HUMIC ROOT | B45: 1000 L | C45: 1159920 | D45: 1000 | E45: =IF(C45="","",C45/D45) -> 1159.92 | F45: =IF(E45="","",E45/(1-$B$3)) -> 2108.9455 | G45: =$B$3 -> 0.45 | I45: 2800 | J45: =IF(I45="","",(I45-E45)/I45) -> 0.58574286 | K45: =IF(I45="","",(I45-F45)/F45) -> 0.32767777 | L45: =IF(OR(I45="",H45=""),"",I45-H45) | M45: =IF(I45="","⚪ SIN PROPUESTA",IF(I45<F45*0.95,"🔴 BAJO PISO",IF(I45>F45*1.05,"🟢 SOBRE PISO","🟡 EN PISO"))) -> 🟢 SOBRE PISO | N45: {=IFERROR(_xlfn.SWITCH(B45,"1 L",1,"5 L",2,"5 L (VECA)",2.5,"20 L",3,"200 L",4,"250 GR",5,"500 GR",6,"1000 L",7),99)} -> 7
A46: AV MAX FULVIC 45% | B46: 1 L | C46: 3338 | D46: 1 | E46: =C46/D46 -> 3338 | F46: =E46/(1-$B$3) -> 6069.0909 | G46: =$B$3 -> 0.45 | I46: 6500 | J46: =IF(I46="","",(I46-E46)/I46) -> 0.48646154 | K46: =IF(I46="","",(I46-F46)/F46) -> 0.071000599 | L46: =IF(OR(I46="",H46=""),"",I46-H46) | M46: =IF(I46="","⚪ SIN PROPUESTA",IF(I46<F46*0.95,"🔴 BAJO PISO",IF(I46>F46*1.05,"🟢 SOBRE PISO","🟡 EN PISO"))) -> 🟢 SOBRE PISO | N46: {=IFERROR(_xlfn.SWITCH(B46,"1 L",1,"5 L",2,"5 L (VECA)",2.5,"20 L",3,"200 L",4,"250 GR",5,"500 GR",6,"1000 L",7),99)} -> 1
A47: AV MAX FULVIC 45% | B47: 5 L | C47: 11108 | D47: 5 | E47: =C47/D47 -> 2221.6 | F47: =E47/(1-$B$3) -> 4039.2727 | G47: =$B$3 -> 0.45 | H47: 4200 | I47: 5800 | J47: =IF(I47="","",(I47-E47)/I47) -> 0.61696552 | K47: =IF(I47="","",(I47-F47)/F47) -> 0.43590205 | L47: =IF(OR(I47="",H47=""),"",I47-H47) -> 1600 | M47: =IF(I47="","⚪ SIN PROPUESTA",IF(I47<F47*0.95,"🔴 BAJO PISO",IF(I47>F47*1.05,"🟢 SOBRE PISO","🟡 EN PISO"))) -> 🟢 SOBRE PISO | N47: {=IFERROR(_xlfn.SWITCH(B47,"1 L",1,"5 L",2,"5 L (VECA)",2.5,"20 L",3,"200 L",4,"250 GR",5,"500 GR",6,"1000 L",7),99)} -> 2
A48: AV MAX FULVIC 45% | B48: 20 L | C48: 30072 | D48: 20 | E48: =C48/D48 -> 1503.6 | F48: =E48/(1-$B$3) -> 2733.8182 | G48: =$B$3 -> 0.45 | H48: 4403 | I48: 4000 | J48: =IF(I48="","",(I48-E48)/I48) -> 0.6241 | K48: =IF(I48="","",(I48-F48)/F48) -> 0.46315509 | L48: =IF(OR(I48="",H48=""),"",I48-H48) -> -403 | M48: =IF(I48="","⚪ SIN PROPUESTA",IF(I48<F48*0.95,"🔴 BAJO PISO",IF(I48>F48*1.05,"🟢 SOBRE PISO","🟡 EN PISO"))) -> 🟢 SOBRE PISO | N48: {=IFERROR(_xlfn.SWITCH(B48,"1 L",1,"5 L",2,"5 L (VECA)",2.5,"20 L",3,"200 L",4,"250 GR",5,"500 GR",6,"1000 L",7),99)} -> 3
A49: AV MAX FULVIC 45% | B49: 200 L | C49: 244610 | D49: 200 | E49: =IF(C49="","",C49/D49) -> 1223.05 | F49: =IF(E49="","",E49/(1-$B$3)) -> 2223.7273 | G49: =$B$3 -> 0.45 | H49: 2700 | I49: 3200 | J49: =IF(I49="","",(I49-E49)/I49) -> 0.61779688 | K49: =IF(I49="","",(I49-F49)/F49) -> 0.43902539 | L49: =IF(OR(I49="",H49=""),"",I49-H49) -> 500 | M49: =IF(I49="","⚪ SIN PROPUESTA",IF(I49<F49*0.95,"🔴 BAJO PISO",IF(I49>F49*1.05,"🟢 SOBRE PISO","🟡 EN PISO"))) -> 🟢 SOBRE PISO | N49: {=IFERROR(_xlfn.SWITCH(B49,"1 L",1,"5 L",2,"5 L (VECA)",2.5,"20 L",3,"200 L",4,"250 GR",5,"500 GR",6,"1000 L",7),99)} -> 4
A50: AV MAX FULVIC 45% | B50: 1000 L | C50: 1159920 | D50: 1000 | E50: =IF(C50="","",C50/D50) -> 1159.92 | F50: =IF(E50="","",E50/(1-$B$3)) -> 2108.9455 | G50: =$B$3 -> 0.45 | I50: 2800 | J50: =IF(I50="","",(I50-E50)/I50) -> 0.58574286 | K50: =IF(I50="","",(I50-F50)/F50) -> 0.32767777 | L50: =IF(OR(I50="",H50=""),"",I50-H50) | M50: =IF(I50="","⚪ SIN PROPUESTA",IF(I50<F50*0.95,"🔴 BAJO PISO",IF(I50>F50*1.05,"🟢 SOBRE PISO","🟡 EN PISO"))) -> 🟢 SOBRE PISO | N50: {=IFERROR(_xlfn.SWITCH(B50,"1 L",1,"5 L",2,"5 L (VECA)",2.5,"20 L",3,"200 L",4,"250 GR",5,"500 GR",6,"1000 L",7),99)} -> 7
A51: AV MOVE | B51: 1 L | C51: 4631 | D51: 1 | E51: =C51/D51 -> 4631 | F51: =E51/(1-$B$3) -> 8420 | G51: =$B$3 -> 0.45 | H51: 8670 | I51: 8800 | J51: =IF(I51="","",(I51-E51)/I51) -> 0.47375 | K51: =IF(I51="","",(I51-F51)/F51) -> 0.045130641 | L51: =IF(OR(I51="",H51=""),"",I51-H51) -> 130 | M51: =IF(I51="","⚪ SIN PROPUESTA",IF(I51<F51*0.95,"🔴 BAJO PISO",IF(I51>F51*1.05,"🟢 SOBRE PISO","🟡 EN PISO"))) -> 🟡 EN PISO | N51: {=IFERROR(_xlfn.SWITCH(B51,"1 L",1,"5 L",2,"5 L (VECA)",2.5,"20 L",3,"200 L",4,"250 GR",5,"500 GR",6,"1000 L",7),99)} -> 1
A52: AV MOVE | B52: 5 L | C52: 17574 | D52: 5 | E52: =C52/D52 -> 3514.8 | F52: =E52/(1-$B$3) -> 6390.5455 | G52: =$B$3 -> 0.45 | H52: 8065 | I52: 7800 | J52: =IF(I52="","",(I52-E52)/I52) -> 0.54938462 | K52: =IF(I52="","",(I52-F52)/F52) -> 0.22055309 | L52: =IF(OR(I52="",H52=""),"",I52-H52) -> -265 | M52: =IF(I52="","⚪ SIN PROPUESTA",IF(I52<F52*0.95,"🔴 BAJO PISO",IF(I52>F52*1.05,"🟢 SOBRE PISO","🟡 EN PISO"))) -> 🟢 SOBRE PISO | N52: {=IFERROR(_xlfn.SWITCH(B52,"1 L",1,"5 L",2,"5 L (VECA)",2.5,"20 L",3,"200 L",4,"250 GR",5,"500 GR",6,"1000 L",7),99)} -> 2
A53: AV MOVE | B53: 20 L | C53: 55955 | D53: 20 | E53: =C53/D53 -> 2797.75 | F53: =E53/(1-$B$3) -> 5086.8182 | G53: =$B$3 -> 0.45 | H53: 7767 | I53: 7500 | J53: =IF(I53="","",(I53-E53)/I53) -> 0.62696667 | K53: =IF(I53="","",(I53-F53)/F53) -> 0.47439907 | L53: =IF(OR(I53="",H53=""),"",I53-H53) -> -267 | M53: =IF(I53="","⚪ SIN PROPUESTA",IF(I53<F53*0.95,"🔴 BAJO PISO",IF(I53>F53*1.05,"🟢 SOBRE PISO","🟡 EN PISO"))) -> 🟢 SOBRE PISO | N53: {=IFERROR(_xlfn.SWITCH(B53,"1 L",1,"5 L",2,"5 L (VECA)",2.5,"20 L",3,"200 L",4,"250 GR",5,"500 GR",6,"1000 L",7),99)} -> 3
A54: AV MOVE | B54: 200 L | C54: 503237 | D54: 200 | E54: =IF(C54="","",C54/D54) -> 2516.185 | F54: =IF(E54="","",E54/(1-$B$3)) -> 4574.8818 | G54: =$B$3 -> 0.45 | I54: 6000 | J54: =IF(I54="","",(I54-E54)/I54) -> 0.58063583 | K54: =IF(I54="","",(I54-F54)/F54) -> 0.31150929 | L54: =IF(OR(I54="",H54=""),"",I54-H54) | M54: =IF(I54="","⚪ SIN PROPUESTA",IF(I54<F54*0.95,"🔴 BAJO PISO",IF(I54>F54*1.05,"🟢 SOBRE PISO","🟡 EN PISO"))) -> 🟢 SOBRE PISO | N54: {=IFERROR(_xlfn.SWITCH(B54,"1 L",1,"5 L",2,"5 L (VECA)",2.5,"20 L",3,"200 L",4,"250 GR",5,"500 GR",6,"1000 L",7),99)} -> 4
A55: AV MOVE | B55: 1000 L | C55: 2453056 | D55: 1000 | E55: =IF(C55="","",C55/D55) -> 2453.056 | F55: =IF(E55="","",E55/(1-$B$3)) -> 4460.1018 | G55: =$B$3 -> 0.45 | I55: 5000 | J55: =IF(I55="","",(I55-E55)/I55) -> 0.5093888 | K55: =IF(I55="","",(I55-F55)/F55) -> 0.12105064 | L55: =IF(OR(I55="",H55=""),"",I55-H55) | M55: =IF(I55="","⚪ SIN PROPUESTA",IF(I55<F55*0.95,"🔴 BAJO PISO",IF(I55>F55*1.05,"🟢 SOBRE PISO","🟡 EN PISO"))) -> 🟢 SOBRE PISO | N55: {=IFERROR(_xlfn.SWITCH(B55,"1 L",1,"5 L",2,"5 L (VECA)",2.5,"20 L",3,"200 L",4,"250 GR",5,"500 GR",6,"1000 L",7),99)} -> 7
A56: AV PLUS BORO | B56: 1 L | C56: 3090 | D56: 1 | E56: =C56/D56 -> 3090 | F56: =E56/(1-$B$3) -> 5618.1818 | G56: =$B$3 -> 0.45 | H56: 5838 | I56: 6000 | J56: =IF(I56="","",(I56-E56)/I56) -> 0.485 | K56: =IF(I56="","",(I56-F56)/F56) -> 0.067961165 | L56: =IF(OR(I56="",H56=""),"",I56-H56) -> 162 | M56: =IF(I56="","⚪ SIN PROPUESTA",IF(I56<F56*0.95,"🔴 BAJO PISO",IF(I56>F56*1.05,"🟢 SOBRE PISO","🟡 EN PISO"))) -> 🟢 SOBRE PISO | N56: {=IFERROR(_xlfn.SWITCH(B56,"1 L",1,"5 L",2,"5 L (VECA)",2.5,"20 L",3,"200 L",4,"250 GR",5,"500 GR",6,"1000 L",7),99)} -> 1
A57: AV PLUS BORO | B57: 5 L | C57: 9868 | D57: 5 | E57: =C57/D57 -> 1973.6 | F57: =E57/(1-$B$3) -> 3588.3636 | G57: =$B$3 -> 0.45 | H57: 5040 | I57: 5000 | J57: =IF(I57="","",(I57-E57)/I57) -> 0.60528 | K57: =IF(I57="","",(I57-F57)/F57) -> 0.39339278 | L57: =IF(OR(I57="",H57=""),"",I57-H57) -> -40 | M57: =IF(I57="","⚪ SIN PROPUESTA",IF(I57<F57*0.95,"🔴 BAJO PISO",IF(I57>F57*1.05,"🟢 SOBRE PISO","🟡 EN PISO"))) -> 🟢 SOBRE PISO | N57: {=IFERROR(_xlfn.SWITCH(B57,"1 L",1,"5 L",2,"5 L (VECA)",2.5,"20 L",3,"200 L",4,"250 GR",5,"500 GR",6,"1000 L",7),99)} -> 2
A58: AV PLUS BORO | B58: 20 L | C58: 25134 | D58: 20 | E58: =C58/D58 -> 1256.7 | F58: =E58/(1-$B$3) -> 2284.9091 | G58: =$B$3 -> 0.45 | H58: 4001 | I58: 4000 | J58: =IF(I58="","",(I58-E58)/I58) -> 0.685825 | K58: =IF(I58="","",(I58-F58)/F58) -> 0.75061669 | L58: =IF(OR(I58="",H58=""),"",I58-H58) -> -1 | M58: =IF(I58="","⚪ SIN PROPUESTA",IF(I58<F58*0.95,"🔴 BAJO PISO",IF(I58>F58*1.05,"🟢 SOBRE PISO","🟡 EN PISO"))) -> 🟢 SOBRE PISO | N58: {=IFERROR(_xlfn.SWITCH(B58,"1 L",1,"5 L",2,"5 L (VECA)",2.5,"20 L",3,"200 L",4,"250 GR",5,"500 GR",6,"1000 L",7),99)} -> 3
A59: AV PLUS BORO | B59: 200 L | C59: 195025 | D59: 200 | E59: =IF(C59="","",C59/D59) -> 975.125 | F59: =IF(E59="","",E59/(1-$B$3)) -> 1772.9545 | G59: =$B$3 -> 0.45 | I59: 3000 | J59: =IF(I59="","",(I59-E59)/I59) -> 0.67495833 | K59: =IF(I59="","",(I59-F59)/F59) -> 0.69209076 | L59: =IF(OR(I59="",H59=""),"",I59-H59) | M59: =IF(I59="","⚪ SIN PROPUESTA",IF(I59<F59*0.95,"🔴 BAJO PISO",IF(I59>F59*1.05,"🟢 SOBRE PISO","🟡 EN PISO"))) -> 🟢 SOBRE PISO | N59: {=IFERROR(_xlfn.SWITCH(B59,"1 L",1,"5 L",2,"5 L (VECA)",2.5,"20 L",3,"200 L",4,"250 GR",5,"500 GR",6,"1000 L",7),99)} -> 4
A60: AV PLUS BORO | B60: 1000 L | C60: 911997 | D60: 1000 | E60: =IF(C60="","",C60/D60) -> 911.997 | F60: =IF(E60="","",E60/(1-$B$3)) -> 1658.1764 | G60: =$B$3 -> 0.45 | I60: 2000 | J60: =IF(I60="","",(I60-E60)/I60) -> 0.5440015 | K60: =IF(I60="","",(I60-F60)/F60) -> 0.20614432 | L60: =IF(OR(I60="",H60=""),"",I60-H60) | M60: =IF(I60="","⚪ SIN PROPUESTA",IF(I60<F60*0.95,"🔴 BAJO PISO",IF(I60>F60*1.05,"🟢 SOBRE PISO","🟡 EN PISO"))) -> 🟢 SOBRE PISO | N60: {=IFERROR(_xlfn.SWITCH(B60,"1 L",1,"5 L",2,"5 L (VECA)",2.5,"20 L",3,"200 L",4,"250 GR",5,"500 GR",6,"1000 L",7),99)} -> 7
A61: AV PLUS CALCIO | B61: 1 L | C61: 3110 | D61: 1 | E61: =C61/D61 -> 3110 | F61: =E61/(1-$B$3) -> 5654.5455 | G61: =$B$3 -> 0.45 | H61: 5806 | I61: 6000 | J61: =IF(I61="","",(I61-E61)/I61) -> 0.48166667 | K61: =IF(I61="","",(I61-F61)/F61) -> 0.061093248 | L61: =IF(OR(I61="",H61=""),"",I61-H61) -> 194 | M61: =IF(I61="","⚪ SIN PROPUESTA",IF(I61<F61*0.95,"🔴 BAJO PISO",IF(I61>F61*1.05,"🟢 SOBRE PISO","🟡 EN PISO"))) -> 🟢 SOBRE PISO | N61: {=IFERROR(_xlfn.SWITCH(B61,"1 L",1,"5 L",2,"5 L (VECA)",2.5,"20 L",3,"200 L",4,"250 GR",5,"500 GR",6,"1000 L",7),99)} -> 1
A62: AV PLUS CALCIO | B62: 5 L | C62: 9971 | D62: 5 | E62: =C62/D62 -> 1994.2 | F62: =E62/(1-$B$3) -> 3625.8182 | G62: =$B$3 -> 0.45 | H62: 4193 | I62: 5000 | J62: =IF(I62="","",(I62-E62)/I62) -> 0.60116 | K62: =IF(I62="","",(I62-F62)/F62) -> 0.3789991 | L62: =IF(OR(I62="",H62=""),"",I62-H62) -> 807 | M62: =IF(I62="","⚪ SIN PROPUESTA",IF(I62<F62*0.95,"🔴 BAJO PISO",IF(I62>F62*1.05,"🟢 SOBRE PISO","🟡 EN PISO"))) -> 🟢 SOBRE PISO | N62: {=IFERROR(_xlfn.SWITCH(B62,"1 L",1,"5 L",2,"5 L (VECA)",2.5,"20 L",3,"200 L",4,"250 GR",5,"500 GR",6,"1000 L",7),99)} -> 2
A63: AV PLUS CALCIO | B63: 20 L | C63: 25543 | D63: 20 | E63: =C63/D63 -> 1277.15 | F63: =E63/(1-$B$3) -> 2322.0909 | G63: =$B$3 -> 0.45 | H63: 4177 | I63: 4000 | J63: =IF(I63="","",(I63-E63)/I63) -> 0.6807125 | K63: =IF(I63="","",(I63-F63)/F63) -> 0.72258544 | L63: =IF(OR(I63="",H63=""),"",I63-H63) -> -177 | M63: =IF(I63="","⚪ SIN PROPUESTA",IF(I63<F63*0.95,"🔴 BAJO PISO",IF(I63>F63*1.05,"🟢 SOBRE PISO","🟡 EN PISO"))) -> 🟢 SOBRE PISO | N63: {=IFERROR(_xlfn.SWITCH(B63,"1 L",1,"5 L",2,"5 L (VECA)",2.5,"20 L",3,"200 L",4,"250 GR",5,"500 GR",6,"1000 L",7),99)} -> 3
A64: AV PLUS CALCIO | B64: 200 L | C64: 199124 | D64: 200 | E64: =IF(C64="","",C64/D64) -> 995.62 | F64: =IF(E64="","",E64/(1-$B$3)) -> 1810.2182 | G64: =$B$3 -> 0.45 | I64: 3000 | J64: =IF(I64="","",(I64-E64)/I64) -> 0.66812667 | K64: =IF(I64="","",(I64-F64)/F64) -> 0.65725879 | L64: =IF(OR(I64="",H64=""),"",I64-H64) | M64: =IF(I64="","⚪ SIN PROPUESTA",IF(I64<F64*0.95,"🔴 BAJO PISO",IF(I64>F64*1.05,"🟢 SOBRE PISO","🟡 EN PISO"))) -> 🟢 SOBRE PISO | N64: {=IFERROR(_xlfn.SWITCH(B64,"1 L",1,"5 L",2,"5 L (VECA)",2.5,"20 L",3,"200 L",4,"250 GR",5,"500 GR",6,"1000 L",7),99)} -> 4
A65: AV PLUS CALCIO | B65: 1000 L | C65: 932488 | D65: 1000 | E65: =IF(C65="","",C65/D65) -> 932.488 | F65: =IF(E65="","",E65/(1-$B$3)) -> 1695.4327 | G65: =$B$3 -> 0.45 | I65: 2000 | J65: =IF(I65="","",(I65-E65)/I65) -> 0.533756 | K65: =IF(I65="","",(I65-F65)/F65) -> 0.17963985 | L65: =IF(OR(I65="",H65=""),"",I65-H65) | M65: =IF(I65="","⚪ SIN PROPUESTA",IF(I65<F65*0.95,"🔴 BAJO PISO",IF(I65>F65*1.05,"🟢 SOBRE PISO","🟡 EN PISO"))) -> 🟢 SOBRE PISO | N65: {=IFERROR(_xlfn.SWITCH(B65,"1 L",1,"5 L",2,"5 L (VECA)",2.5,"20 L",3,"200 L",4,"250 GR",5,"500 GR",6,"1000 L",7),99)} -> 7
A66: AV PLUS CALCIO BORO | B66: 1 L | C66: 3194 | D66: 1 | E66: =C66/D66 -> 3194 | F66: =E66/(1-$B$3) -> 5807.2727 | G66: =$B$3 -> 0.45 | H66: 6557 | I66: 7500 | J66: =IF(I66="","",(I66-E66)/I66) -> 0.57413333 | K66: =IF(I66="","",(I66-F66)/F66) -> 0.29148403 | L66: =IF(OR(I66="",H66=""),"",I66-H66) -> 943 | M66: =IF(I66="","⚪ SIN PROPUESTA",IF(I66<F66*0.95,"🔴 BAJO PISO",IF(I66>F66*1.05,"🟢 SOBRE PISO","🟡 EN PISO"))) -> 🟢 SOBRE PISO | N66: {=IFERROR(_xlfn.SWITCH(B66,"1 L",1,"5 L",2,"5 L (VECA)",2.5,"20 L",3,"200 L",4,"250 GR",5,"500 GR",6,"1000 L",7),99)} -> 1
A67: AV PLUS CALCIO BORO | B67: 5 L | C67: 10388 | D67: 5 | E67: =C67/D67 -> 2077.6 | F67: =E67/(1-$B$3) -> 3777.4545 | G67: =$B$3 -> 0.45 | H67: 5340 | I67: 6000 | J67: =IF(I67="","",(I67-E67)/I67) -> 0.65373333 | K67: =IF(I67="","",(I67-F67)/F67) -> 0.5883712 | L67: =IF(OR(I67="",H67=""),"",I67-H67) -> 660 | M67: =IF(I67="","⚪ SIN PROPUESTA",IF(I67<F67*0.95,"🔴 BAJO PISO",IF(I67>F67*1.05,"🟢 SOBRE PISO","🟡 EN PISO"))) -> 🟢 SOBRE PISO | N67: {=IFERROR(_xlfn.SWITCH(B67,"1 L",1,"5 L",2,"5 L (VECA)",2.5,"20 L",3,"200 L",4,"250 GR",5,"500 GR",6,"1000 L",7),99)} -> 2
A68: AV PLUS CALCIO BORO | B68: 20 L | C68: 27211 | D68: 20 | E68: =C68/D68 -> 1360.55 | F68: =E68/(1-$B$3) -> 2473.7273 | G68: =$B$3 -> 0.45 | H68: 5270 | I68: 5000 | J68: =IF(I68="","",(I68-E68)/I68) -> 0.72789 | K68: =IF(I68="","",(I68-F68)/F68) -> 1.0212414 | L68: =IF(OR(I68="",H68=""),"",I68-H68) -> -270 | M68: =IF(I68="","⚪ SIN PROPUESTA",IF(I68<F68*0.95,"🔴 BAJO PISO",IF(I68>F68*1.05,"🟢 SOBRE PISO","🟡 EN PISO"))) -> 🟢 SOBRE PISO | N68: {=IFERROR(_xlfn.SWITCH(B68,"1 L",1,"5 L",2,"5 L (VECA)",2.5,"20 L",3,"200 L",4,"250 GR",5,"500 GR",6,"1000 L",7),99)} -> 3
A69: AV PLUS CALCIO BORO | B69: 200 L | C69: 215805 | D69: 200 | E69: =IF(C69="","",C69/D69) -> 1079.025 | F69: =IF(E69="","",E69/(1-$B$3)) -> 1961.8636 | G69: =$B$3 -> 0.45 | I69: 4000 | J69: =IF(I69="","",(I69-E69)/I69) -> 0.73024375 | K69: =IF(I69="","",(I69-F69)/F69) -> 1.0388777 | L69: =IF(OR(I69="",H69=""),"",I69-H69) | M69: =IF(I69="","⚪ SIN PROPUESTA",IF(I69<F69*0.95,"🔴 BAJO PISO",IF(I69>F69*1.05,"🟢 SOBRE PISO","🟡 EN PISO"))) -> 🟢 SOBRE PISO | N69: {=IFERROR(_xlfn.SWITCH(B69,"1 L",1,"5 L",2,"5 L (VECA)",2.5,"20 L",3,"200 L",4,"250 GR",5,"500 GR",6,"1000 L",7),99)} -> 4
A70: AV PLUS CALCIO BORO | B70: 1000 L | C70: 1015893 | D70: 1000 | E70: =IF(C70="","",C70/D70) -> 1015.893 | F70: =IF(E70="","",E70/(1-$B$3)) -> 1847.0782 | G70: =$B$3 -> 0.45 | I70: 3000 | J70: =IF(I70="","",(I70-E70)/I70) -> 0.661369 | K70: =IF(I70="","",(I70-F70)/F70) -> 0.6241868 | L70: =IF(OR(I70="",H70=""),"",I70-H70) | M70: =IF(I70="","⚪ SIN PROPUESTA",IF(I70<F70*0.95,"🔴 BAJO PISO",IF(I70>F70*1.05,"🟢 SOBRE PISO","🟡 EN PISO"))) -> 🟢 SOBRE PISO | N70: {=IFERROR(_xlfn.SWITCH(B70,"1 L",1,"5 L",2,"5 L (VECA)",2.5,"20 L",3,"200 L",4,"250 GR",5,"500 GR",6,"1000 L",7),99)} -> 7
A71: AV PLUS HIERRO | B71: 1 L | C71: 3154 | D71: 1 | E71: =C71/D71 -> 3154 | F71: =E71/(1-$B$3) -> 5734.5455 | G71: =$B$3 -> 0.45 | H71: 8150 | I71: 8000 | J71: =IF(I71="","",(I71-E71)/I71) -> 0.60575 | K71: =IF(I71="","",(I71-F71)/F71) -> 0.3950539 | L71: =IF(OR(I71="",H71=""),"",I71-H71) -> -150 | M71: =IF(I71="","⚪ SIN PROPUESTA",IF(I71<F71*0.95,"🔴 BAJO PISO",IF(I71>F71*1.05,"🟢 SOBRE PISO","🟡 EN PISO"))) -> 🟢 SOBRE PISO | N71: {=IFERROR(_xlfn.SWITCH(B71,"1 L",1,"5 L",2,"5 L (VECA)",2.5,"20 L",3,"200 L",4,"250 GR",5,"500 GR",6,"1000 L",7),99)} -> 1
A72: AV PLUS HIERRO | B72: 5 L | C72: 10190 | D72: 5 | E72: =C72/D72 -> 2038 | F72: =E72/(1-$B$3) -> 3705.4545 | G72: =$B$3 -> 0.45 | H72: 3540 | I72: 6800 | J72: =IF(I72="","",(I72-E72)/I72) -> 0.70029412 | K72: =IF(I72="","",(I72-F72)/F72) -> 0.83513248 | L72: =IF(OR(I72="",H72=""),"",I72-H72) -> 3260 | M72: =IF(I72="","⚪ SIN PROPUESTA",IF(I72<F72*0.95,"🔴 BAJO PISO",IF(I72>F72*1.05,"🟢 SOBRE PISO","🟡 EN PISO"))) -> 🟢 SOBRE PISO | N72: {=IFERROR(_xlfn.SWITCH(B72,"1 L",1,"5 L",2,"5 L (VECA)",2.5,"20 L",3,"200 L",4,"250 GR",5,"500 GR",6,"1000 L",7),99)} -> 2
A73: AV PLUS HIERRO | B73: 20 L | C73: 26419 | D73: 20 | E73: =IF(C73="","",C73/D73) -> 1320.95 | F73: =IF(E73="","",E73/(1-$B$3)) -> 2401.7273 | G73: =$B$3 -> 0.45 | I73: 5000 | J73: =IF(I73="","",(I73-E73)/I73) -> 0.73581 | K73: =IF(I73="","",(I73-F73)/F73) -> 1.081835 | L73: =IF(OR(I73="",H73=""),"",I73-H73) | M73: =IF(I73="","⚪ SIN PROPUESTA",IF(I73<F73*0.95,"🔴 BAJO PISO",IF(I73>F73*1.05,"🟢 SOBRE PISO","🟡 EN PISO"))) -> 🟢 SOBRE PISO | N73: {=IFERROR(_xlfn.SWITCH(B73,"1 L",1,"5 L",2,"5 L (VECA)",2.5,"20 L",3,"200 L",4,"250 GR",5,"500 GR",6,"1000 L",7),99)} -> 3
A74: AV PLUS HIERRO | B74: 200 L | C74: 207883 | D74: 200 | E74: =IF(C74="","",C74/D74) -> 1039.415 | F74: =IF(E74="","",E74/(1-$B$3)) -> 1889.8455 | G74: =$B$3 -> 0.45 | I74: 4000 | J74: =IF(I74="","",(I74-E74)/I74) -> 0.74014625 | K74: =IF(I74="","",(I74-F74)/F74) -> 1.1165752 | L74: =IF(OR(I74="",H74=""),"",I74-H74) | M74: =IF(I74="","⚪ SIN PROPUESTA",IF(I74<F74*0.95,"🔴 BAJO PISO",IF(I74>F74*1.05,"🟢 SOBRE PISO","🟡 EN PISO"))) -> 🟢 SOBRE PISO | N74: {=IFERROR(_xlfn.SWITCH(B74,"1 L",1,"5 L",2,"5 L (VECA)",2.5,"20 L",3,"200 L",4,"250 GR",5,"500 GR",6,"1000 L",7),99)} -> 4
A75: AV PLUS HIERRO | B75: 1000 L | C75: 976283 | D75: 1000 | E75: =IF(C75="","",C75/D75) -> 976.283 | F75: =IF(E75="","",E75/(1-$B$3)) -> 1775.06 | G75: =$B$3 -> 0.45 | I75: 3000 | J75: =IF(I75="","",(I75-E75)/I75) -> 0.67457233 | K75: =IF(I75="","",(I75-F75)/F75) -> 0.69008372 | L75: =IF(OR(I75="",H75=""),"",I75-H75) | M75: =IF(I75="","⚪ SIN PROPUESTA",IF(I75<F75*0.95,"🔴 BAJO PISO",IF(I75>F75*1.05,"🟢 SOBRE PISO","🟡 EN PISO"))) -> 🟢 SOBRE PISO | N75: {=IFERROR(_xlfn.SWITCH(B75,"1 L",1,"5 L",2,"5 L (VECA)",2.5,"20 L",3,"200 L",4,"250 GR",5,"500 GR",6,"1000 L",7),99)} -> 7
A76: AV PLUS MACRO FRUIT | B76: 1 L | C76: 3931 | D76: 1 | E76: =C76/D76 -> 3931 | F76: =E76/(1-$B$3) -> 7147.2727 | G76: =$B$3 -> 0.45 | I76: 8000 | J76: =IF(I76="","",(I76-E76)/I76) -> 0.508625 | K76: =IF(I76="","",(I76-F76)/F76) -> 0.11930806 | L76: =IF(OR(I76="",H76=""),"",I76-H76) | M76: =IF(I76="","⚪ SIN PROPUESTA",IF(I76<F76*0.95,"🔴 BAJO PISO",IF(I76>F76*1.05,"🟢 SOBRE PISO","🟡 EN PISO"))) -> 🟢 SOBRE PISO | N76: {=IFERROR(_xlfn.SWITCH(B76,"1 L",1,"5 L",2,"5 L (VECA)",2.5,"20 L",3,"200 L",4,"250 GR",5,"500 GR",6,"1000 L",7),99)} -> 1
A77: AV PLUS MACRO FRUIT | B77: 5 L | C77: 14073 | D77: 5 | E77: =C77/D77 -> 2814.6 | F77: =E77/(1-$B$3) -> 5117.4545 | G77: =$B$3 -> 0.45 | I77: 6800 | J77: =IF(I77="","",(I77-E77)/I77) -> 0.58608824 | K77: =IF(I77="","",(I77-F77)/F77) -> 0.32878562 | L77: =IF(OR(I77="",H77=""),"",I77-H77) | M77: =IF(I77="","⚪ SIN PROPUESTA",IF(I77<F77*0.95,"🔴 BAJO PISO",IF(I77>F77*1.05,"🟢 SOBRE PISO","🟡 EN PISO"))) -> 🟢 SOBRE PISO | N77: {=IFERROR(_xlfn.SWITCH(B77,"1 L",1,"5 L",2,"5 L (VECA)",2.5,"20 L",3,"200 L",4,"250 GR",5,"500 GR",6,"1000 L",7),99)} -> 2
A78: AV PLUS MACRO FRUIT | B78: 20 L | C78: 41951 | D78: 20 | E78: =C78/D78 -> 2097.55 | F78: =E78/(1-$B$3) -> 3813.7273 | G78: =$B$3 -> 0.45 | I78: 5500 | J78: =IF(I78="","",(I78-E78)/I78) -> 0.61862727 | K78: =IF(I78="","",(I78-F78)/F78) -> 0.44215871 | L78: =IF(OR(I78="",H78=""),"",I78-H78) | M78: =IF(I78="","⚪ SIN PROPUESTA",IF(I78<F78*0.95,"🔴 BAJO PISO",IF(I78>F78*1.05,"🟢 SOBRE PISO","🟡 EN PISO"))) -> 🟢 SOBRE PISO | N78: {=IFERROR(_xlfn.SWITCH(B78,"1 L",1,"5 L",2,"5 L (VECA)",2.5,"20 L",3,"200 L",4,"250 GR",5,"500 GR",6,"1000 L",7),99)} -> 3
A79: AV PLUS MACRO FRUIT | B79: 200 L | C79: 363198 | D79: 200 | E79: =IF(C79="","",C79/D79) -> 1815.99 | F79: =IF(E79="","",E79/(1-$B$3)) -> 3301.8 | G79: =$B$3 -> 0.45 | I79: 4500 | J79: =IF(I79="","",(I79-E79)/I79) -> 0.59644667 | K79: =IF(I79="","",(I79-F79)/F79) -> 0.36289297 | L79: =IF(OR(I79="",H79=""),"",I79-H79) | M79: =IF(I79="","⚪ SIN PROPUESTA",IF(I79<F79*0.95,"🔴 BAJO PISO",IF(I79>F79*1.05,"🟢 SOBRE PISO","🟡 EN PISO"))) -> 🟢 SOBRE PISO | N79: {=IFERROR(_xlfn.SWITCH(B79,"1 L",1,"5 L",2,"5 L (VECA)",2.5,"20 L",3,"200 L",4,"250 GR",5,"500 GR",6,"1000 L",7),99)} -> 4
A80: AV PLUS MACRO FRUIT | B80: 1000 L | C80: 1752858 | D80: 1000 | E80: =IF(C80="","",C80/D80) -> 1752.858 | F80: =IF(E80="","",E80/(1-$B$3)) -> 3187.0145 | G80: =$B$3 -> 0.45 | I80: 3500 | J80: =IF(I80="","",(I80-E80)/I80) -> 0.49918343 | K80: =IF(I80="","",(I80-F80)/F80) -> 0.098206472 | L80: =IF(OR(I80="",H80=""),"",I80-H80) | M80: =IF(I80="","⚪ SIN PROPUESTA",IF(I80<F80*0.95,"🔴 BAJO PISO",IF(I80>F80*1.05,"🟢 SOBRE PISO","🟡 EN PISO"))) -> 🟢 SOBRE PISO | N80: {=IFERROR(_xlfn.SWITCH(B80,"1 L",1,"5 L",2,"5 L (VECA)",2.5,"20 L",3,"200 L",4,"250 GR",5,"500 GR",6,"1000 L",7),99)} -> 7
A81: AV PLUS MAGNESIO | B81: 1 L | C81: 3278 | D81: 1 | E81: =C81/D81 -> 3278 | F81: =E81/(1-$B$3) -> 5960 | G81: =$B$3 -> 0.45 | H81: 4446 | I81: 6000 | J81: =IF(I81="","",(I81-E81)/I81) -> 0.45366667 | K81: =IF(I81="","",(I81-F81)/F81) -> 0.0067114094 | L81: =IF(OR(I81="",H81=""),"",I81-H81) -> 1554 | M81: =IF(I81="","⚪ SIN PROPUESTA",IF(I81<F81*0.95,"🔴 BAJO PISO",IF(I81>F81*1.05,"🟢 SOBRE PISO","🟡 EN PISO"))) -> 🟡 EN PISO | N81: {=IFERROR(_xlfn.SWITCH(B81,"1 L",1,"5 L",2,"5 L (VECA)",2.5,"20 L",3,"200 L",4,"250 GR",5,"500 GR",6,"1000 L",7),99)} -> 1
A82: AV PLUS MAGNESIO | B82: 5 L | C82: 10809 | D82: 5 | E82: =C82/D82 -> 2161.8 | F82: =E82/(1-$B$3) -> 3930.5455 | G82: =$B$3 -> 0.45 | H82: 3956 | I82: 4000 | J82: =IF(I82="","",(I82-E82)/I82) -> 0.45955 | K82: =IF(I82="","",(I82-F82)/F82) -> 0.01767046 | L82: =IF(OR(I82="",H82=""),"",I82-H82) -> 44 | M82: =IF(I82="","⚪ SIN PROPUESTA",IF(I82<F82*0.95,"🔴 BAJO PISO",IF(I82>F82*1.05,"🟢 SOBRE PISO","🟡 EN PISO"))) -> 🟡 EN PISO | N82: {=IFERROR(_xlfn.SWITCH(B82,"1 L",1,"5 L",2,"5 L (VECA)",2.5,"20 L",3,"200 L",4,"250 GR",5,"500 GR",6,"1000 L",7),99)} -> 2
A83: AV PLUS MAGNESIO | B83: 20 L | C83: 28894 | D83: 20 | E83: =C83/D83 -> 1444.7 | F83: =E83/(1-$B$3) -> 2626.7273 | G83: =$B$3 -> 0.45 | H83: 3110 | I83: 3200 | J83: =IF(I83="","",(I83-E83)/I83) -> 0.54853125 | K83: =IF(I83="","",(I83-F83)/F83) -> 0.218246 | L83: =IF(OR(I83="",H83=""),"",I83-H83) -> 90 | M83: =IF(I83="","⚪ SIN PROPUESTA",IF(I83<F83*0.95,"🔴 BAJO PISO",IF(I83>F83*1.05,"🟢 SOBRE PISO","🟡 EN PISO"))) -> 🟢 SOBRE PISO | N83: {=IFERROR(_xlfn.SWITCH(B83,"1 L",1,"5 L",2,"5 L (VECA)",2.5,"20 L",3,"200 L",4,"250 GR",5,"500 GR",6,"1000 L",7),99)} -> 3
A84: AV PLUS MAGNESIO | B84: 200 L | C84: 232630 | D84: 200 | E84: =IF(C84="","",C84/D84) -> 1163.15 | F84: =IF(E84="","",E84/(1-$B$3)) -> 2114.8182 | G84: =$B$3 -> 0.45 | I84: 2800 | J84: =IF(I84="","",(I84-E84)/I84) -> 0.58458929 | K84: =IF(I84="","",(I84-F84)/F84) -> 0.32399089 | L84: =IF(OR(I84="",H84=""),"",I84-H84) | M84: =IF(I84="","⚪ SIN PROPUESTA",IF(I84<F84*0.95,"🔴 BAJO PISO",IF(I84>F84*1.05,"🟢 SOBRE PISO","🟡 EN PISO"))) -> 🟢 SOBRE PISO | N84: {=IFERROR(_xlfn.SWITCH(B84,"1 L",1,"5 L",2,"5 L (VECA)",2.5,"20 L",3,"200 L",4,"250 GR",5,"500 GR",6,"1000 L",7),99)} -> 4
A85: AV PLUS MAGNESIO | B85: 1000 L | C85: 1100020 | D85: 1000 | E85: =IF(C85="","",C85/D85) -> 1100.02 | F85: =IF(E85="","",E85/(1-$B$3)) -> 2000.0364 | G85: =$B$3 -> 0.45 | I85: 2200 | J85: =IF(I85="","",(I85-E85)/I85) -> 0.49999091 | K85: =IF(I85="","",(I85-F85)/F85) -> 0.09998 | L85: =IF(OR(I85="",H85=""),"",I85-H85) | M85: =IF(I85="","⚪ SIN PROPUESTA",IF(I85<F85*0.95,"🔴 BAJO PISO",IF(I85>F85*1.05,"🟢 SOBRE PISO","🟡 EN PISO"))) -> 🟢 SOBRE PISO | N85: {=IFERROR(_xlfn.SWITCH(B85,"1 L",1,"5 L",2,"5 L (VECA)",2.5,"20 L",3,"200 L",4,"250 GR",5,"500 GR",6,"1000 L",7),99)} -> 7
A86: AV PLUS MICRO MIX | B86: 1 L | C86: 4366 | D86: 1 | E86: =C86/D86 -> 4366 | F86: =E86/(1-$B$3) -> 7938.1818 | G86: =$B$3 -> 0.45 | H86: 7028 | I86: 8000 | J86: =IF(I86="","",(I86-E86)/I86) -> 0.45425 | K86: =IF(I86="","",(I86-F86)/F86) -> 0.0077874485 | L86: =IF(OR(I86="",H86=""),"",I86-H86) -> 972 | M86: =IF(I86="","⚪ SIN PROPUESTA",IF(I86<F86*0.95,"🔴 BAJO PISO",IF(I86>F86*1.05,"🟢 SOBRE PISO","🟡 EN PISO"))) -> 🟡 EN PISO | N86: {=IFERROR(_xlfn.SWITCH(B86,"1 L",1,"5 L",2,"5 L (VECA)",2.5,"20 L",3,"200 L",4,"250 GR",5,"500 GR",6,"1000 L",7),99)} -> 1
A87: AV PLUS MICRO MIX | B87: 5 L | C87: 16249 | D87: 5 | E87: =C87/D87 -> 3249.8 | F87: =E87/(1-$B$3) -> 5908.7273 | G87: =$B$3 -> 0.45 | H87: 5653 | I87: 6500 | J87: =IF(I87="","",(I87-E87)/I87) -> 0.50003077 | K87: =IF(I87="","",(I87-F87)/F87) -> 0.1000677 | L87: =IF(OR(I87="",H87=""),"",I87-H87) -> 847 | M87: =IF(I87="","⚪ SIN PROPUESTA",IF(I87<F87*0.95,"🔴 BAJO PISO",IF(I87>F87*1.05,"🟢 SOBRE PISO","🟡 EN PISO"))) -> 🟢 SOBRE PISO | N87: {=IFERROR(_xlfn.SWITCH(B87,"1 L",1,"5 L",2,"5 L (VECA)",2.5,"20 L",3,"200 L",4,"250 GR",5,"500 GR",6,"1000 L",7),99)} -> 2
A88: AV PLUS MICRO MIX | B88: 20 L | C88: 50656 | D88: 20 | E88: =C88/D88 -> 2532.8 | F88: =E88/(1-$B$3) -> 4605.0909 | G88: =$B$3 -> 0.45 | H88: 5236 | I88: 5500 | J88: =IF(I88="","",(I88-E88)/I88) -> 0.53949091 | K88: =IF(I88="","",(I88-F88)/F88) -> 0.19433039 | L88: =IF(OR(I88="",H88=""),"",I88-H88) -> 264 | M88: =IF(I88="","⚪ SIN PROPUESTA",IF(I88<F88*0.95,"🔴 BAJO PISO",IF(I88>F88*1.05,"🟢 SOBRE PISO","🟡 EN PISO"))) -> 🟢 SOBRE PISO | N88: {=IFERROR(_xlfn.SWITCH(B88,"1 L",1,"5 L",2,"5 L (VECA)",2.5,"20 L",3,"200 L",4,"250 GR",5,"500 GR",6,"1000 L",7),99)} -> 3
A89: AV PLUS MICRO MIX | B89: 200 L | C89: 450254 | D89: 200 | E89: =C89/D89 -> 2251.27 | F89: =E89/(1-$B$3) -> 4093.2182 | G89: =$B$3 -> 0.45 | H89: 4500 | I89: 4500 | J89: =IF(I89="","",(I89-E89)/I89) -> 0.49971778 | K89: =IF(I89="","",(I89-F89)/F89) -> 0.099379461 | L89: =IF(OR(I89="",H89=""),"",I89-H89) -> 0 | M89: =IF(I89="","⚪ SIN PROPUESTA",IF(I89<F89*0.95,"🔴 BAJO PISO",IF(I89>F89*1.05,"🟢 SOBRE PISO","🟡 EN PISO"))) -> 🟢 SOBRE PISO | N89: {=IFERROR(_xlfn.SWITCH(B89,"1 L",1,"5 L",2,"5 L (VECA)",2.5,"20 L",3,"200 L",4,"250 GR",5,"500 GR",6,"1000 L",7),99)} -> 4
A90: AV PLUS MICRO MIX | B90: 1000 L | C90: 2188140 | D90: 1000 | E90: =IF(C90="","",C90/D90) -> 2188.14 | F90: =IF(E90="","",E90/(1-$B$3)) -> 3978.4364 | G90: =$B$3 -> 0.45 | I90: 4000 | J90: =IF(I90="","",(I90-E90)/I90) -> 0.452965 | K90: =IF(I90="","",(I90-F90)/F90) -> 0.0054201285 | L90: =IF(OR(I90="",H90=""),"",I90-H90) | M90: =IF(I90="","⚪ SIN PROPUESTA",IF(I90<F90*0.95,"🔴 BAJO PISO",IF(I90>F90*1.05,"🟢 SOBRE PISO","🟡 EN PISO"))) -> 🟡 EN PISO | N90: {=IFERROR(_xlfn.SWITCH(B90,"1 L",1,"5 L",2,"5 L (VECA)",2.5,"20 L",3,"200 L",4,"250 GR",5,"500 GR",6,"1000 L",7),99)} -> 7
A91: AV PLUS NP-MIX | B91: 1 L | C91: 4666 | D91: 1 | E91: =C91/D91 -> 4666 | F91: =E91/(1-$B$3) -> 8483.6364 | G91: =$B$3 -> 0.45 | H91: 7175 | I91: 8000 | J91: =IF(I91="","",(I91-E91)/I91) -> 0.41675 | K91: =IF(I91="","",(I91-F91)/F91) -> -0.057008144 | L91: =IF(OR(I91="",H91=""),"",I91-H91) -> 825 | M91: =IF(I91="","⚪ SIN PROPUESTA",IF(I91<F91*0.95,"🔴 BAJO PISO",IF(I91>F91*1.05,"🟢 SOBRE PISO","🟡 EN PISO"))) -> 🔴 BAJO PISO | N91: {=IFERROR(_xlfn.SWITCH(B91,"1 L",1,"5 L",2,"5 L (VECA)",2.5,"20 L",3,"200 L",4,"250 GR",5,"500 GR",6,"1000 L",7),99)} -> 1
A92: AV PLUS NP-MIX | B92: 5 L | C92: 17752 | D92: 5 | E92: =IF(C92="","",C92/D92) -> 3550.4 | F92: =IF(E92="","",E92/(1-$B$3)) -> 6455.2727 | G92: =$B$3 -> 0.45 | I92: 7000 | J92: =IF(I92="","",(I92-E92)/I92) -> 0.4928 | K92: =IF(I92="","",(I92-F92)/F92) -> 0.084384858 | L92: =IF(OR(I92="",H92=""),"",I92-H92) | M92: =IF(I92="","⚪ SIN PROPUESTA",IF(I92<F92*0.95,"🔴 BAJO PISO",IF(I92>F92*1.05,"🟢 SOBRE PISO","🟡 EN PISO"))) -> 🟢 SOBRE PISO | N92: {=IFERROR(_xlfn.SWITCH(B92,"1 L",1,"5 L",2,"5 L (VECA)",2.5,"20 L",3,"200 L",4,"250 GR",5,"500 GR",6,"1000 L",7),99)} -> 2
A93: AV PLUS NP-MIX | B93: 20 L | C93: 56668 | D93: 20 | E93: =IF(C93="","",C93/D93) -> 2833.4 | F93: =IF(E93="","",E93/(1-$B$3)) -> 5151.6364 | G93: =$B$3 -> 0.45 | I93: 6000 | J93: =IF(I93="","",(I93-E93)/I93) -> 0.52776667 | K93: =IF(I93="","",(I93-F93)/F93) -> 0.16467848 | L93: =IF(OR(I93="",H93=""),"",I93-H93) | M93: =IF(I93="","⚪ SIN PROPUESTA",IF(I93<F93*0.95,"🔴 BAJO PISO",IF(I93>F93*1.05,"🟢 SOBRE PISO","🟡 EN PISO"))) -> 🟢 SOBRE PISO | N93: {=IFERROR(_xlfn.SWITCH(B93,"1 L",1,"5 L",2,"5 L (VECA)",2.5,"20 L",3,"200 L",4,"250 GR",5,"500 GR",6,"1000 L",7),99)} -> 3
A94: AV PLUS NP-MIX | B94: 200 L | C94: 510365 | D94: 200 | E94: =IF(C94="","",C94/D94) -> 2551.825 | F94: =IF(E94="","",E94/(1-$B$3)) -> 4639.6818 | G94: =$B$3 -> 0.45 | I94: 5000 | J94: =IF(I94="","",(I94-E94)/I94) -> 0.489635 | K94: =IF(I94="","",(I94-F94)/F94) -> 0.077660106 | L94: =IF(OR(I94="",H94=""),"",I94-H94) | M94: =IF(I94="","⚪ SIN PROPUESTA",IF(I94<F94*0.95,"🔴 BAJO PISO",IF(I94>F94*1.05,"🟢 SOBRE PISO","🟡 EN PISO"))) -> 🟢 SOBRE PISO | N94: {=IFERROR(_xlfn.SWITCH(B94,"1 L",1,"5 L",2,"5 L (VECA)",2.5,"20 L",3,"200 L",4,"250 GR",5,"500 GR",6,"1000 L",7),99)} -> 4
A95: AV PLUS NP-MIX | B95: 1000 L | C95: 2488696 | D95: 1000 | E95: =IF(C95="","",C95/D95) -> 2488.696 | F95: =IF(E95="","",E95/(1-$B$3)) -> 4524.9018 | G95: =$B$3 -> 0.45 | I95: 4800 | J95: =IF(I95="","",(I95-E95)/I95) -> 0.48152167 | K95: =IF(I95="","",(I95-F95)/F95) -> 0.060796497 | L95: =IF(OR(I95="",H95=""),"",I95-H95) | M95: =IF(I95="","⚪ SIN PROPUESTA",IF(I95<F95*0.95,"🔴 BAJO PISO",IF(I95>F95*1.05,"🟢 SOBRE PISO","🟡 EN PISO"))) -> 🟢 SOBRE PISO | N95: {=IFERROR(_xlfn.SWITCH(B95,"1 L",1,"5 L",2,"5 L (VECA)",2.5,"20 L",3,"200 L",4,"250 GR",5,"500 GR",6,"1000 L",7),99)} -> 7
A96: AV PLUS NUTRI MIX | B96: 1 L | C96: 4047 | D96: 1 | E96: =C96/D96 -> 4047 | F96: =E96/(1-$B$3) -> 7358.1818 | G96: =$B$3 -> 0.45 | H96: 6927 | I96: 8000 | J96: =IF(I96="","",(I96-E96)/I96) -> 0.494125 | K96: =IF(I96="","",(I96-F96)/F96) -> 0.087225105 | L96: =IF(OR(I96="",H96=""),"",I96-H96) -> 1073 | M96: =IF(I96="","⚪ SIN PROPUESTA",IF(I96<F96*0.95,"🔴 BAJO PISO",IF(I96>F96*1.05,"🟢 SOBRE PISO","🟡 EN PISO"))) -> 🟢 SOBRE PISO | N96: {=IFERROR(_xlfn.SWITCH(B96,"1 L",1,"5 L",2,"5 L (VECA)",2.5,"20 L",3,"200 L",4,"250 GR",5,"500 GR",6,"1000 L",7),99)} -> 1
A97: AV PLUS NUTRI MIX | B97: 5 L | C97: 14657 | D97: 5 | E97: =C97/D97 -> 2931.4 | F97: =E97/(1-$B$3) -> 5329.8182 | G97: =$B$3 -> 0.45 | H97: 7000 | I97: 7200 | J97: =IF(I97="","",(I97-E97)/I97) -> 0.59286111 | K97: =IF(I97="","",(I97-F97)/F97) -> 0.35089036 | L97: =IF(OR(I97="",H97=""),"",I97-H97) -> 200 | M97: =IF(I97="","⚪ SIN PROPUESTA",IF(I97<F97*0.95,"🔴 BAJO PISO",IF(I97>F97*1.05,"🟢 SOBRE PISO","🟡 EN PISO"))) -> 🟢 SOBRE PISO | N97: {=IFERROR(_xlfn.SWITCH(B97,"1 L",1,"5 L",2,"5 L (VECA)",2.5,"20 L",3,"200 L",4,"250 GR",5,"500 GR",6,"1000 L",7),99)} -> 2
A98: AV PLUS NUTRI MIX | B98: 20 L | C98: 44287 | D98: 20 | E98: =IF(C98="","",C98/D98) -> 2214.35 | F98: =IF(E98="","",E98/(1-$B$3)) -> 4026.0909 | G98: =$B$3 -> 0.45 | I98: 6800 | J98: =IF(I98="","",(I98-E98)/I98) -> 0.67436029 | K98: =IF(I98="","",(I98-F98)/F98) -> 0.68898322 | L98: =IF(OR(I98="",H98=""),"",I98-H98) | M98: =IF(I98="","⚪ SIN PROPUESTA",IF(I98<F98*0.95,"🔴 BAJO PISO",IF(I98>F98*1.05,"🟢 SOBRE PISO","🟡 EN PISO"))) -> 🟢 SOBRE PISO | N98: {=IFERROR(_xlfn.SWITCH(B98,"1 L",1,"5 L",2,"5 L (VECA)",2.5,"20 L",3,"200 L",4,"250 GR",5,"500 GR",6,"1000 L",7),99)} -> 3
A99: AV PLUS NUTRI MIX | B99: 200 L | C99: 386562 | D99: 200 | E99: =IF(C99="","",C99/D99) -> 1932.81 | F99: =IF(E99="","",E99/(1-$B$3)) -> 3514.2 | G99: =$B$3 -> 0.45 | I99: 5500 | J99: =IF(I99="","",(I99-E99)/I99) -> 0.64858 | K99: =IF(I99="","",(I99-F99)/F99) -> 0.56507882 | L99: =IF(OR(I99="",H99=""),"",I99-H99) | M99: =IF(I99="","⚪ SIN PROPUESTA",IF(I99<F99*0.95,"🔴 BAJO PISO",IF(I99>F99*1.05,"🟢 SOBRE PISO","🟡 EN PISO"))) -> 🟢 SOBRE PISO | N99: {=IFERROR(_xlfn.SWITCH(B99,"1 L",1,"5 L",2,"5 L (VECA)",2.5,"20 L",3,"200 L",4,"250 GR",5,"500 GR",6,"1000 L",7),99)} -> 4
A100: AV PLUS NUTRI MIX | B100: 1000 L | C100: 1869680 | D100: 1000 | E100: =IF(C100="","",C100/D100) -> 1869.68 | F100: =IF(E100="","",E100/(1-$B$3)) -> 3399.4182 | G100: =$B$3 -> 0.45 | I100: 4000 | J100: =IF(I100="","",(I100-E100)/I100) -> 0.53258 | K100: =IF(I100="","",(I100-F100)/F100) -> 0.17667194 | L100: =IF(OR(I100="",H100=""),"",I100-H100) | M100: =IF(I100="","⚪ SIN PROPUESTA",IF(I100<F100*0.95,"🔴 BAJO PISO",IF(I100>F100*1.05,"🟢 SOBRE PISO","🟡 EN PISO"))) -> 🟢 SOBRE PISO | N100: {=IFERROR(_xlfn.SWITCH(B100,"1 L",1,"5 L",2,"5 L (VECA)",2.5,"20 L",3,"200 L",4,"250 GR",5,"500 GR",6,"1000 L",7),99)} -> 7
A101: AV PLUS POTASIO | B101: 1 L | C101: 3705 | D101: 1 | E101: =C101/D101 -> 3705 | F101: =E101/(1-$B$3) -> 6736.3636 | G101: =$B$3 -> 0.45 | H101: 5817 | I101: 6800 | J101: =IF(I101="","",(I101-E101)/I101) -> 0.45514706 | K101: =IF(I101="","",(I101-F101)/F101) -> 0.0094466937 | L101: =IF(OR(I101="",H101=""),"",I101-H101) -> 983 | M101: =IF(I101="","⚪ SIN PROPUESTA",IF(I101<F101*0.95,"🔴 BAJO PISO",IF(I101>F101*1.05,"🟢 SOBRE PISO","🟡 EN PISO"))) -> 🟡 EN PISO | N101: {=IFERROR(_xlfn.SWITCH(B101,"1 L",1,"5 L",2,"5 L (VECA)",2.5,"20 L",3,"200 L",4,"250 GR",5,"500 GR",6,"1000 L",7),99)} -> 1
...

Sheet Lista de precios
B1: LISTA DE PRECIOS PISO — FUERZA COMERCIAL CHILE 2026
B2: AGROVECA GRUPO LATAM | Precios mínimos de venta | Vigencia: Abril 2026 | Aprobado: Gerencia General
B3: ⚠️ Ninguna venta puede realizarse por debajo de estos precios sin autorización escrita de Gerencia General.
B4: PRODUCTO | C4: FORMATO | D4: Precio Piso AV
B5: ='Pricing Piso Chile'!A6 -> AV ALGAP 30 | C5: ='Pricing Piso Chile'!B6 -> 1 L | D5: ='Pricing Piso Chile'!I6 -> 6800
B6: ='Pricing Piso Chile'!A7 -> AV ALGAP 30 | C6: ='Pricing Piso Chile'!B7 -> 5 L | D6: ='Pricing Piso Chile'!I7 -> 5000
B7: ='Pricing Piso Chile'!A8 -> AV ALGAP 30 | C7: ='Pricing Piso Chile'!B8 -> 20 L | D7: ='Pricing Piso Chile'!I8 -> 4000
B8: ='Pricing Piso Chile'!A9 -> AV ALGAP 30 | C8: ='Pricing Piso Chile'!B9 -> 200 L | D8: ='Pricing Piso Chile'!I9 -> 3500
B9: ='Pricing Piso Chile'!A10 -> AV ALGAP 30 | C9: ='Pricing Piso Chile'!B10 -> 1000 L | D9: ='Pricing Piso Chile'!I10 -> 3000
B10: ='Pricing Piso Chile'!A11 -> AV AMIN | C10: ='Pricing Piso Chile'!B11 -> 1 L | D10: ='Pricing Piso Chile'!I11 -> 7800
B11: ='Pricing Piso Chile'!A12 -> AV AMIN | C11: ='Pricing Piso Chile'!B12 -> 5 L | D11: ='Pricing Piso Chile'!I12 -> 7000
B12: ='Pricing Piso Chile'!A13 -> AV AMIN | C12: ='Pricing Piso Chile'!B13 -> 20 L | D12: ='Pricing Piso Chile'!I13 -> 5500
B13: ='Pricing Piso Chile'!A14 -> AV AMIN | C13: ='Pricing Piso Chile'!B14 -> 200 L | D13: ='Pricing Piso Chile'!I14 -> 3500
B14: ='Pricing Piso Chile'!A15 -> AV AMIN | C14: ='Pricing Piso Chile'!B15 -> 1000 L | D14: ='Pricing Piso Chile'!I15 -> 3000
B15: ='Pricing Piso Chile'!A16 -> AV AMIN SUGAR | C15: ='Pricing Piso Chile'!B16 -> 1 L | D15: ='Pricing Piso Chile'!I16 -> 9000
B16: ='Pricing Piso Chile'!A17 -> AV AMIN SUGAR | C16: ='Pricing Piso Chile'!B17 -> 5 L | D16: ='Pricing Piso Chile'!I17 -> 8000
... B142: ='Pricing Piso Chile'!A143 -> GREEN GUARDIAN MAX | C142: ='Pricing Piso Chile'!B143 -> 1000 L | D142: ='Pricing Piso Chile'!I143 -> 3800
