Workbook

Sheet RESUMEN
A2: Suma de Total | B2: Etiquetas de columna
A3: Etiquetas de fila | B3: ENERO | C3: FEBRERO | D3: MARZO | E3: ABRIL | F3: Total general
A4: EN TERRENO 1 | E4: 0 | F4: 0
A5: FRANCISCO VELASQUEZ | B5: 14491000 | C5: 9912000 | D5: 5196500 | E5: 3113000 | F5: 32712500
A6: IVAN VEVERKA | B6: 6186000 | C6: 944000 | D6: 1680000 | F6: 8810000
A7: JORGE CAROCA | B7: 14820273 | C7: 6389076 | D7: 31913309 | E7: 10171393 | F7: 63294051
A8: LABORATORIO | B8: 0 | D8: 0 | F8: 0
A9: PABLO LARATRO | B9: 37027580 | C9: 10378585 | D9: 5487150 | E9: 8304645 | F9: 61197960
A10: RAYEN BERNAZAR | C10: 0 | D10: 0 | E10: 39826 | F10: 39826
A11: RODRIGO ENCINA | B11: 13510783 | C11: 7262717 | D11: 6819022 | E11: 1763157 | F11: 29355679
A12: VALENTINA MUÑOZ | B12: 2195728 | C12: 765600 | D12: 1274728 | E12: 0 | F12: 4236056
A13: Total general | B13: 88231364 | C13: 35651978 | D13: 52370709 | E13: 23392021 | F13: 199646072
G15: 2. Detalle Presupuesto vs Venta
H16: Acumulado T1 ( Concepto Año)
G17: Mes | H17: Presupuesto ($) | I17: Venta ($) | J17: Cumplimiento (%)
G18: Enero | H18: =H30 -> 83558032 | I18: =H31 -> 88231364 | J18: =Tabla1[[#This Row],[Venta ($)]]*100/Tabla1[[#This Row],[Presupuesto ($)]] -> 105.59292
G19: Febrero | H19: =H32 -> 41601950 | I19: =H33 -> 35651978 | J19: =Tabla1[[#This Row],[Venta ($)]]*100/Tabla1[[#This Row],[Presupuesto ($)]] -> 85.697853
G20: Marzo | H20: =H34 -> 42000000 | I20: =H35 -> 52370709 | J20: =Tabla1[[#This Row],[Venta ($)]]*100/Tabla1[[#This Row],[Presupuesto ($)]] -> 124.69216
G21: Abril | H21: =H36 -> 46431368 | I21: =H37 -> 23392021 | J21: =Tabla1[[#This Row],[Venta ($)]]*100/Tabla1[[#This Row],[Presupuesto ($)]] -> 50.37978
G22: Total Acumulado Año | H22: =H18+H19+H20+H21 -> 213591350 | I22: =I18+I19+I20+I21 -> 199646072 | J22: =Tabla1[[#This Row],[Venta ($)]]*100/Tabla1[[#This Row],[Presupuesto ($)]] -> 93.471047
G28: Venta día 31-03-2026
I29: Cumplimiento %
G30: PPTO Enero | H30: 83558032 | I30: =H31*100/H30 -> 105.59292
G31: Venta Enero | H31: =GETPIVOTDATA("Total",$A$2,"MES","ENERO") -> 88231364
G32: PPTO Febrero | H32: 41601950 | I32: =H33*100/H32 -> 85.697853
G33: Venta Febrero | H33: =GETPIVOTDATA("Total",$A$2,"MES","FEBRERO") -> 35651978
G34: PPTO Marzo | H34: 42000000 | I34: =J20 -> 124.69216
G35: Venta Marzo | H35: =GETPIVOTDATA("Total",$A$2,"MES","MARZO") -> 52370709
G36: Ppto Abril | H36: 46431368 | I36: =J21 -> 50.37978
G37: Venta Abril | H37: =GETPIVOTDATA("Total",$A$2,"MES","ABRIL") -> 23392021
G39: Total Acumulado (año) | H39: =GETPIVOTDATA("Total",$A$2) -> 199646072

Sheet VENTAS
A2: MES | B2: Rut | C2: Razón Social | D2: Fecha | E2: Región | F2: Vendedor | G2: Producto | H2: UN | I2: Documento | J2: Folio | K2: UM | L2: Cantidad | M2: Total | N2: Precio Uni | O2: Moneda | P2: PAÍS | Q2: FECHA VENCIMIENTO | R2: Negocio | S2: Comentarios | T2: Fecha guía
A3: ENERO | B3: 76.412.827-3 | C3: FRUTICOLA RIO BLANCO SPA | D3: 02/01/2026 | E3: METROPOLITANA | F3: PABLO LARATRO | G3: VECA MOVE - 20 L | H3: Agroveca | I3: Factura Electrónica | J3: 395 | K3: LTS | L3: 200 | M3: 1300000 | N3: =M3/L3 -> 6500 | O3: CLP | P3: CHILE | Q3: 46142 | R3: AV
A4: ENERO | B4: 13.304.290-3 | C4: ANITA ANDREA SALGADO MUNOZ | D4: 02/01/2026 | E4: SEXTA | F4: PABLO LARATRO | G4: VECA ROOT MAX - 20 L | H4: Agroveca | I4: Guía de Despacho Electrónica | J4: 128 | K4: LTS | L4: 60 | M4: 630000 | N4: =M4/L4 -> 10500 | O4: CLP | P4: CHILE | Q4: 46173 | R4: AV | S4: Guía de Diciembre (Pablo acuerda con Jorrge dejarla para Enero 2026
A5: ENERO | B5: 13.304.290-3 | C5: ANITA ANDREA SALGADO MUNOZ | D5: 02/01/2026 | E5: SEXTA | F5: PABLO LARATRO | G5: VECASIL FORTE - 20 L | H5: Agroveca | I5: Guía de Despacho Electrónica | J5: 128 | K5: LTS | L5: 80 | M5: 1008000 | N5: =M5/L5 -> 12600 | O5: CLP | P5: CHILE | Q5: 46173 | R5: AV | S5: Guía de Diciembre (Pablo acuerda con Jorrge dejarla para Enero 2027
A6: ENERO | B6: 13.304.290-3 | C6: ANITA ANDREA SALGADO MUNOZ | D6: 02/01/2026 | E6: SEXTA | F6: PABLO LARATRO | G6: VECA HUMIC ROOT - 20 L | H6: Agroveca | I6: Guía de Despacho Electrónica | J6: 128 | K6: LTS | L6: 220 | M6: 990000 | N6: =M6/L6 -> 4500 | O6: CLP | P6: CHILE | Q6: 46173 | R6: AV | S6: Guía de Diciembre (Pablo acuerda con Jorrge dejarla para Enero 2028
A7: ENERO | B7: 13.304.290-3 | C7: ANITA ANDREA SALGADO MUNOZ | D7: 02/01/2026 | E7: SEXTA | F7: PABLO LARATRO | G7: CYTOPRIME | H7: Agroveca | I7: Guía de Despacho Electrónica | J7: 128 | K7: LTS | L7: 11 | M7: 209000 | N7: =M7/L7 -> 19000 | O7: CLP | P7: CHILE | Q7: 46173 | R7: AV | S7: Guía de Diciembre (Pablo acuerda con Jorrge dejarla para Enero 2029
A8: ENERO | B8: 13.304.290-3 | C8: ANITA ANDREA SALGADO MUNOZ | D8: 02/01/2026 | E8: SEXTA | F8: PABLO LARATRO | G8: VECA PLUS POTASIO - 20 L | H8: Agroveca | I8: Guía de Despacho Electrónica | J8: 128 | K8: LTS | L8: 80 | M8: 408000 | N8: =M8/L8 -> 5100 | O8: CLP | P8: CHILE | Q8: 46173 | R8: AV | S8: Guía de Diciembre (Pablo acuerda con Jorrge dejarla para Enero 2030
A9: ENERO | B9: 13.304.290-3 | C9: ANITA ANDREA SALGADO MUNOZ | D9: 02/01/2026 | E9: SEXTA | F9: PABLO LARATRO | G9: VECA PLUS MAGNESIO - 20 L | H9: Agroveca | I9: Guía de Despacho Electrónica | J9: 128 | K9: LTS | L9: 100 | M9: 510000 | N9: =M9/L9 -> 5100 | O9: CLP | P9: CHILE | Q9: 46173 | R9: AV | S9: Guía de Diciembre (Pablo acuerda con Jorrge dejarla para Enero 2031
A10: ENERO | B10: 13.304.290-3 | C10: ANITA ANDREA SALGADO MUNOZ | D10: 02/01/2026 | E10: SEXTA | F10: PABLO LARATRO | G10: VECA MICROMIX - 20 L | H10: Agroveca | I10: Guía de Despacho Electrónica | J10: 128 | K10: LTS | L10: 80 | M10: 440000 | N10: =M10/L10 -> 5500 | O10: CLP | P10: CHILE | Q10: 46173 | R10: AV | S10: Guía de Diciembre (Pablo acuerda con Jorrge dejarla para Enero 2032
A11: ENERO | B11: 13.304.290-3 | C11: ANITA ANDREA SALGADO MUNOZ | D11: 02/01/2026 | E11: SEXTA | F11: PABLO LARATRO | G11: ALGAP 30 - 20 L | H11: Agroveca | I11: Guía de Despacho Electrónica | J11: 128 | K11: LTS | L11: 80 | M11: 544000 | N11: =M11/L11 -> 6800 | O11: CLP | P11: CHILE | Q11: 46173 | R11: AV | S11: Guía de Diciembre (Pablo acuerda con Jorrge dejarla para Enero 2033
A12: ENERO | B12: 13.304.290-3 | C12: ANITA ANDREA SALGADO MUNOZ | D12: 02/01/2026 | E12: SEXTA | F12: PABLO LARATRO | G12: VECA MOVE - 20 L | H12: Agroveca | I12: Guía de Despacho Electrónica | J12: 128 | K12: LTS | L12: 140 | M12: 1204000 | N12: =M12/L12 -> 8600 | O12: CLP | P12: CHILE | Q12: 46173 | R12: AV | S12: Guía de Diciembre (Pablo acuerda con Jorrge dejarla para Enero 2034
A13: ENERO | B13: 77.852.841-K | C13: COMERCIAL GUS SPA | D13: 05/01/2026 | E13: SEPTIMA | F13: FRANCISCO VELASQUEZ | G13: BIOVECA FOLIAR 250 GR | H13: Agroveca | I13: Factura Electrónica | J13: 396 | K13: UN | L13: 1 | M13: 35000 | N13: =M13/L13 -> 35000 | O13: CLP | P13: CHILE | Q13: 46027 | R13: AV
A14: ENERO | B14: 78.148.834-8 | C14: COMERCIALIZADORA LA COLONIA LIMITADA | D14: 05/01/2026 | E14: QUINTA | F14: FRANCISCO VELASQUEZ | G14: VECA MAX FULVIC 45% - 20 L | H14: Agroveca | I14: Factura Electrónica | J14: 397 | K14: LITROS | L14: 500 | M14: 1250000 | N14: =M14/L14 -> 2500 | O14: CLP | P14: CHILE | Q14: 46027 | R14: AV
A15: ENERO | B15: 18.584.049-2 | C15: SEBASTIAN MAURICIO BUTTI MENDOZA | D15: 05/01/2026 | E15: QUINTA | F15: FRANCISCO VELASQUEZ | G15: VECA ROOT MAX - 20 L | H15: Agroveca | I15: Factura Electrónica | J15: 398 | K15: LTS | L15: 20 | M15: 160000 | N15: =M15/L15 -> 8000 | O15: CLP | P15: CHILE | Q15: 46027 | R15: AV
A16: ENERO | B16: 76.532.516-1 | C16: AGROINVEST SPA | D16: 05/01/2026 | E16: SEXTA | F16: VALENTINA MUÑOZ | G16: PK-DEFEND MAX - 20 L | H16: Agroveca | I16: Factura Electrónica | J16: 399 | K16: LTS | L16: 140 | M16: 560000 | N16: =M16/L16 -> 4000 | O16: CLP | P16: CHILE | Q16: 46097 | R16: AV
A17: ENERO | B17: 76.532.516-1 | C17: AGROINVEST SPA | D17: 05/01/2026 | E17: SEXTA | F17: VALENTINA MUÑOZ | G17: PK-DEFEND MAX - 5 L | H17: Agroveca | I17: Factura Electrónica | J17: 399 | K17: LTS | L17: 10 | M17: 40000 | N17: =M17/L17 -> 4000 | O17: CLP | P17: CHILE | Q17: 46097 | R17: AV
A18: ENERO | B18: 76.428.021-0 | C18: SOCIEDAD AGRICOLA TIERRA DE BACO LIMITADA | D18: 05/01/2026 | E18: SEXTA | F18: JORGE CAROCA | G18: BIOVECA FOLIAR - 250 GR | H18: Agrocomercial | I18: Factura Electrónica | J18: 439 | K18: UN | L18: 70 | M18: 0 | N18: =M18/L18 -> 0 | O18: CLP | P18: CHILE | Q18: 46098 | R18: AV | S18: Guia N 107 | T18: 46008
A19: ENERO | B19: 76.428.021-0 | C19: SOCIEDAD AGRICOLA TIERRA DE BACO LIMITADA | D19: 05/01/2026 | E19: SEXTA | F19: RODRIGO ENCINA | G19: BIOVECA FOLIAR - 250 GRS | H19: Agroveca | I19: Factura Electrónica | J19: 440 | K19: UN | L19: 65 | M19: 0 | N19: =M19/L19 -> 0 | O19: CLP | P19: CHILE | Q19: 46110 | R19: AV | S19: Guia N 121 | T19: 46020
A20: ENERO | B20: 5.786.817-1 | C20: MARIO FERNANDO MUÑOZ SILVA | D20: 05/01/2026 | E20: SEXTA | F20: PABLO LARATRO | G20: AV-BIOSOLARIS - 20 L | H20: Agroveca | I20: Guía de Despacho Electrónica | J20: 129 | K20: LTS | L20: 40 | M20: 512000 | N20: =M20/L20 -> 12800 | O20: CLP | P20: CHILE | Q20: 46188 | R20: AV
A21: ENERO | B21: 5.786.817-1 | C21: MARIO FERNANDO MUÑOZ SILVA | D21: 05/01/2026 | E21: SEXTA | F21: PABLO LARATRO | G21: AV-BIOSOLARIS - 5 L | H21: Agroveca | I21: Guía de Despacho Electrónica | J21: 129 | K21: LTS | L21: 5 | M21: 64000 | N21: =M21/L21 -> 12800 | O21: CLP | P21: CHILE | Q21: 46188 | R21: AV
A22: ENERO | B22: 5.786.817-1 | C22: MARIO FERNANDO MUÑOZ SILVA | D22: 05/01/2026 | E22: SEXTA | F22: PABLO LARATRO | G22: AV-BIOSOLARIS - 1 L | H22: Agroveca | I22: Guía de Despacho Electrónica | J22: 129 | K22: LTS | L22: 3 | M22: 38400 | N22: =M22/L22 -> 12800 | O22: CLP | P22: CHILE | Q22: 46188 | R22: AV
A23: ENERO | B23: 78.189.158-4 | C23: AGRICOLA SAN PEDRO SPA | D23: 05/01/2026 | E23: SEXTA | F23: PABLO LARATRO | G23: AV-AMIN SUGAR - 20 L | H23: Agroveca | I23: Guía de Despacho Electrónica | J23: 130 | K23: LTS | L23: 20 | M23: 62000 | N23: =M23/L23 -> 3100 | O23: CLP | P23: CHILE | Q23: 46173 | R23: AV
A24: ENERO | B24: 78.189.158-4 | C24: AGRICOLA SAN PEDRO SPA | D24: 05/01/2026 | E24: SEXTA | F24: PABLO LARATRO | G24: AV-AMIN SUGAR - 1 L | H24: Agroveca | I24: Guía de Despacho Electrónica | J24: 130 | K24: LTS | L24: 3 | M24: 9300 | N24: =M24/L24 -> 3100 | O24: CLP | P24: CHILE | Q24: 46173 | R24: AV
A25: ENERO | B25: 78.189.158-4 | C25: AGRICOLA SAN PEDRO SPA | D25: 05/01/2026 | E25: SEXTA | F25: PABLO LARATRO | G25: AV-SILFORTE - 20 L | H25: Agroveca | I25: Guía de Despacho Electrónica | J25: 130 | K25: LTS | L25: 20 | M25: 272000 | N25: =M25/L25 -> 13600 | O25: CLP | P25: CHILE | Q25: 46173 | R25: AV
A26: ENERO | B26: 78.304.686-5 | C26: DISTRIBUIDORA AGRO DEL MONTE SPA | D26: 06/01/2026 | E26: SEXTA | F26: RODRIGO ENCINA | G26: VECA AMIN - 5 L | H26: Agroveca | I26: Factura Electrónica | J26: 400 | K26: LTS | L26: 10 | M26: 75900 | N26: =M26/L26 -> 7590 | O26: CLP | P26: CHILE | Q26: 46028 | R26: AV
A27: ENERO | B27: 76.428.021-0 | C27: SOCIEDAD AGRICOLA TIERRA DE BACO LIMITADA | D27: 06/01/2026 | E27: SEXTA | F27: RODRIGO ENCINA | G27: BIOVECA FOLIAR - 250 GR | H27: Agroveca | I27: Factura Electrónica | J27: 438 | K27: UN | L27: 55 | M27: 0 | N27: =M27/L27 -> 0 | O27: CLP | P27: CHILE | Q27: 46118 | R27: AV | S27: Guia N 132 | T27: 46028
A28: ENERO | B28: 4.593.930-8 | C28: MANUEL ANTONIO CASTRO LOPEZ | D28: 06/01/2026 | E28: SEPTIMA | F28: FRANCISCO VELASQUEZ | G28: AV BIOSOLARIS - 20 L | H28: Agroveca | I28: Guía de Despacho Electrónica | J28: 131 | K28: LTS | L28: 20 | M28: 260000 | N28: =M28/L28 -> 13000 | O28: CLP | P28: CHILE | Q28: 46162 | R28: AV
A29: ENERO | B29: 4.593.930-8 | C29: MANUEL ANTONIO CASTRO LOPEZ | D29: 06/01/2026 | E29: SEPTIMA | F29: FRANCISCO VELASQUEZ | G29: AV BIOSOLARIS - 5 L | H29: Agroveca | I29: Guía de Despacho Electrónica | J29: 131 | K29: LTS | L29: 5 | M29: 65000 | N29: =M29/L29 -> 13000 | O29: CLP | P29: CHILE | Q29: 46162 | R29: AV
A30: ENERO | B30: 76.428.021-0 | C30: SOCIEDAD AGRICOLA TIERRA DE BACO LIMITADA | D30: 06/01/2026 | E30: SEXTA | F30: RODRIGO ENCINA | G30: BIOVECA FOLIAR - 250 GR | H30: Agroveca | I30: Guía de Despacho Electrónica | J30: 132 | K30: UN | L30: 55 | M30: 1925000 | N30: =M30/L30 -> 35000 | O30: CLP | P30: CHILE | Q30: 46118 | R30: AV
A31: ENERO | B31: 78.061.253-3 | C31: AGRICOLA DON PEDRO SPA | D31: 07/01/2026 | E31: METROPOLITANA | F31: PABLO LARATRO | G31: ANALISIS FOLIAR CEREZO | H31: Laboratorio | I31: Factura Electrónica | J31: 402 | K31: UN | L31: 2 | M31: 0 | N31: =M31/L31 -> 0 | O31: CLP | P31: CHILE | Q31: 46029 | R31: AV | S31: Analisis foliar
A32: ENERO | B32: 77.598.960-2 | C32: AGROCOMERCIAL Y GANADERA LOMA LARGA LIMITADA | D32: 07/01/2026 | E32: CUARTA | F32: IVAN VEVERKA | G32: AV ALGAP 30 x 20 LT | H32: Agroveca | I32: Factura Electrónica | J32: 403 | K32: LTS | L32: 120 | M32: 876000 | N32: =M32/L32 -> 7300 | O32: CLP | P32: CHILE | Q32: 46089 | R32: AV | S32: 3 cuotas
A33: ENERO | B33: 77.598.960-2 | C33: AGROCOMERCIAL Y GANADERA LOMA LARGA LIMITADA | D33: 07/01/2026 | E33: CUARTA | F33: IVAN VEVERKA | G33: AV PLUS POTASIO x 20 LT | H33: Agroveca | I33: Factura Electrónica | J33: 403 | K33: LTS | L33: 120 | M33: 564000 | N33: =M33/L33 -> 4700 | O33: CLP | P33: CHILE | Q33: 46089 | R33: AV | S33: 3 cuotas
A34: ENERO | B34: 77.598.960-2 | C34: AGROCOMERCIAL Y GANADERA LOMA LARGA LIMITADA | D34: 07/01/2026 | E34: CUARTA | F34: IVAN VEVERKA | G34: AV PLUS AMIN x 20 LT | H34: Agroveca | I34: Factura Electrónica | J34: 403 | K34: LTS | L34: 120 | M34: 624000 | N34: =M34/L34 -> 5200 | O34: CLP | P34: CHILE | Q34: 46089 | R34: AV | S34: 3 cuotas
A35: ENERO | B35: 81.669.200-8 | C35: PONTIFICIA UNIVERSIDAD CATOLICA DE VALPARAISO | D35: 07/01/2026 | E35: QUINTA | F35: FRANCISCO VELASQUEZ | G35: AV BIOSOLARIS - 20 L | H35: Agroveca | I35: Factura Electrónica | J35: 404 | K35: LTS | L35: 20 | M35: 0 | N35: =M35/L35 -> 0 | O35: CLP | P35: CHILE | Q35: 46037 | R35: AV | S35: Guia N 105 | T35: 46007
A36: ENERO | B36: 76.826.270-5 | C36: INVERSIONES DON FORTUNATO LTDA | D36: 07/01/2026 | E36: SEXTA | F36: FRANCISCO VELASQUEZ | G36: VECA PLUS POTASIO - 20 L | H36: Agroveca | I36: Factura Electrónica | J36: 405 | K36: LTS | L36: 40 | M36: 0 | N36: =M36/L36 -> 0 | O36: CLP | P36: CHILE | Q36: 46031 | R36: AV
A37: ENERO | B37: 76.826.270-5 | C37: INVERSIONES DON FORTUNATO LTDA | D37: 07/01/2026 | E37: SEXTA | F37: FRANCISCO VELASQUEZ | G37: VECA PLUS CALCIO - 20 L | H37: Agroveca | I37: Factura Electrónica | J37: 405 | K37: LTS | L37: 40 | M37: 0 | N37: =M37/L37 -> 0 | O37: CLP | P37: CHILE | Q37: 46031 | R37: AV
A38: ENERO | B38: 76.826.270-5 | C38: INVERSIONES DON FORTUNATO LTDA | D38: 07/01/2026 | E38: SEXTA | F38: FRANCISCO VELASQUEZ | G38: VECA PLUS MAGNESIO - 20 L | H38: Agroveca | I38: Factura Electrónica | J38: 405 | K38: LTS | L38: 20 | M38: 0 | N38: =M38/L38 -> 0 | O38: CLP | P38: CHILE | Q38: 46031 | R38: AV
A39: ENERO | B39: 76.826.270-5 | C39: INVERSIONES DON FORTUNATO LTDA | D39: 07/01/2026 | E39: SEXTA | F39: FRANCISCO VELASQUEZ | G39: BIOVECA RAÍZ - 500 GRS | H39: Agroveca | I39: Factura Electrónica | J39: 405 | K39: UN | L39: 8 | M39: 0 | N39: =M39/L39 -> 0 | O39: CLP | P39: CHILE | Q39: =--Q40 -> 46031 | R39: AV
A40: ENERO | B40: 76.826.270-5 | C40: INVERSIONES DON FORTUNATO LTDA | D40: 07/01/2026 | E40: SEXTA | F40: FRANCISCO VELASQUEZ | G40: ODIN TEBUCONAZOLE 43% LT | H40: Agroveca | I40: Factura Electrónica | J40: 405 | K40: LTS | L40: 5 | M40: 0 | N40: =M40/L40 -> 0 | O40: CLP | P40: CHILE | Q40: 46031 | R40: AV
A41: ENERO | B41: 76.188.119-1 | C41: PEDRO PATRICIO MENESES SOTO AGRICOLA Y TRANSPORTES E.I.R.L. | D41: 07/01/2026 | E41: SEXTA | F41: RODRIGO ENCINA | G41: AV PLUS ROOT MAX x 5LT | H41: Agroveca | I41: Guía de Despacho Electrónica | J41: 133 | K41: LTS | L41: 5 | M41: 49750 | N41: =M41/L41 -> 9950 | O41: CLP | P41: CHILE | Q41: 46059 | R41: AV
A42: ENERO | B42: 76.188.119-1 | C42: PEDRO PATRICIO MENESES SOTO AGRICOLA Y TRANSPORTES E.I.R.L. | D42: 07/01/2026 | E42: SEXTA | F42: RODRIGO ENCINA | G42: BIOVECA NEMAOFF 500 GRS | H42: Agroveca | I42: Guía de Despacho Electrónica | J42: 133 | K42: UN | L42: 1 | M42: 35000 | N42: =M42/L42 -> 35000 | O42: CLP | P42: CHILE | Q42: 46059 | R42: AV
A43: ENERO | B43: 77.758.114-7 | C43: SOCIEDAD AGRÍCOLA COMERCIAL SIEMBRA SPA | D43: 07/01/2026 | E43: SEXTA | F43: RODRIGO ENCINA | G43: AV PLUS MAGNESIO x 5 LT | H43: Agroveca | I43: Guía de Despacho Electrónica | J43: 134 | K43: LTS | L43: 5 | M43: 20000 | N43: =M43/L43 -> 4000 | O43: CLP | P43: CHILE | Q43: 46087 | R43: AV
A44: ENERO | B44: 77.758.114-7 | C44: SOCIEDAD AGRÍCOLA COMERCIAL SIEMBRA SPA | D44: 07/01/2026 | E44: SEXTA | F44: RODRIGO ENCINA | G44: AV PLUS POTASIO x 5 LT | H44: Agroveca | I44: Guía de Despacho Electrónica | J44: 134 | K44: LTS | L44: 5 | M44: 20000 | N44: =M44/L44 -> 4000 | O44: CLP | P44: CHILE | Q44: 46087 | R44: AV
A45: ENERO | B45: 76.552.164-5 | C45: ANGELA MARIA DIAZ SCHMIDT AGRICOLA E.I.R.L. | D45: 07/01/2026 | E45: CUARTA | F45: IVAN VEVERKA | G45: AV PLUS AMIN x 20 LT | H45: Agroveca | I45: Guía de Despacho Electrónica | J45: 135 | K45: LTS | L45: 60 | M45: 312000 | N45: =M45/L45 -> 5200 | O45: CLP | P45: CHILE | Q45: 46172 | R45: AV
A46: ENERO | B46: 76.552.164-5 | C46: ANGELA MARIA DIAZ SCHMIDT AGRICOLA E.I.R.L. | D46: 07/01/2026 | E46: CUARTA | F46: IVAN VEVERKA | G46: AV ALGAP 30 x 20 LT | H46: Agroveca | I46: Guía de Despacho Electrónica | J46: 135 | K46: LTS | L46: 40 | M46: 292000 | N46: =M46/L46 -> 7300 | O46: CLP | P46: CHILE | Q46: 46172 | R46: AV
A47: ENERO | B47: 76.552.164-5 | C47: ANGELA MARIA DIAZ SCHMIDT AGRICOLA E.I.R.L. | D47: 07/01/2026 | E47: CUARTA | F47: IVAN VEVERKA | G47: AV PLUS POTASIO x 20 LT | H47: Agroveca | I47: Guía de Despacho Electrónica | J47: 135 | K47: LTS | L47: 40 | M47: 188000 | N47: =M47/L47 -> 4700 | O47: CLP | P47: CHILE | Q47: 46172 | R47: AV
A48: ENERO | B48: 76.552.164-5 | C48: ANGELA MARIA DIAZ SCHMIDT AGRICOLA E.I.R.L. | D48: 07/01/2026 | E48: CUARTA | F48: IVAN VEVERKA | G48: AV ROOT MAX x 20 LT | H48: Agroveca | I48: Guía de Despacho Electrónica | J48: 135 | K48: LTS | L48: 300 | M48: 2670000 | N48: =M48/L48 -> 8900 | O48: CLP | P48: CHILE | Q48: 46172 | R48: AV
A49: ENERO | B49: 76.552.164-5 | C49: ANGELA MARIA DIAZ SCHMIDT AGRICOLA E.I.R.L. | D49: 07/01/2026 | E49: CUARTA | F49: IVAN VEVERKA | G49: BIOVECA FOLIAR 250 GRS | H49: Agroveca | I49: Guía de Despacho Electrónica | J49: 135 | K49: UN | L49: 15 | M49: 420000 | N49: =M49/L49 -> 28000 | O49: CLP | P49: CHILE | Q49: 46172 | R49: AV
A50: ENERO | B50: 76.180.961-K | C50: AGRICOLA SAN ANTONIO LIMITADA | D50: 07/01/2026 | E50: CUARTA | F50: IVAN VEVERKA | G50: AV ALGAP 30 x 20 LT | H50: Agroveca | I50: Guía de Despacho Electrónica | J50: 136 | K50: LTS | L50: 20 | M50: 146000 | N50: =M50/L50 -> 7300 | O50: CLP | P50: CHILE | Q50: 46172 | R50: AV
A51: ENERO | B51: 76.180.961-K | C51: AGRICOLA SAN ANTONIO LIMITADA | D51: 07/01/2026 | E51: CUARTA | F51: IVAN VEVERKA | G51: AV PLUS MAGNESIO x 20 LT | H51: Agroveca | I51: Guía de Despacho Electrónica | J51: 136 | K51: LTS | L51: 20 | M51: 94000 | N51: =M51/L51 -> 4700 | O51: CLP | P51: CHILE | Q51: 46172 | R51: AV
A52: ENERO | B52: 77.650.227-8 | C52: SOCIEDAD AGRICOLA COMERCIAL LA HIGUERA SPA | D52: 08/01/2026 | E52: SEXTA | F52: JORGE CAROCA | G52: VECA AMIN - 20 L | H52: Agroveca | I52: Factura Electrónica | J52: 406 | K52: LITROS | L52: 20 | M52: 0 | N52: =M52/L52 -> 0 | O52: CLP | P52: CHILE | Q52: 46032 | R52: AV | S52: Guia N 48 | T52: 45894
A53: ENERO | B53: 77.650.227-8 | C53: SOCIEDAD AGRICOLA COMERCIAL LA HIGUERA SPA | D53: 08/01/2026 | E53: SEXTA | F53: JORGE CAROCA | G53: VECA BALANCE - 5 L | H53: Agroveca | I53: Factura Electrónica | J53: 407 | K53: LTS | L53: 5 | M53: 0 | N53: =M53/L53 -> 0 | O53: CLP | P53: CHILE | Q53: 46032 | R53: AV | S53: Guia N 60 | T53: 45931
A54: ENERO | B54: 77.650.227-8 | C54: SOCIEDAD AGRICOLA COMERCIAL LA HIGUERA SPA | D54: 08/01/2026 | E54: SEXTA | F54: JORGE CAROCA | G54: CYTO PRIME - 1 L | H54: Agroveca | I54: Factura Electrónica | J54: 407 | K54: LTS | L54: 3 | M54: 0 | N54: =M54/L54 -> 0 | O54: CLP | P54: CHILE | Q54: 46032 | R54: AV | S54: Guia N 60 | T54: 45931
A55: ENERO | B55: 77.650.227-8 | C55: SOCIEDAD AGRICOLA COMERCIAL LA HIGUERA SPA | D55: 08/01/2026 | E55: SEXTA | F55: JORGE CAROCA | G55: VECA PLUS POTASIO - 5 L | H55: Agroveca | I55: Factura Electrónica | J55: 408 | K55: LTS | L55: 10 | M55: 0 | N55: =M55/L55 -> 0 | O55: CLP | P55: CHILE | Q55: 46045 | R55: AV | S55: Guia N 78 | T55: 45985
A56: ENERO | B56: 77.650.227-8 | C56: SOCIEDAD AGRICOLA COMERCIAL LA HIGUERA SPA | D56: 08/01/2026 | E56: SEXTA | F56: JORGE CAROCA | G56: VECA PLUS CALCIO - 5 L | H56: Agroveca | I56: Factura Electrónica | J56: 408 | K56: LTS | L56: 10 | M56: 0 | N56: =M56/L56 -> 0 | O56: CLP | P56: CHILE | Q56: 46045 | R56: AV | S56: Guia N 78 | T56: 45985
A57: ENERO | B57: 77.650.227-8 | C57: SOCIEDAD AGRICOLA COMERCIAL LA HIGUERA SPA | D57: 08/01/2026 | E57: SEXTA | F57: JORGE CAROCA | G57: VECA PLUS BORO - 5 L (PRECIO EN USD) | H57: Agroveca | I57: Factura Electrónica | J57: 409 | K57: LITROS | L57: 5 | M57: 0 | N57: =M57/L57 -> 0 | O57: CLP | P57: CHILE | Q57: 46032 | R57: AV | S57: Guia N 49 | T57: 45897
A58: ENERO | B58: 77.650.227-8 | C58: SOCIEDAD AGRICOLA COMERCIAL LA HIGUERA SPA | D58: 08/01/2026 | E58: SEXTA | F58: JORGE CAROCA | G58: VECA PLUS ZINC - 5 L (PRECIO EN USD) | H58: Agroveca | I58: Factura Electrónica | J58: 409 | K58: LITROS | L58: 5 | M58: 0 | N58: =M58/L58 -> 0 | O58: CLP | P58: CHILE | Q58: 46032 | R58: AV | S58: Guia N 49 | T58: 45897
A59: ENERO | B59: 5.904.111-8 | C59: BETTY PATRICIA MONTENEGRO ESCOBAR | D59: 08/01/2026 | E59: QUINTA | F59: FRANCISCO VELASQUEZ | G59: VECA AMIN SUGAR - 20 L | H59: Agroveca | I59: Factura Electrónica | J59: 410 | K59: LTS | L59: 20 | M59: 130000 | N59: =M59/L59 -> 6500 | O59: CLP | P59: CHILE | Q59: 46031 | R59: AV
A60: ENERO | B60: 76.428.021-0 | C60: SOCIEDAD AGRICOLA TIERRA DE BACO LIMITADA | D60: 08/01/2026 | E60: SEXTA | F60: RODRIGO ENCINA | G60: BIOVECA FOLIAR - 250 GRS | H60: Agroveca | I60: Factura Electrónica | J60: 437 | K60: UN | L60: 25 | M60: 0 | N60: =M60/L60 -> 0 | O60: CLP | P60: CHILE | Q60: 46120 | R60: AV | S60: Guia N 139 | T60: 46030
A61: ENERO | B61: 77.036.196-6 | C61: SOCIEDAD COMERCIAL RYN SPA | D61: 08/01/2026 | E61: SEXTA | F61: RODRIGO ENCINA | G61: VECA CALCIO BORO - 20 L | H61: Agroveca | I61: Guía de Despacho Electrónica | J61: 138 | K61: LTS | L61: 60 | M61: 228309 | N61: =M61/L61 -> 3805.15 | O61: CLP | P61: CHILE | Q61: 46150 | R61: AV
A62: ENERO | B62: 76.428.021-0 | C62: SOCIEDAD AGRICOLA TIERRA DE BACO LIMITADA | D62: 08/01/2026 | E62: SEXTA | F62: RODRIGO ENCINA | G62: BIOVECA FOLIAR - 250 GRS | H62: Agroveca | I62: Guía de Despacho Electrónica | J62: 139 | K62: UN | L62: 25 | M62: 875000 | N62: =M62/L62 -> 35000 | O62: CLP | P62: CHILE | Q62: 46120 | R62: AV
A63: ENERO | B63: 76.788.317-K | C63: AGRICOLA MARIO ALEJANDRO VIDAL NUNEZ EIRL | D63: 09/01/2026 | E63: SEXTA | F63: JORGE CAROCA | G63: VECA PLUS POTASIO - 20 L | H63: Agrocomercial | I63: Factura Electrónica | J63: 411 | K63: LTS | L63: 20 | M63: 89689 | N63: =M63/L63 -> 4484.45 | O63: CLP | P63: CHILE | Q63: 46031 | R63: AV
A64: ENERO | B64: 76.788.317-K | C64: AGRICOLA MARIO ALEJANDRO VIDAL NUNEZ EIRL | D64: 09/01/2026 | E64: SEXTA | F64: JORGE CAROCA | G64: VECA PLUS MAGNESIO - 20 L | H64: Agrocomercial | I64: Factura Electrónica | J64: 411 | K64: LTS | L64: 20 | M64: 89689 | N64: =M64/L64 -> 4484.45 | O64: CLP | P64: CHILE | Q64: 46031 | R64: AV
A65: ENERO | B65: 76.788.317-K | C65: AGRICOLA MARIO ALEJANDRO VIDAL NUNEZ EIRL | D65: 09/01/2026 | E65: SEXTA | F65: JORGE CAROCA | G65: VECA PLUS CALCIO - 20 L | H65: Agrocomercial | I65: Factura Electrónica | J65: 411 | K65: LTS | L65: 20 | M65: 89689 | N65: =M65/L65 -> 4484.45 | O65: CLP | P65: CHILE | Q65: 46031 | R65: AV
A66: ENERO | B66: 76.788.317-K | C66: AGRICOLA MARIO ALEJANDRO VIDAL NUNEZ EIRL | D66: 09/01/2026 | E66: SEXTA | F66: JORGE CAROCA | G66: VECA MAX FULVIC 45% - 20 L | H66: Agrocomercial | I66: Factura Electrónica | J66: 411 | K66: LTS | L66: 40 | M66: 172203 | N66: =M66/L66 -> 4305.075 | O66: CLP | P66: CHILE | Q66: 46031 | R66: AV
A67: ENERO | B67: 76.788.317-K | C67: AGRICOLA MARIO ALEJANDRO VIDAL NUNEZ EIRL | D67: 09/01/2026 | E67: SEXTA | F67: JORGE CAROCA | G67: BIOVECA NEMAOFF - 500 GR | H67: Agrocomercial | I67: Factura Electrónica | J67: 411 | K67: UN | L67: 3 | M67: 121080 | N67: =M67/L67 -> 40360 | O67: CLP | P67: CHILE | Q67: 46031 | R67: AV
A68: ENERO | B68: 9.056.061-1 | C68: FELIPE ALBERTO RIQUELME ACUNA | D68: 09/01/2026 | E68: ÑUBLE | F68: VALENTINA MUÑOZ | G68: AV ROOT MAX X 20 LT | H68: Agroveca | I68: Factura Electrónica | J68: 412 | K68: LTS | L68: 20 | M68: 200000 | N68: =M68/L68 -> 10000 | O68: CLP | P68: CHILE | Q68: 46031 | R68: AV
A69: ENERO | B69: 9.056.061-1 | C69: FELIPE ALBERTO RIQUELME ACUNA | D69: 09/01/2026 | E69: ÑUBLE | F69: VALENTINA MUÑOZ | G69: AV PLUS MAGNESIO X 20 LT | H69: Agroveca | I69: Factura Electrónica | J69: 412 | K69: LTS | L69: 20 | M69: 100000 | N69: =M69/L69 -> 5000 | O69: CLP | P69: CHILE | Q69: 46031 | R69: AV
A70: ENERO | B70: 9.056.061-1 | C70: FELIPE ALBERTO RIQUELME ACUNA | D70: 09/01/2026 | E70: ÑUBLE | F70: VALENTINA MUÑOZ | G70: AV PLUS POTASIO X 20 LT | H70: Agroveca | I70: Factura Electrónica | J70: 412 | K70: LTS | L70: 20 | M70: 100000 | N70: =M70/L70 -> 5000 | O70: CLP | P70: CHILE | Q70: 46031 | R70: AV
A71: ENERO | B71: 76.547.701-8 | C71: SOCIEDAD AGRICOLA BRUGNATO LIMITADA | D71: 09/01/2026 | E71: QUINTA | F71: FRANCISCO VELASQUEZ | G71: VECASIL FORTE - 20 L | H71: Agroveca | I71: Guía de Despacho Electrónica | J71: 141 | K71: LTS | L71: 40 | M71: 320000 | N71: =M71/L71 -> 8000 | O71: CLP | P71: CHILE | Q71: 46091 | R71: AV
A72: ENERO | B72: 77.988.779-0 | C72: SEIS SOLES SPA | D72: 10/01/2026 | E72: TERCERA | F72: PABLO LARATRO | G72: ALGAP 30 - 20 L | H72: Agroveca | I72: Factura Electrónica | J72: 413 | K72: UN | L72: 100 | M72: 0 | N72: =M72/L72 -> 0 | O72: CLP | P72: CHILE | Q72: 46049 | R72: AV
A73: ENERO | B73: 77.582.414-K | C73: AGROINSUMOS KULLIN | D73: 12/01/2026 | E73: SEPTIMA | F73: PABLO LARATRO | G73: AV PLUS CALCIO BORO - 20 L | H73: Agroveca | I73: Factura Electrónica | J73: 414 | K73: LTS | L73: 20 | M73: 0 | N73: =M73/L73 -> 0 | O73: CLP | P73: CHILE | Q73: 46044 | R73: AV | S73: GUIA AV 708 | T73: 45909
A74: ENERO | B74: 77.582.414-K | C74: AGROINSUMOS KULLIN | D74: 12/01/2026 | E74: SEPTIMA | F74: PABLO LARATRO | G74: AV PLUS BORO - 20 L | H74: Agroveca | I74: Factura Electrónica | J74: 414 | K74: LTS | L74: 20 | M74: 0 | N74: =M74/L74 -> 0 | O74: CLP | P74: CHILE | Q74: 46044 | R74: AV | S74: GUIA AV 708 | T74: 45909
A75: ENERO | B75: 77.582.414-K | C75: AGROINSUMOS KULLIN | D75: 12/01/2026 | E75: SEPTIMA | F75: PABLO LARATRO | G75: AV AMIN - 20 L | H75: Agroveca | I75: Factura Electrónica | J75: 414 | K75: LTS | L75: 20 | M75: 0 | N75: =M75/L75 -> 0 | O75: CLP | P75: CHILE | Q75: 46044 | R75: AV | S75: GUIA AV 708 | T75: 45909
A76: ENERO | B76: 77.582.414-K | C76: AGROINSUMOS KULLIN | D76: 12/01/2026 | E76: SEPTIMA | F76: PABLO LARATRO | G76: VECA AMIN - 1 L | H76: Agroveca | I76: Factura Electrónica | J76: 415 | K76: LTS | L76: 5 | M76: 0 | N76: =M76/L76 -> 0 | O76: CLP | P76: CHILE | Q76: 46044 | R76: AV | S76: GUIA AV 709 | T76: 45924
A77: ENERO | B77: 77.582.414-K | C77: AGROINSUMOS KULLIN | D77: 12/01/2026 | E77: SEPTIMA | F77: PABLO LARATRO | G77: VECA PLUS ZINC - 1 L | H77: Agroveca | I77: Factura Electrónica | J77: 415 | K77: LTS | L77: 5 | M77: 0 | N77: =M77/L77 -> 0 | O77: CLP | P77: CHILE | Q77: 46044 | R77: AV | S77: GUIA AV 709 | T77: 45924
A78: ENERO | B78: 77.582.414-K | C78: AGROINSUMOS KULLIN | D78: 12/01/2026 | E78: SEPTIMA | F78: PABLO LARATRO | G78: VECA PLUS MAGNESIO - 1 L | H78: Agroveca | I78: Factura Electrónica | J78: 415 | K78: LTS | L78: 5 | M78: 0 | N78: =M78/L78 -> 0 | O78: CLP | P78: CHILE | Q78: 46044 | R78: AV | S78: GUIA AV 709 | T78: 45924
A79: ENERO | B79: 77.582.414-K | C79: AGROINSUMOS KULLIN | D79: 12/01/2026 | E79: SEPTIMA | F79: PABLO LARATRO | G79: VECA PLUS POTASIO - 5 L | H79: Agroveca | I79: Factura Electrónica | J79: 416 | K79: LTS | L79: 60 | M79: 0 | N79: =M79/L79 -> 0 | O79: CLP | P79: CHILE | Q79: 46044 | R79: AV | S79: GUIA AV 789 | T79: 45954
A80: ENERO | B80: 77.582.414-K | C80: AGROINSUMOS KULLIN | D80: 12/01/2026 | E80: SEPTIMA | F80: PABLO LARATRO | G80: VECA NUTRI MIX - 1 L | H80: Agroveca | I80: Factura Electrónica | J80: 416 | K80: LTS | L80: 10 | M80: 0 | N80: =M80/L80 -> 0 | O80: CLP | P80: CHILE | Q80: 46044 | R80: AV | S80: GUIA AV 789 | T80: 45954
A81: ENERO | B81: 77.582.414-K | C81: AGROINSUMOS KULLIN | D81: 12/01/2026 | E81: SEPTIMA | F81: PABLO LARATRO | G81: VECA NUTRI MIX - 20 L | H81: Agroveca | I81: Factura Electrónica | J81: 416 | K81: LTS | L81: 20 | M81: 0 | N81: =M81/L81 -> 0 | O81: CLP | P81: CHILE | Q81: 46044 | R81: AV | S81: GUIA AV 789 | T81: 45954
A82: ENERO | B82: 77.139.169-9 | C82: AGRICOLA FUNDO LA PROVIDENCIA LTDA | D82: 12/01/2026 | E82: METROPOLITANA | F82: PABLO LARATRO | G82: BIOVECA RAÍZ - 500 GRS | H82: Agroveca | I82: Factura Electrónica | J82: 417 | K82: LTS | L82: 10 | M82: 0 | N82: =M82/L82 -> 0 | O82: CLP | P82: CHILE | Q82: 46038 | R82: AV | S82: GUIA AV 827 | T82: 45974
A83: ENERO | B83: 76.421.617-2 | C83: AGRICOLA CASA DEL CERRILLO EIRL | D83: 12/01/2026 | E83: QUINTA | F83: FRANCISCO VELASQUEZ | G83: ALGAP 30 - 20 L | H83: Agroveca | I83: Factura Electrónica | J83: 418 | K83: LTS | L83: 40 | M83: 0 | N83: =M83/L83 -> 0 | O83: CLP | P83: CHILE | Q83: 46037 | R83: AV | S83: GUIA AV 769 | T83: 45948
A84: ENERO | B84: 76.421.617-2 | C84: AGRICOLA CASA DEL CERRILLO EIRL | D84: 12/01/2026 | E84: QUINTA | F84: FRANCISCO VELASQUEZ | G84: ALGAP 30 - 5 L | H84: Agroveca | I84: Factura Electrónica | J84: 418 | K84: LTS | L84: 10 | M84: 0 | N84: =M84/L84 -> 0 | O84: CLP | P84: CHILE | Q84: 46037 | R84: AV | S84: GUIA AV 769 | T84: 45948
... A96: ENERO | B96: 76.428.021-0 | C96: SOCIEDAD AGRICOLA TIERRA DE BACO LIMITADA | D96: 12/01/2026 | E96: SEXTA | F96: JORGE CAROCA | G96: AV BIOVECA FOLIAR - 250 GR | H96: Agroveca | I96: Factura Electrónica | J96: 436 | K96: UN | L96: 45 | M96: 0 | N96: =M96/L96 -> 0 | O96: CLP | P96: CHILE | Q96: 46121 | R96: AV | S96: Guia N142 | T96: 46034
A97: ENERO | B97: 9.501.614-6 | C97: JUAN ENRIQUE VARGAS ALZAMORA | D97: 12/01/2026 | E97: QUINTA | F97: FRANCISCO VELASQUEZ | G97: AV AMIN SUGAR - 200 L | H97: Agroveca | I97: Guía de Despacho Electrónica | J97: 142 | K97: LITROS | L97: 200 | M97: 900000 | N97: =M97/L97 -> 4500 | O97: CLP | P97: CHILE | Q97: 46123 | R97: AV
A98: ENERO | B98: 76.428.021-0 | C98: SOCIEDAD AGRICOLA TIERRA DE BACO LIMITADA | D98: 12/01/2026 | E98: SEXTA | F98: JORGE CAROCA | G98: AV BIOVECA FOLIAR - 250 GR | H98: Agroveca | I98: Guía de Despacho Electrónica | J98: 143 | K98: UN | L98: 45 | M98: 1575000 | N98: =M98/L98 -> 35000 | O98: CLP | P98: CHILE | Q98: 46121 | R98: AV
A99: ENERO | B99: 10.824.336-8 | C99: EUGENIO ALFREDO AMPUERO GUERRA | D99: 13/01/2026 | E99: QUINTA | F99: FRANCISCO VELASQUEZ | G99: BIOVECA NEMAOFF - 500 GRS | H99: Agroveca | I99: Factura Electrónica | J99: 424 | K99: UN | L99: 10 | M99: 0 | N99: =M99/L99 -> 0 | O99: CLP | P99: CHILE | Q99: 46037 | R99: AV | S99: GUIA AV 851 | T99: 45988
A100: ENERO | B100: 76.104.169-K | C100: AGRICOLA RIBERA LIMITADA | D100: 13/01/2026 | E100: METROPOLITANA | F100: JORGE CAROCA | G100: VECA MOVE - 20 L | H100: Agroveca | I100: Factura Electrónica | J100: 425 | K100: LTS | L100: 180 | M100: 0 | N100: =M100/L100 -> 0 | O100: CLP | P100: CHILE | Q100: 46037 | R100: AV | S100: GUIA AV 550 | T100: 45730
A101: ENERO | B101: 77.987.344-7 | C101: AGRÍCOLA CORNEJO ALVAREZ SPA | D101: 13/01/2026 | E101: SEXTA | F101: RODRIGO ENCINA | G101: AV AMIN X 5 LT | H101: Agroveca | I101: Factura Electrónica | J101: 426 | K101: LTS | L101: 5 | M101: 40125 | N101: =M101/L101 -> 8025 | O101: CLP | P101: CHILE | Q101: 46035 | R101: AV
A102: ENERO | B102: 77.987.344-7 | C102: AGRÍCOLA CORNEJO ALVAREZ SPA | D102: 13/01/2026 | E102: SEXTA | F102: RODRIGO ENCINA | G102: AV AMIN X 1 LT | H102: Agroveca | I102: Factura Electrónica | J102: 426 | K102: LTS | L102: 1 | M102: 8025 | N102: =M102/L102 -> 8025 | O102: CLP | P102: CHILE | Q102: 46035 | R102: AV
A103: ENERO | B103: 78.148.834-8 | C103: COMERCIALIZADORA LA COLONIA LIMITADA | D103: 13/01/2026 | E103: QUINTA | F103: FRANCISCO VELASQUEZ | G103: AV HUMIC ROOT X 20LT | H103: Agroveca | I103: Factura Electrónica | J103: 427 | K103: LITROS | L103: 40 | M103: 100000 | N103: =M103/L103 -> 2500 | O103: CLP | P103: CHILE | Q103: 46035 | R103: AV
A104: ENERO | B104: 78.148.834-8 | C104: COMERCIALIZADORA LA COLONIA LIMITADA | D104: 13/01/2026 | E104: QUINTA | F104: FRANCISCO VELASQUEZ | G104: AV ROOT MAX X 20LT | H104: Agroveca | I104: Factura Electrónica | J104: 427 | K104: LITROS | L104: 20 | M104: 160000 | N104: =M104/L104 -> 8000 | O104: CLP | P104: CHILE | Q104: 46035 | R104: AV
A105: ENERO | B105: 76.412.827-3 | C105: FRUTICOLA RIO BLANCO SPA | D105: 14/01/2026 | E105: METROPOLITANA | F105: LABORATORIO | G105: ANÁLISIS FOLIAR - CAMPO LOS LIRIOS | H105: Laboratorio | I105: Factura Electrónica | J105: 428 | K105: UN | L105: 9 | M105: 0 | N105: =M105/L105 -> 0 | O105: CLP | P105: CHILE | Q105: 46036 | R105: AV
A106: ENERO | B106: 76.412.827-3 | C106: FRUTICOLA RIO BLANCO SPA | D106: 14/01/2026 | E106: METROPOLITANA | F106: LABORATORIO | G106: ANÁLISIS FOLIAR - CAMPO LA MONTAÑA | H106: Laboratorio | I106: Factura Electrónica | J106: 429 | K106: UN | L106: 4 | M106: 0 | N106: =M106/L106 -> 0 | O106: CLP | P106: CHILE | Q106: 46036 | R106: AV
A107: ENERO | B107: 76.412.827-3 | C107: FRUTICOLA RIO BLANCO SPA | D107: 14/01/2026 | E107: METROPOLITANA | F107: LABORATORIO | G107: ANÁLISIS FOLIAR - CAMPO SANTA LUISA | H107: Laboratorio | I107: Factura Electrónica | J107: 430 | K107: UN | L107: 8 | M107: 0 | N107: =M107/L107 -> 0 | O107: CLP | P107: CHILE | Q107: 46036 | R107: AV
A108: ENERO | B108: 13.302.310-0 | C108: LUIS AMERICO VIDAL MEZA | D108: 14/01/2026 | E108: SEXTA | F108: JORGE CAROCA | G108: NUTRI MIX - 5 L | H108: Agrocomercial | I108: Factura Electrónica | J108: 431 | K108: LTS | L108: 5 | M108: 30935 | N108: =M108/L108 -> 6187 | O108: CLP | P108: CHILE | Q108: 46036 | R108: AV
A109: ENERO | B109: 89.308.000-7 | C109: VILLEGAS Y BERRIOS Y CIA LTDA | D109: 14/01/2026 | E109: SEXTA | F109: JORGE CAROCA | G109: VECA BALANCE - 1 L | H109: Agroveca | I109: Factura Electrónica | J109: 432 | K109: LTS | L109: 2 | M109: 30660 | N109: =M109/L109 -> 15330 | O109: CLP | P109: CHILE | Q109: 46126 | R109: AV
A110: ENERO | B110: 89.308.000-7 | C110: VILLEGAS Y BERRIOS Y CIA LTDA | D110: 14/01/2026 | E110: SEXTA | F110: JORGE CAROCA | G110: VECA PLUS ZINC - 5 L | H110: Agroveca | I110: Factura Electrónica | J110: 432 | K110: LTS | L110: 5 | M110: 22050 | N110: =M110/L110 -> 4410 | O110: CLP | P110: CHILE | Q110: 46126 | R110: AV
A111: ENERO | B111: 89.308.000-7 | C111: VILLEGAS Y BERRIOS Y CIA LTDA | D111: 14/01/2026 | E111: SEXTA | F111: JORGE CAROCA | G111: VECA PLUS BORO - 5 L | H111: Agroveca | I111: Factura Electrónica | J111: 432 | K111: LTS | L111: 5 | M111: 22050 | N111: =M111/L111 -> 4410 | O111: CLP | P111: CHILE | Q111: 46126 | R111: AV
A112: ENERO | B112: 89.308.000-7 | C112: VILLEGAS Y BERRIOS Y CIA LTDA | D112: 14/01/2026 | E112: SEXTA | F112: JORGE CAROCA | G112: VECA PLUS CALCIO - 1 L | H112: Agroveca | I112: Factura Electrónica | J112: 432 | K112: LTS | L112: 15 | M112: 87150 | N112: =M112/L112 -> 5810 | O112: CLP | P112: CHILE | Q112: 46126 | R112: AV
...

Sheet ACUMULADO T1
A1: PPTO V/S VENTAS - T1 // 2026
A2: Vendedor | B2: Ppto Enero ($) | C2: Venta Enero ($) | D2: Cumplimiento (%) | E2: Ppto Febrero ($) | F2: Venta Febrero ($) | G2: Cumplimiento (%)2 | H2: Ppto Marzo ($) | I2: Venta Marzo ($) | J2: Cumplimiento (%)3
A3: Francisco Velasquez | B3: 14858032 | C3: 14491000 | D3: =C3*100/B3 -> 97.52974 | E3: 11501950 | F3: 9912000 | G3: =F3*100/E3 -> 86.176692 | H3: 6500000 | I3: =GETPIVOTDATA("Total",RESUMEN!$A$2,"MES","MARZO","Vendedor","FRANCISCO VELASQUEZ") -> 5196500 | J3: =Tabla4[[#This Row],[Venta Marzo ($)]]*100/Tabla4[[#This Row],[Ppto Marzo ($)]] -> 79.946154
A4: Ivan Veverka | B4: 6000000 | C4: 6186000 | D4: =C4*100/B4 -> 103.1 | E4: 6000000 | F4: 944000 | G4: =F4*100/E4 -> 15.733333 | H4: 6000000 | I4: =GETPIVOTDATA("Total",RESUMEN!$A$2,"MES","MARZO","Vendedor","IVAN VEVERKA") -> 1680000 | J4: =Tabla4[[#This Row],[Venta Marzo ($)]]*100/Tabla4[[#This Row],[Ppto Marzo ($)]] -> 28
A5: Jorge Caroca | B5: 12500000 | C5: 15269491 | D5: =C5*100/B5 -> 122.15593 | E5: 6000000 | F5: 6389076 | G5: =F5*100/E5 -> 106.4846 | H5: 14500000 | I5: =GETPIVOTDATA("Total",RESUMEN!$A$2,"MES","MARZO","Vendedor","JORGE CAROCA") -> 31913309 | J5: =Tabla4[[#This Row],[Venta Marzo ($)]]*100/Tabla4[[#This Row],[Ppto Marzo ($)]] -> 220.09179
A6: Pablo Laratro | B6: 36000000 | C6: 37027580 | D6: =C6*100/B6 -> 102.85439 | E6: 10600000 | F6: 10378585 | G6: =F6*100/E6 -> 97.911179 | H6: 7500000 | I6: =GETPIVOTDATA("Total",RESUMEN!$A$2,"MES","MARZO","Vendedor","PABLO LARATRO") -> 5487150 | J6: =Tabla4[[#This Row],[Venta Marzo ($)]]*100/Tabla4[[#This Row],[Ppto Marzo ($)]] -> 73.162
A7: Rodrigo Encina | B7: 14200000 | C7: 13510783 | D7: =C7*100/B7 -> 95.146359 | E7: 7500000 | F7: 7262717 | G7: =F7*100/E7 -> 96.836227 | H7: 7500000 | I7: =GETPIVOTDATA("Total",RESUMEN!$A$2,"MES","MARZO","Vendedor","RODRIGO ENCINA") -> 6819022 | J7: =Tabla4[[#This Row],[Venta Marzo ($)]]*100/Tabla4[[#This Row],[Ppto Marzo ($)]] -> 90.920293
A8: Valentina Muñoz | B8: 1200000 | C8: 2195728 | D8: =Tabla4[[#This Row],[Venta Enero ($)]]*100/Tabla4[[#This Row],[Ppto Enero ($)]] -> 182.97733 | E8: 1200000 | F8: 765600 | G8: =Tabla4[[#This Row],[Venta Febrero ($)]]*100/Tabla4[[#This Row],[Ppto Febrero ($)]] -> 63.8 | H8: 1200000 | I8: =GETPIVOTDATA("Total",RESUMEN!$A$2,"MES","MARZO","Vendedor","VALENTINA MUÑOZ") -> 1274728 | J8: =Tabla4[[#This Row],[Venta Marzo ($)]]*100/Tabla4[[#This Row],[Ppto Marzo ($)]] -> 106.22733
B9: =SUM(B3:B8) -> 84758032 | C9: =SUM(C3:C8) -> 88680582 | D9: =Tabla4[[#Totals],[Venta Enero ($)]]*100/Tabla4[[#Totals],[Ppto Enero ($)]] -> 104.62794 | E9: =SUM(E3:E8) -> 42801950 | F9: =SUM(F3:F8) -> 35651978 | G9: =Tabla4[[#Totals],[Venta Febrero ($)]]*100/Tabla4[[#Totals],[Ppto Febrero ($)]] -> 83.295219 | H9: =SUM(H3:H8) -> 43200000 | I9: =SUM(I3:I8) -> 52370709 | J9: =Tabla4[[#Totals],[Venta Marzo ($)]]*100/Tabla4[[#Totals],[Ppto Marzo ($)]] -> 121.22849
A12: PPTO V/S VENTAS - T2 // 2026
A13: Vendedor | B13: Ppto Abril ($) | C13: Venta Abril ($) | D13: Cumplimiento (%) | E13: Ppto Mayo ($) | F13: Venta Mayo ($) | G13: Cumplimiento (%)2 | H13: Ppto Junio ($) | I13: Venta Junio ($) | J13: Cumplimiento (%)3
A14: Francisco Velasquez | B14: 10000000 | C14: =GETPIVOTDATA("Total",RESUMEN!$A$2,"MES","ABRIL","Vendedor","FRANCISCO VELASQUEZ") -> 3113000 | D14: =C14*100/B14 -> 31.13 | E14: 5000000 | G14: =F14*100/E14 -> 0 | H14: 20000000 | J14: =Tabla43[[#This Row],[Venta Junio ($)]]*100/Tabla43[[#This Row],[Ppto Junio ($)]] -> 0
A15: Ivan Veverka | B15: 6000000 | D15: =C15*100/B15 -> 0 | E15: 6000000 | G15: =F15*100/E15 -> 0 | H15: 6000000 | J15: =Tabla43[[#This Row],[Venta Junio ($)]]*100/Tabla43[[#This Row],[Ppto Junio ($)]] -> 0
A16: Jorge Caroca | B16: 8831368 | C16: =GETPIVOTDATA("Total",RESUMEN!$A$2,"MES","ABRIL","Vendedor","JORGE CAROCA") -> 10171393 | D16: =C16*100/B16 -> 115.17347 | E16: 12500000 | G16: =F16*100/E16 -> 0 | H16: 8730000 | J16: =Tabla43[[#This Row],[Venta Junio ($)]]*100/Tabla43[[#This Row],[Ppto Junio ($)]] -> 0
A17: Pablo Laratro | B17: 16600000 | C17: =GETPIVOTDATA("Total",RESUMEN!$A$2,"MES","ABRIL","Vendedor","PABLO LARATRO") -> 8304645 | D17: =C17*100/B17 -> 50.027982 | E17: 22500000 | G17: =F17*100/E17 -> 0 | H17: 7800000 | J17: =Tabla43[[#This Row],[Venta Junio ($)]]*100/Tabla43[[#This Row],[Ppto Junio ($)]] -> 0
A18: Rodrigo Encina | B18: 5000000 | C18: =GETPIVOTDATA("Total",RESUMEN!$A$2,"MES","ABRIL","Vendedor","RODRIGO ENCINA") -> 1763157 | D18: =C18*100/B18 -> 35.26314 | E18: 5000000 | G18: =F18*100/E18 -> 0 | H18: 5000000 | J18: =Tabla43[[#This Row],[Venta Junio ($)]]*100/Tabla43[[#This Row],[Ppto Junio ($)]] -> 0
A19: Valentina Muñoz | B19: 1200000 | D19: =Tabla43[[#This Row],[Venta Abril ($)]]*100/Tabla43[[#This Row],[Ppto Abril ($)]] -> 0 | E19: 1200000 | G19: =Tabla43[[#This Row],[Venta Mayo ($)]]*100/Tabla43[[#This Row],[Ppto Mayo ($)]] -> 0 | H19: 1200000 | J19: =Tabla43[[#This Row],[Venta Junio ($)]]*100/Tabla43[[#This Row],[Ppto Junio ($)]] -> 0
B20: =SUM(B14:B19) -> 47631368 | C20: =SUM(C14:C19) -> 23352195 | D20: =Tabla43[[#Totals],[Venta Abril ($)]]*100/Tabla43[[#Totals],[Ppto Abril ($)]] -> 49.026925 | E20: =SUM(E14:E19) -> 52200000 | F20: =SUM(F14:F19) -> 0 | G20: =Tabla43[[#Totals],[Venta Mayo ($)]]*100/Tabla43[[#Totals],[Ppto Mayo ($)]] -> 0 | H20: =SUM(H14:H19) -> 48730000 | I20: =SUM(I14:I19) -> 0 | J20: =Tabla43[[#Totals],[Venta Junio ($)]]*100/Tabla43[[#Totals],[Ppto Junio ($)]] -> 0
B24: Acumulado T1 (Concepto RTC)
A25: Vendedor | B25: Ppto | C25: Venta | D25: %
A26: Francisco Velasquez | B26: =B3+E3+H3+B14 -> 42859982 | C26: =C3+F3+I3 -> 29599500 | D26: =C26*100/B26 -> 69.060925
A27: Ivan Veverka | B27: =B4+E4+H4+B15 -> 24000000 | C27: =C4+F4+I4 -> 8810000 | D27: =C27*100/B27 -> 36.708333
A28: Jorge Caroca | B28: =B5+E5+H5+B16 -> 41831368 | C28: =C5+F5+I5 -> 53571876 | D28: =C28*100/B28 -> 128.06628
A29: Pablo Laratro | B29: =B6+E6+H6+B17 -> 70700000 | C29: =C6+F6+I6 -> 52893315 | D29: =C29*100/B29 -> 74.813741
A30: Rodrigo Encina | B30: =B7+E7+H7+B18 -> 34200000 | C30: =C7+F7+I7 -> 27592522 | D30: =C30*100/B30 -> 80.679889
A31: Valentina Muñoz | B31: 0 | C31: =C8+F8 -> 2961328
B32: =SUM(B26:B31) -> 213591350 | C32: =SUM(C26:C31) -> 175428541 | D32: =Tabla5[[#Totals],[Venta]]*100/Tabla5[[#Totals],[Ppto]] -> 82.132793
