Workbook

Sheet Pricing Piso Peru
A1: TABLA DE PRECIOS PISO — PERÚ 2026 | AGROVECA GRUPO LATAM
A2: ⚙️ Celda B3 = margen objetivo (recalcula columnas E-K automáticamente). Celda azul = editable. Celda verde = precio propuesto por Gerencia. PRECIOS EN USD.
A3: MARGEN OBJETIVO → | B3: 0.47 | C3: ← Cambia este % y todo se recalcula
A5: PRODUCTO | B5: FORMATO | C5: COSTO FÁBRICA (PKG) USD | D5: TAMAÑO FMT | E5: COSTO USD/UNIDAD | F5: PRECIO PISO (CALCULADO) | G5: MARGEN CALC % | H5: PRECIO PROM REAL | I5: NUEVO PRECIO PISO PROPUESTO | J5: MARGEN PROPUESTO % | K5: GAP PROP. vs CALC % | L5: VAR $ (Prop - Real) | M5: CLASIF. PROPUESTO | N5: ORDEN FMT
A6: AV HUMIC ROOT | B6: 1 L | D6: 1 | E6: =IF(C6="","",C6/D6) | F6: =IF(E6="","",E6/(1-$B$3)) | G6: =$B$3 -> 0.47 | I6: 4.2 | J6: =IF(OR(I6="",E6=""),"",(I6-E6)/I6) | K6: =IF(OR(I6="",F6=""),"",(I6-F6)/F6) | L6: =IF(OR(I6="",H6=""),"",I6-H6) | M6: =IF(I6="","⚪ SIN PROPUESTA",IF(F6="","🟢 SOBRE PISO",IF(I6<F6*0.95,"🔴 BAJO PISO",IF(I6>F6*1.05,"🟢 SOBRE PISO","🟡 EN PISO")))) -> 🟢 SOBRE PISO | N6: 1
A7: AV HUMIC ROOT | B7: 20 L | C7: 32 | D7: 20 | E7: =IF(C7="","",C7/D7) -> 1.6 | F7: =IF(E7="","",E7/(1-$B$3)) -> 3.0188679 | G7: =$B$3 -> 0.47 | H7: 3.5 | I7: 3.5 | J7: =IF(OR(I7="",E7=""),"",(I7-E7)/I7) -> 0.54285714 | K7: =IF(OR(I7="",F7=""),"",(I7-F7)/F7) -> 0.159375 | L7: =IF(OR(I7="",H7=""),"",I7-H7) -> 0 | M7: =IF(I7="","⚪ SIN PROPUESTA",IF(F7="","🟢 SOBRE PISO",IF(I7<F7*0.95,"🔴 BAJO PISO",IF(I7>F7*1.05,"🟢 SOBRE PISO","🟡 EN PISO")))) -> 🟢 SOBRE PISO | N7: 3
A8: AV HUMIC ROOT | B8: 200 L | C8: 250 | D8: 200 | E8: =IF(C8="","",C8/D8) -> 1.25 | F8: =IF(E8="","",E8/(1-$B$3)) -> 2.3584906 | G8: =$B$3 -> 0.47 | I8: 3 | J8: =IF(OR(I8="",E8=""),"",(I8-E8)/I8) -> 0.58333333 | K8: =IF(OR(I8="",F8=""),"",(I8-F8)/F8) -> 0.272 | L8: =IF(OR(I8="",H8=""),"",I8-H8) | M8: =IF(I8="","⚪ SIN PROPUESTA",IF(F8="","🟢 SOBRE PISO",IF(I8<F8*0.95,"🔴 BAJO PISO",IF(I8>F8*1.05,"🟢 SOBRE PISO","🟡 EN PISO")))) -> 🟢 SOBRE PISO | N8: 4
A9: AV HUMIC ROOT | B9: 1000 L | C9: 1160 | D9: 1000 | E9: =IF(C9="","",C9/D9) -> 1.16 | F9: =IF(E9="","",E9/(1-$B$3)) -> 2.1886792 | G9: =$B$3 -> 0.47 | I9: 2.5 | J9: =IF(OR(I9="",E9=""),"",(I9-E9)/I9) -> 0.536 | K9: =IF(OR(I9="",F9=""),"",(I9-F9)/F9) -> 0.14224138 | L9: =IF(OR(I9="",H9=""),"",I9-H9) | M9: =IF(I9="","⚪ SIN PROPUESTA",IF(F9="","🟢 SOBRE PISO",IF(I9<F9*0.95,"🔴 BAJO PISO",IF(I9>F9*1.05,"🟢 SOBRE PISO","🟡 EN PISO")))) -> 🟢 SOBRE PISO | N9: 7
A10: AV MAX FULVIC 45% | B10: 1 L | D10: 1 | E10: =IF(C10="","",C10/D10) | F10: =IF(E10="","",E10/(1-$B$3)) | G10: =$B$3 -> 0.47 | I10: 4.2 | J10: =IF(OR(I10="",E10=""),"",(I10-E10)/I10) | K10: =IF(OR(I10="",F10=""),"",(I10-F10)/F10) | L10: =IF(OR(I10="",H10=""),"",I10-H10) | M10: =IF(I10="","⚪ SIN PROPUESTA",IF(F10="","🟢 SOBRE PISO",IF(I10<F10*0.95,"🔴 BAJO PISO",IF(I10>F10*1.05,"🟢 SOBRE PISO","🟡 EN PISO")))) -> 🟢 SOBRE PISO | N10: 1
A11: AV MAX FULVIC 45% | B11: 20 L | C11: 32 | D11: 20 | E11: =IF(C11="","",C11/D11) -> 1.6 | F11: =IF(E11="","",E11/(1-$B$3)) -> 3.0188679 | G11: =$B$3 -> 0.47 | H11: 2.8 | I11: 3 | J11: =IF(OR(I11="",E11=""),"",(I11-E11)/I11) -> 0.46666667 | K11: =IF(OR(I11="",F11=""),"",(I11-F11)/F11) -> -0.00625 | L11: =IF(OR(I11="",H11=""),"",I11-H11) -> 0.2 | M11: =IF(I11="","⚪ SIN PROPUESTA",IF(F11="","🟢 SOBRE PISO",IF(I11<F11*0.95,"🔴 BAJO PISO",IF(I11>F11*1.05,"🟢 SOBRE PISO","🟡 EN PISO")))) -> 🟡 EN PISO | N11: 3
A12: AV MAX FULVIC 45% | B12: 200 L | C12: 250 | D12: 200 | E12: =IF(C12="","",C12/D12) -> 1.25 | F12: =IF(E12="","",E12/(1-$B$3)) -> 2.3584906 | G12: =$B$3 -> 0.47 | I12: 2.5 | J12: =IF(OR(I12="",E12=""),"",(I12-E12)/I12) -> 0.5 | K12: =IF(OR(I12="",F12=""),"",(I12-F12)/F12) -> 0.06 | L12: =IF(OR(I12="",H12=""),"",I12-H12) | M12: =IF(I12="","⚪ SIN PROPUESTA",IF(F12="","🟢 SOBRE PISO",IF(I12<F12*0.95,"🔴 BAJO PISO",IF(I12>F12*1.05,"🟢 SOBRE PISO","🟡 EN PISO")))) -> 🟢 SOBRE PISO | N12: 4
A13: AV MAX FULVIC 45% | B13: 1000 L | C13: 1160 | D13: 1000 | E13: =IF(C13="","",C13/D13) -> 1.16 | F13: =IF(E13="","",E13/(1-$B$3)) -> 2.1886792 | G13: =$B$3 -> 0.47 | I13: 2.2 | J13: =IF(OR(I13="",E13=""),"",(I13-E13)/I13) -> 0.47272727 | K13: =IF(OR(I13="",F13=""),"",(I13-F13)/F13) -> 0.0051724138 | L13: =IF(OR(I13="",H13=""),"",I13-H13) | M13: =IF(I13="","⚪ SIN PROPUESTA",IF(F13="","🟢 SOBRE PISO",IF(I13<F13*0.95,"🔴 BAJO PISO",IF(I13>F13*1.05,"🟢 SOBRE PISO","🟡 EN PISO")))) -> 🟡 EN PISO | N13: 7
A14: AV AMIN | B14: 1 L | D14: 1 | E14: =IF(C14="","",C14/D14) | F14: =IF(E14="","",E14/(1-$B$3)) | G14: =$B$3 -> 0.47 | I14: 5 | J14: =IF(OR(I14="",E14=""),"",(I14-E14)/I14) | K14: =IF(OR(I14="",F14=""),"",(I14-F14)/F14) | L14: =IF(OR(I14="",H14=""),"",I14-H14) | M14: =IF(I14="","⚪ SIN PROPUESTA",IF(F14="","🟢 SOBRE PISO",IF(I14<F14*0.95,"🔴 BAJO PISO",IF(I14>F14*1.05,"🟢 SOBRE PISO","🟡 EN PISO")))) -> 🟢 SOBRE PISO | N14: 1
A15: AV AMIN | B15: 20 L | C15: 37 | D15: 20 | E15: =IF(C15="","",C15/D15) -> 1.85 | F15: =IF(E15="","",E15/(1-$B$3)) -> 3.490566 | G15: =$B$3 -> 0.47 | H15: 7.5 | I15: 4.2 | J15: =IF(OR(I15="",E15=""),"",(I15-E15)/I15) -> 0.55952381 | K15: =IF(OR(I15="",F15=""),"",(I15-F15)/F15) -> 0.20324324 | L15: =IF(OR(I15="",H15=""),"",I15-H15) -> -3.3 | M15: =IF(I15="","⚪ SIN PROPUESTA",IF(F15="","🟢 SOBRE PISO",IF(I15<F15*0.95,"🔴 BAJO PISO",IF(I15>F15*1.05,"🟢 SOBRE PISO","🟡 EN PISO")))) -> 🟢 SOBRE PISO | N15: 3
A16: AV AMIN | B16: 200 L | C16: 255 | D16: 200 | E16: =IF(C16="","",C16/D16) -> 1.275 | F16: =IF(E16="","",E16/(1-$B$3)) -> 2.4056604 | G16: =$B$3 -> 0.47 | I16: 3.5 | J16: =IF(OR(I16="",E16=""),"",(I16-E16)/I16) -> 0.63571429 | K16: =IF(OR(I16="",F16=""),"",(I16-F16)/F16) -> 0.45490196 | L16: =IF(OR(I16="",H16=""),"",I16-H16) | M16: =IF(I16="","⚪ SIN PROPUESTA",IF(F16="","🟢 SOBRE PISO",IF(I16<F16*0.95,"🔴 BAJO PISO",IF(I16>F16*1.05,"🟢 SOBRE PISO","🟡 EN PISO")))) -> 🟢 SOBRE PISO | N16: 4
A17: AV AMIN | B17: 1000 L | C17: 1492 | D17: 1000 | E17: =IF(C17="","",C17/D17) -> 1.492 | F17: =IF(E17="","",E17/(1-$B$3)) -> 2.8150943 | G17: =$B$3 -> 0.47 | I17: 3 | J17: =IF(OR(I17="",E17=""),"",(I17-E17)/I17) -> 0.50266667 | K17: =IF(OR(I17="",F17=""),"",(I17-F17)/F17) -> 0.065683646 | L17: =IF(OR(I17="",H17=""),"",I17-H17) | M17: =IF(I17="","⚪ SIN PROPUESTA",IF(F17="","🟢 SOBRE PISO",IF(I17<F17*0.95,"🔴 BAJO PISO",IF(I17>F17*1.05,"🟢 SOBRE PISO","🟡 EN PISO")))) -> 🟢 SOBRE PISO | N17: 7
A18: AV AMIN SUGAR | B18: 1 L | D18: 1 | E18: =IF(C18="","",C18/D18) | F18: =IF(E18="","",E18/(1-$B$3)) | G18: =$B$3 -> 0.47 | I18: 8 | J18: =IF(OR(I18="",E18=""),"",(I18-E18)/I18) | K18: =IF(OR(I18="",F18=""),"",(I18-F18)/F18) | L18: =IF(OR(I18="",H18=""),"",I18-H18) | M18: =IF(I18="","⚪ SIN PROPUESTA",IF(F18="","🟢 SOBRE PISO",IF(I18<F18*0.95,"🔴 BAJO PISO",IF(I18>F18*1.05,"🟢 SOBRE PISO","🟡 EN PISO")))) -> 🟢 SOBRE PISO | N18: 1
A19: AV AMIN SUGAR | B19: 20 L | C19: 36 | D19: 20 | E19: =IF(C19="","",C19/D19) -> 1.8 | F19: =IF(E19="","",E19/(1-$B$3)) -> 3.3962264 | G19: =$B$3 -> 0.47 | I19: 7.5 | J19: =IF(OR(I19="",E19=""),"",(I19-E19)/I19) -> 0.76 | K19: =IF(OR(I19="",F19=""),"",(I19-F19)/F19) -> 1.2083333 | L19: =IF(OR(I19="",H19=""),"",I19-H19) | M19: =IF(I19="","⚪ SIN PROPUESTA",IF(F19="","🟢 SOBRE PISO",IF(I19<F19*0.95,"🔴 BAJO PISO",IF(I19>F19*1.05,"🟢 SOBRE PISO","🟡 EN PISO")))) -> 🟢 SOBRE PISO | N19: 3
A20: AV AMIN SUGAR | B20: 200 L | C20: 240 | D20: 200 | E20: =IF(C20="","",C20/D20) -> 1.2 | F20: =IF(E20="","",E20/(1-$B$3)) -> 2.2641509 | G20: =$B$3 -> 0.47 | I20: 6 | J20: =IF(OR(I20="",E20=""),"",(I20-E20)/I20) -> 0.8 | K20: =IF(OR(I20="",F20=""),"",(I20-F20)/F20) -> 1.65 | L20: =IF(OR(I20="",H20=""),"",I20-H20) | M20: =IF(I20="","⚪ SIN PROPUESTA",IF(F20="","🟢 SOBRE PISO",IF(I20<F20*0.95,"🔴 BAJO PISO",IF(I20>F20*1.05,"🟢 SOBRE PISO","🟡 EN PISO")))) -> 🟢 SOBRE PISO | N20: 4
A21: AV AMIN SUGAR | B21: 1000 L | C21: 1412 | D21: 1000 | E21: =IF(C21="","",C21/D21) -> 1.412 | F21: =IF(E21="","",E21/(1-$B$3)) -> 2.6641509 | G21: =$B$3 -> 0.47 | I21: 5 | J21: =IF(OR(I21="",E21=""),"",(I21-E21)/I21) -> 0.7176 | K21: =IF(OR(I21="",F21=""),"",(I21-F21)/F21) -> 0.87677054 | L21: =IF(OR(I21="",H21=""),"",I21-H21) | M21: =IF(I21="","⚪ SIN PROPUESTA",IF(F21="","🟢 SOBRE PISO",IF(I21<F21*0.95,"🔴 BAJO PISO",IF(I21>F21*1.05,"🟢 SOBRE PISO","🟡 EN PISO")))) -> 🟢 SOBRE PISO | N21: 7
A22: AV ROOT MAX | B22: 1 L | D22: 1 | E22: =IF(C22="","",C22/D22) | F22: =IF(E22="","",E22/(1-$B$3)) | G22: =$B$3 -> 0.47 | I22: 15 | J22: =IF(OR(I22="",E22=""),"",(I22-E22)/I22) | K22: =IF(OR(I22="",F22=""),"",(I22-F22)/F22) | L22: =IF(OR(I22="",H22=""),"",I22-H22) | M22: =IF(I22="","⚪ SIN PROPUESTA",IF(F22="","🟢 SOBRE PISO",IF(I22<F22*0.95,"🔴 BAJO PISO",IF(I22>F22*1.05,"🟢 SOBRE PISO","🟡 EN PISO")))) -> 🟢 SOBRE PISO | N22: 1
A23: AV ROOT MAX | B23: 20 L | C23: 36 | D23: 20 | E23: =IF(C23="","",C23/D23) -> 1.8 | F23: =IF(E23="","",E23/(1-$B$3)) -> 3.3962264 | G23: =$B$3 -> 0.47 | H23: 13.86 | I23: 13.8 | J23: =IF(OR(I23="",E23=""),"",(I23-E23)/I23) -> 0.86956522 | K23: =IF(OR(I23="",F23=""),"",(I23-F23)/F23) -> 3.0633333 | L23: =IF(OR(I23="",H23=""),"",I23-H23) -> -0.06 | M23: =IF(I23="","⚪ SIN PROPUESTA",IF(F23="","🟢 SOBRE PISO",IF(I23<F23*0.95,"🔴 BAJO PISO",IF(I23>F23*1.05,"🟢 SOBRE PISO","🟡 EN PISO")))) -> 🟢 SOBRE PISO | N23: 3
A24: AV ROOT MAX | B24: 200 L | C24: 250 | D24: 200 | E24: =IF(C24="","",C24/D24) -> 1.25 | F24: =IF(E24="","",E24/(1-$B$3)) -> 2.3584906 | G24: =$B$3 -> 0.47 | I24: 12 | J24: =IF(OR(I24="",E24=""),"",(I24-E24)/I24) -> 0.89583333 | K24: =IF(OR(I24="",F24=""),"",(I24-F24)/F24) -> 4.088 | L24: =IF(OR(I24="",H24=""),"",I24-H24) | M24: =IF(I24="","⚪ SIN PROPUESTA",IF(F24="","🟢 SOBRE PISO",IF(I24<F24*0.95,"🔴 BAJO PISO",IF(I24>F24*1.05,"🟢 SOBRE PISO","🟡 EN PISO")))) -> 🟢 SOBRE PISO | N24: 4
A25: AV ROOT MAX | B25: 1000 L | C25: 1170 | D25: 1000 | E25: =IF(C25="","",C25/D25) -> 1.17 | F25: =IF(E25="","",E25/(1-$B$3)) -> 2.2075472 | G25: =$B$3 -> 0.47 | I25: 11 | J25: =IF(OR(I25="",E25=""),"",(I25-E25)/I25) -> 0.89363636 | K25: =IF(OR(I25="",F25=""),"",(I25-F25)/F25) -> 3.982906 | L25: =IF(OR(I25="",H25=""),"",I25-H25) | M25: =IF(I25="","⚪ SIN PROPUESTA",IF(F25="","🟢 SOBRE PISO",IF(I25<F25*0.95,"🔴 BAJO PISO",IF(I25>F25*1.05,"🟢 SOBRE PISO","🟡 EN PISO")))) -> 🟢 SOBRE PISO | N25: 7
A26: AV ALGAP 30 | B26: 1 L | D26: 1 | E26: =IF(C26="","",C26/D26) | F26: =IF(E26="","",E26/(1-$B$3)) | G26: =$B$3 -> 0.47 | I26: 11 | J26: =IF(OR(I26="",E26=""),"",(I26-E26)/I26) | K26: =IF(OR(I26="",F26=""),"",(I26-F26)/F26) | L26: =IF(OR(I26="",H26=""),"",I26-H26) | M26: =IF(I26="","⚪ SIN PROPUESTA",IF(F26="","🟢 SOBRE PISO",IF(I26<F26*0.95,"🔴 BAJO PISO",IF(I26>F26*1.05,"🟢 SOBRE PISO","🟡 EN PISO")))) -> 🟢 SOBRE PISO | N26: 1
A27: AV ALGAP 30 | B27: 20 L | C27: 40 | D27: 20 | E27: =IF(C27="","",C27/D27) -> 2 | F27: =IF(E27="","",E27/(1-$B$3)) -> 3.7735849 | G27: =$B$3 -> 0.47 | H27: 10.4 | I27: 10 | J27: =IF(OR(I27="",E27=""),"",(I27-E27)/I27) -> 0.8 | K27: =IF(OR(I27="",F27=""),"",(I27-F27)/F27) -> 1.65 | L27: =IF(OR(I27="",H27=""),"",I27-H27) -> -0.4 | M27: =IF(I27="","⚪ SIN PROPUESTA",IF(F27="","🟢 SOBRE PISO",IF(I27<F27*0.95,"🔴 BAJO PISO",IF(I27>F27*1.05,"🟢 SOBRE PISO","🟡 EN PISO")))) -> 🟢 SOBRE PISO | N27: 3
A28: AV ALGAP 30 | B28: 200 L | C28: 340 | D28: 200 | E28: =IF(C28="","",C28/D28) -> 1.7 | F28: =IF(E28="","",E28/(1-$B$3)) -> 3.2075472 | G28: =$B$3 -> 0.47 | I28: 8 | J28: =IF(OR(I28="",E28=""),"",(I28-E28)/I28) -> 0.7875 | K28: =IF(OR(I28="",F28=""),"",(I28-F28)/F28) -> 1.4941176 | L28: =IF(OR(I28="",H28=""),"",I28-H28) | M28: =IF(I28="","⚪ SIN PROPUESTA",IF(F28="","🟢 SOBRE PISO",IF(I28<F28*0.95,"🔴 BAJO PISO",IF(I28>F28*1.05,"🟢 SOBRE PISO","🟡 EN PISO")))) -> 🟢 SOBRE PISO | N28: 4
A29: AV ALGAP 30 | B29: 1000 L | C29: 1560 | D29: 1000 | E29: =IF(C29="","",C29/D29) -> 1.56 | F29: =IF(E29="","",E29/(1-$B$3)) -> 2.9433962 | G29: =$B$3 -> 0.47 | I29: 5.8 | J29: =IF(OR(I29="",E29=""),"",(I29-E29)/I29) -> 0.73103448 | K29: =IF(OR(I29="",F29=""),"",(I29-F29)/F29) -> 0.97051282 | L29: =IF(OR(I29="",H29=""),"",I29-H29) | M29: =IF(I29="","⚪ SIN PROPUESTA",IF(F29="","🟢 SOBRE PISO",IF(I29<F29*0.95,"🔴 BAJO PISO",IF(I29>F29*1.05,"🟢 SOBRE PISO","🟡 EN PISO")))) -> 🟢 SOBRE PISO | N29: 7
A30: AV SILFORTE | B30: 1 L | D30: 1 | E30: =IF(C30="","",C30/D30) | F30: =IF(E30="","",E30/(1-$B$3)) | G30: =$B$3 -> 0.47 | I30: 14 | J30: =IF(OR(I30="",E30=""),"",(I30-E30)/I30) | K30: =IF(OR(I30="",F30=""),"",(I30-F30)/F30) | L30: =IF(OR(I30="",H30=""),"",I30-H30) | M30: =IF(I30="","⚪ SIN PROPUESTA",IF(F30="","🟢 SOBRE PISO",IF(I30<F30*0.95,"🔴 BAJO PISO",IF(I30>F30*1.05,"🟢 SOBRE PISO","🟡 EN PISO")))) -> 🟢 SOBRE PISO | N30: 1
A31: AV SILFORTE | B31: 20 L | C31: 48 | D31: 20 | E31: =IF(C31="","",C31/D31) -> 2.4 | F31: =IF(E31="","",E31/(1-$B$3)) -> 4.5283019 | G31: =$B$3 -> 0.47 | H31: 12.05 | I31: 13 | J31: =IF(OR(I31="",E31=""),"",(I31-E31)/I31) -> 0.81538462 | K31: =IF(OR(I31="",F31=""),"",(I31-F31)/F31) -> 1.8708333 | L31: =IF(OR(I31="",H31=""),"",I31-H31) -> 0.95 | M31: =IF(I31="","⚪ SIN PROPUESTA",IF(F31="","🟢 SOBRE PISO",IF(I31<F31*0.95,"🔴 BAJO PISO",IF(I31>F31*1.05,"🟢 SOBRE PISO","🟡 EN PISO")))) -> 🟢 SOBRE PISO | N31: 3
A32: AV SILFORTE | B32: 200 L | C32: 430 | D32: 200 | E32: =IF(C32="","",C32/D32) -> 2.15 | F32: =IF(E32="","",E32/(1-$B$3)) -> 4.0566038 | G32: =$B$3 -> 0.47 | I32: 12 | J32: =IF(OR(I32="",E32=""),"",(I32-E32)/I32) -> 0.82083333 | K32: =IF(OR(I32="",F32=""),"",(I32-F32)/F32) -> 1.9581395 | L32: =IF(OR(I32="",H32=""),"",I32-H32) | M32: =IF(I32="","⚪ SIN PROPUESTA",IF(F32="","🟢 SOBRE PISO",IF(I32<F32*0.95,"🔴 BAJO PISO",IF(I32>F32*1.05,"🟢 SOBRE PISO","🟡 EN PISO")))) -> 🟢 SOBRE PISO | N32: 4
A33: AV SILFORTE | B33: 1000 L | C33: 1990 | D33: 1000 | E33: =IF(C33="","",C33/D33) -> 1.99 | F33: =IF(E33="","",E33/(1-$B$3)) -> 3.754717 | G33: =$B$3 -> 0.47 | I33: 10 | J33: =IF(OR(I33="",E33=""),"",(I33-E33)/I33) -> 0.801 | K33: =IF(OR(I33="",F33=""),"",(I33-F33)/F33) -> 1.6633166 | L33: =IF(OR(I33="",H33=""),"",I33-H33) | M33: =IF(I33="","⚪ SIN PROPUESTA",IF(F33="","🟢 SOBRE PISO",IF(I33<F33*0.95,"🔴 BAJO PISO",IF(I33>F33*1.05,"🟢 SOBRE PISO","🟡 EN PISO")))) -> 🟢 SOBRE PISO | N33: 7
A34: GREEN GUARDIAN MAX | B34: 1 L | D34: 1 | E34: =IF(C34="","",C34/D34) | F34: =IF(E34="","",E34/(1-$B$3)) | G34: =$B$3 -> 0.47 | I34: 5 | J34: =IF(OR(I34="",E34=""),"",(I34-E34)/I34) | K34: =IF(OR(I34="",F34=""),"",(I34-F34)/F34) | L34: =IF(OR(I34="",H34=""),"",I34-H34) | M34: =IF(I34="","⚪ SIN PROPUESTA",IF(F34="","🟢 SOBRE PISO",IF(I34<F34*0.95,"🔴 BAJO PISO",IF(I34>F34*1.05,"🟢 SOBRE PISO","🟡 EN PISO")))) -> 🟢 SOBRE PISO | N34: 1
A35: GREEN GUARDIAN MAX | B35: 20 L | C35: 44 | D35: 20 | E35: =IF(C35="","",C35/D35) -> 2.2 | F35: =IF(E35="","",E35/(1-$B$3)) -> 4.1509434 | G35: =$B$3 -> 0.47 | I35: 4.5 | J35: =IF(OR(I35="",E35=""),"",(I35-E35)/I35) -> 0.51111111 | K35: =IF(OR(I35="",F35=""),"",(I35-F35)/F35) -> 0.084090909 | L35: =IF(OR(I35="",H35=""),"",I35-H35) | M35: =IF(I35="","⚪ SIN PROPUESTA",IF(F35="","🟢 SOBRE PISO",IF(I35<F35*0.95,"🔴 BAJO PISO",IF(I35>F35*1.05,"🟢 SOBRE PISO","🟡 EN PISO")))) -> 🟢 SOBRE PISO | N35: 3
A36: GREEN GUARDIAN MAX | B36: 200 L | C36: 380 | D36: 200 | E36: =IF(C36="","",C36/D36) -> 1.9 | F36: =IF(E36="","",E36/(1-$B$3)) -> 3.5849057 | G36: =$B$3 -> 0.47 | I36: 4 | J36: =IF(OR(I36="",E36=""),"",(I36-E36)/I36) -> 0.525 | K36: =IF(OR(I36="",F36=""),"",(I36-F36)/F36) -> 0.11578947 | L36: =IF(OR(I36="",H36=""),"",I36-H36) | M36: =IF(I36="","⚪ SIN PROPUESTA",IF(F36="","🟢 SOBRE PISO",IF(I36<F36*0.95,"🔴 BAJO PISO",IF(I36>F36*1.05,"🟢 SOBRE PISO","🟡 EN PISO")))) -> 🟢 SOBRE PISO | N36: 4
A37: GREEN GUARDIAN MAX | B37: 1000 L | C37: 1820 | D37: 1000 | E37: =IF(C37="","",C37/D37) -> 1.82 | F37: =IF(E37="","",E37/(1-$B$3)) -> 3.4339623 | G37: =$B$3 -> 0.47 | I37: 3.5 | J37: =IF(OR(I37="",E37=""),"",(I37-E37)/I37) -> 0.48 | K37: =IF(OR(I37="",F37=""),"",(I37-F37)/F37) -> 0.019230769 | L37: =IF(OR(I37="",H37=""),"",I37-H37) | M37: =IF(I37="","⚪ SIN PROPUESTA",IF(F37="","🟢 SOBRE PISO",IF(I37<F37*0.95,"🔴 BAJO PISO",IF(I37>F37*1.05,"🟢 SOBRE PISO","🟡 EN PISO")))) -> 🟡 EN PISO | N37: 7
A38: AV15 40-20 | B38: 1 L | D38: 1 | E38: =IF(C38="","",C38/D38) | F38: =IF(E38="","",E38/(1-$B$3)) | G38: =$B$3 -> 0.47 | I38: 5 | J38: =IF(OR(I38="",E38=""),"",(I38-E38)/I38) | K38: =IF(OR(I38="",F38=""),"",(I38-F38)/F38) | L38: =IF(OR(I38="",H38=""),"",I38-H38) | M38: =IF(I38="","⚪ SIN PROPUESTA",IF(F38="","🟢 SOBRE PISO",IF(I38<F38*0.95,"🔴 BAJO PISO",IF(I38>F38*1.05,"🟢 SOBRE PISO","🟡 EN PISO")))) -> 🟢 SOBRE PISO | N38: 1
A39: AV15 40-20 | B39: 20 L | C39: 38 | D39: 20 | E39: =IF(C39="","",C39/D39) -> 1.9 | F39: =IF(E39="","",E39/(1-$B$3)) -> 3.5849057 | G39: =$B$3 -> 0.47 | I39: 4 | J39: =IF(OR(I39="",E39=""),"",(I39-E39)/I39) -> 0.525 | K39: =IF(OR(I39="",F39=""),"",(I39-F39)/F39) -> 0.11578947 | L39: =IF(OR(I39="",H39=""),"",I39-H39) | M39: =IF(I39="","⚪ SIN PROPUESTA",IF(F39="","🟢 SOBRE PISO",IF(I39<F39*0.95,"🔴 BAJO PISO",IF(I39>F39*1.05,"🟢 SOBRE PISO","🟡 EN PISO")))) -> 🟢 SOBRE PISO | N39: 3
A40: AV15 40-20 | B40: 200 L | C40: 330 | D40: 200 | E40: =IF(C40="","",C40/D40) -> 1.65 | F40: =IF(E40="","",E40/(1-$B$3)) -> 3.1132075 | G40: =$B$3 -> 0.47 | I40: 3 | J40: =IF(OR(I40="",E40=""),"",(I40-E40)/I40) -> 0.45 | K40: =IF(OR(I40="",F40=""),"",(I40-F40)/F40) -> -0.036363636 | L40: =IF(OR(I40="",H40=""),"",I40-H40) | M40: =IF(I40="","⚪ SIN PROPUESTA",IF(F40="","🟢 SOBRE PISO",IF(I40<F40*0.95,"🔴 BAJO PISO",IF(I40>F40*1.05,"🟢 SOBRE PISO","🟡 EN PISO")))) -> 🟡 EN PISO | N40: 4
A41: AV15 40-20 | B41: 1000 L | C41: 1540 | D41: 1000 | E41: =IF(C41="","",C41/D41) -> 1.54 | F41: =IF(E41="","",E41/(1-$B$3)) -> 2.9056604 | G41: =$B$3 -> 0.47 | I41: 2.8 | J41: =IF(OR(I41="",E41=""),"",(I41-E41)/I41) -> 0.45 | K41: =IF(OR(I41="",F41=""),"",(I41-F41)/F41) -> -0.036363636 | L41: =IF(OR(I41="",H41=""),"",I41-H41) | M41: =IF(I41="","⚪ SIN PROPUESTA",IF(F41="","🟢 SOBRE PISO",IF(I41<F41*0.95,"🔴 BAJO PISO",IF(I41>F41*1.05,"🟢 SOBRE PISO","🟡 EN PISO")))) -> 🟡 EN PISO | N41: 7
A42: AV PLUS POTASIO | B42: 1 L | D42: 1 | E42: =IF(C42="","",C42/D42) | F42: =IF(E42="","",E42/(1-$B$3)) | G42: =$B$3 -> 0.47 | I42: 5.5 | J42: =IF(OR(I42="",E42=""),"",(I42-E42)/I42) | K42: =IF(OR(I42="",F42=""),"",(I42-F42)/F42) | L42: =IF(OR(I42="",H42=""),"",I42-H42) | M42: =IF(I42="","⚪ SIN PROPUESTA",IF(F42="","🟢 SOBRE PISO",IF(I42<F42*0.95,"🔴 BAJO PISO",IF(I42>F42*1.05,"🟢 SOBRE PISO","🟡 EN PISO")))) -> 🟢 SOBRE PISO | N42: 1
A43: AV PLUS POTASIO | B43: 20 L | C43: 38 | D43: 20 | E43: =IF(C43="","",C43/D43) -> 1.9 | F43: =IF(E43="","",E43/(1-$B$3)) -> 3.5849057 | G43: =$B$3 -> 0.47 | I43: 4 | J43: =IF(OR(I43="",E43=""),"",(I43-E43)/I43) -> 0.525 | K43: =IF(OR(I43="",F43=""),"",(I43-F43)/F43) -> 0.11578947 | L43: =IF(OR(I43="",H43=""),"",I43-H43) | M43: =IF(I43="","⚪ SIN PROPUESTA",IF(F43="","🟢 SOBRE PISO",IF(I43<F43*0.95,"🔴 BAJO PISO",IF(I43>F43*1.05,"🟢 SOBRE PISO","🟡 EN PISO")))) -> 🟢 SOBRE PISO | N43: 3
A44: AV PLUS POTASIO | B44: 200 L | C44: 320 | D44: 200 | E44: =IF(C44="","",C44/D44) -> 1.6 | F44: =IF(E44="","",E44/(1-$B$3)) -> 3.0188679 | G44: =$B$3 -> 0.47 | I44: 3.5 | J44: =IF(OR(I44="",E44=""),"",(I44-E44)/I44) -> 0.54285714 | K44: =IF(OR(I44="",F44=""),"",(I44-F44)/F44) -> 0.159375 | L44: =IF(OR(I44="",H44=""),"",I44-H44) | M44: =IF(I44="","⚪ SIN PROPUESTA",IF(F44="","🟢 SOBRE PISO",IF(I44<F44*0.95,"🔴 BAJO PISO",IF(I44>F44*1.05,"🟢 SOBRE PISO","🟡 EN PISO")))) -> 🟢 SOBRE PISO | N44: 4
A45: AV PLUS POTASIO | B45: 1000 L | C45: 1530 | D45: 1000 | E45: =IF(C45="","",C45/D45) -> 1.53 | F45: =IF(E45="","",E45/(1-$B$3)) -> 2.8867925 | G45: =$B$3 -> 0.47 | I45: 2.8 | J45: =IF(OR(I45="",E45=""),"",(I45-E45)/I45) -> 0.45357143 | K45: =IF(OR(I45="",F45=""),"",(I45-F45)/F45) -> -0.030065359 | L45: =IF(OR(I45="",H45=""),"",I45-H45) | M45: =IF(I45="","⚪ SIN PROPUESTA",IF(F45="","🟢 SOBRE PISO",IF(I45<F45*0.95,"🔴 BAJO PISO",IF(I45>F45*1.05,"🟢 SOBRE PISO","🟡 EN PISO")))) -> 🟡 EN PISO | N45: 7
A46: AV PLUS MAGNESIO | B46: 1 L | D46: 1 | E46: =IF(C46="","",C46/D46) | F46: =IF(E46="","",E46/(1-$B$3)) | G46: =$B$3 -> 0.47 | I46: 7 | J46: =IF(OR(I46="",E46=""),"",(I46-E46)/I46) | K46: =IF(OR(I46="",F46=""),"",(I46-F46)/F46) | L46: =IF(OR(I46="",H46=""),"",I46-H46) | M46: =IF(I46="","⚪ SIN PROPUESTA",IF(F46="","🟢 SOBRE PISO",IF(I46<F46*0.95,"🔴 BAJO PISO",IF(I46>F46*1.05,"🟢 SOBRE PISO","🟡 EN PISO")))) -> 🟢 SOBRE PISO | N46: 1
A47: AV PLUS MAGNESIO | B47: 20 L | C47: 30 | D47: 20 | E47: =IF(C47="","",C47/D47) -> 1.5 | F47: =IF(E47="","",E47/(1-$B$3)) -> 2.8301887 | G47: =$B$3 -> 0.47 | H47: 5.85 | I47: 5.5 | J47: =IF(OR(I47="",E47=""),"",(I47-E47)/I47) -> 0.72727273 | K47: =IF(OR(I47="",F47=""),"",(I47-F47)/F47) -> 0.94333333 | L47: =IF(OR(I47="",H47=""),"",I47-H47) -> -0.35 | M47: =IF(I47="","⚪ SIN PROPUESTA",IF(F47="","🟢 SOBRE PISO",IF(I47<F47*0.95,"🔴 BAJO PISO",IF(I47>F47*1.05,"🟢 SOBRE PISO","🟡 EN PISO")))) -> 🟢 SOBRE PISO | N47: 3
A48: AV PLUS MAGNESIO | B48: 200 L | C48: 236 | D48: 200 | E48: =IF(C48="","",C48/D48) -> 1.18 | F48: =IF(E48="","",E48/(1-$B$3)) -> 2.2264151 | G48: =$B$3 -> 0.47 | I48: 5 | J48: =IF(OR(I48="",E48=""),"",(I48-E48)/I48) -> 0.764 | K48: =IF(OR(I48="",F48=""),"",(I48-F48)/F48) -> 1.2457627 | L48: =IF(OR(I48="",H48=""),"",I48-H48) | M48: =IF(I48="","⚪ SIN PROPUESTA",IF(F48="","🟢 SOBRE PISO",IF(I48<F48*0.95,"🔴 BAJO PISO",IF(I48>F48*1.05,"🟢 SOBRE PISO","🟡 EN PISO")))) -> 🟢 SOBRE PISO | N48: 4
A49: AV PLUS MAGNESIO | B49: 1000 L | C49: 1120 | D49: 1000 | E49: =IF(C49="","",C49/D49) -> 1.12 | F49: =IF(E49="","",E49/(1-$B$3)) -> 2.1132075 | G49: =$B$3 -> 0.47 | I49: 4 | J49: =IF(OR(I49="",E49=""),"",(I49-E49)/I49) -> 0.72 | K49: =IF(OR(I49="",F49=""),"",(I49-F49)/F49) -> 0.89285714 | L49: =IF(OR(I49="",H49=""),"",I49-H49) | M49: =IF(I49="","⚪ SIN PROPUESTA",IF(F49="","🟢 SOBRE PISO",IF(I49<F49*0.95,"🔴 BAJO PISO",IF(I49>F49*1.05,"🟢 SOBRE PISO","🟡 EN PISO")))) -> 🟢 SOBRE PISO | N49: 7
A50: AV PLUS CALCIO | B50: 1 L | D50: 1 | E50: =IF(C50="","",C50/D50) | F50: =IF(E50="","",E50/(1-$B$3)) | G50: =$B$3 -> 0.47 | I50: 5.5 | J50: =IF(OR(I50="",E50=""),"",(I50-E50)/I50) | K50: =IF(OR(I50="",F50=""),"",(I50-F50)/F50) | L50: =IF(OR(I50="",H50=""),"",I50-H50) | M50: =IF(I50="","⚪ SIN PROPUESTA",IF(F50="","🟢 SOBRE PISO",IF(I50<F50*0.95,"🔴 BAJO PISO",IF(I50>F50*1.05,"🟢 SOBRE PISO","🟡 EN PISO")))) -> 🟢 SOBRE PISO | N50: 1
A51: AV PLUS CALCIO | B51: 20 L | C51: 27 | D51: 20 | E51: =IF(C51="","",C51/D51) -> 1.35 | F51: =IF(E51="","",E51/(1-$B$3)) -> 2.5471698 | G51: =$B$3 -> 0.47 | H51: 4.4 | I51: 4.5 | J51: =IF(OR(I51="",E51=""),"",(I51-E51)/I51) -> 0.7 | K51: =IF(OR(I51="",F51=""),"",(I51-F51)/F51) -> 0.76666667 | L51: =IF(OR(I51="",H51=""),"",I51-H51) -> 0.1 | M51: =IF(I51="","⚪ SIN PROPUESTA",IF(F51="","🟢 SOBRE PISO",IF(I51<F51*0.95,"🔴 BAJO PISO",IF(I51>F51*1.05,"🟢 SOBRE PISO","🟡 EN PISO")))) -> 🟢 SOBRE PISO | N51: 3
A52: AV PLUS CALCIO | B52: 200 L | C52: 210 | D52: 200 | E52: =IF(C52="","",C52/D52) -> 1.05 | F52: =IF(E52="","",E52/(1-$B$3)) -> 1.9811321 | G52: =$B$3 -> 0.47 | I52: 3.8 | J52: =IF(OR(I52="",E52=""),"",(I52-E52)/I52) -> 0.72368421 | K52: =IF(OR(I52="",F52=""),"",(I52-F52)/F52) -> 0.91809524 | L52: =IF(OR(I52="",H52=""),"",I52-H52) | M52: =IF(I52="","⚪ SIN PROPUESTA",IF(F52="","🟢 SOBRE PISO",IF(I52<F52*0.95,"🔴 BAJO PISO",IF(I52>F52*1.05,"🟢 SOBRE PISO","🟡 EN PISO")))) -> 🟢 SOBRE PISO | N52: 4
A53: AV PLUS CALCIO | B53: 1000 L | C53: 940 | D53: 1000 | E53: =IF(C53="","",C53/D53) -> 0.94 | F53: =IF(E53="","",E53/(1-$B$3)) -> 1.7735849 | G53: =$B$3 -> 0.47 | I53: 3 | J53: =IF(OR(I53="",E53=""),"",(I53-E53)/I53) -> 0.68666667 | K53: =IF(OR(I53="",F53=""),"",(I53-F53)/F53) -> 0.69148936 | L53: =IF(OR(I53="",H53=""),"",I53-H53) | M53: =IF(I53="","⚪ SIN PROPUESTA",IF(F53="","🟢 SOBRE PISO",IF(I53<F53*0.95,"🔴 BAJO PISO",IF(I53>F53*1.05,"🟢 SOBRE PISO","🟡 EN PISO")))) -> 🟢 SOBRE PISO | N53: 7
A54: AV PLUS CALCIO BORO | B54: 1 L | D54: 1 | E54: =IF(C54="","",C54/D54) | F54: =IF(E54="","",E54/(1-$B$3)) | G54: =$B$3 -> 0.47 | I54: 7 | J54: =IF(OR(I54="",E54=""),"",(I54-E54)/I54) | K54: =IF(OR(I54="",F54=""),"",(I54-F54)/F54) | L54: =IF(OR(I54="",H54=""),"",I54-H54) | M54: =IF(I54="","⚪ SIN PROPUESTA",IF(F54="","🟢 SOBRE PISO",IF(I54<F54*0.95,"🔴 BAJO PISO",IF(I54>F54*1.05,"🟢 SOBRE PISO","🟡 EN PISO")))) -> 🟢 SOBRE PISO | N54: 1
A55: AV PLUS CALCIO BORO | B55: 20 L | C55: 29 | D55: 20 | E55: =IF(C55="","",C55/D55) -> 1.45 | F55: =IF(E55="","",E55/(1-$B$3)) -> 2.7358491 | G55: =$B$3 -> 0.47 | I55: 5 | J55: =IF(OR(I55="",E55=""),"",(I55-E55)/I55) -> 0.71 | K55: =IF(OR(I55="",F55=""),"",(I55-F55)/F55) -> 0.82758621 | L55: =IF(OR(I55="",H55=""),"",I55-H55) | M55: =IF(I55="","⚪ SIN PROPUESTA",IF(F55="","🟢 SOBRE PISO",IF(I55<F55*0.95,"🔴 BAJO PISO",IF(I55>F55*1.05,"🟢 SOBRE PISO","🟡 EN PISO")))) -> 🟢 SOBRE PISO | N55: 3
A56: AV PLUS CALCIO BORO | B56: 200 L | C56: 220 | D56: 200 | E56: =IF(C56="","",C56/D56) -> 1.1 | F56: =IF(E56="","",E56/(1-$B$3)) -> 2.0754717 | G56: =$B$3 -> 0.47 | I56: 4 | J56: =IF(OR(I56="",E56=""),"",(I56-E56)/I56) -> 0.725 | K56: =IF(OR(I56="",F56=""),"",(I56-F56)/F56) -> 0.92727273 | L56: =IF(OR(I56="",H56=""),"",I56-H56) | M56: =IF(I56="","⚪ SIN PROPUESTA",IF(F56="","🟢 SOBRE PISO",IF(I56<F56*0.95,"🔴 BAJO PISO",IF(I56>F56*1.05,"🟢 SOBRE PISO","🟡 EN PISO")))) -> 🟢 SOBRE PISO | N56: 4
A57: AV PLUS CALCIO BORO | B57: 1000 L | C57: 1020 | D57: 1000 | E57: =IF(C57="","",C57/D57) -> 1.02 | F57: =IF(E57="","",E57/(1-$B$3)) -> 1.9245283 | G57: =$B$3 -> 0.47 | I57: 3 | J57: =IF(OR(I57="",E57=""),"",(I57-E57)/I57) -> 0.66 | K57: =IF(OR(I57="",F57=""),"",(I57-F57)/F57) -> 0.55882353 | L57: =IF(OR(I57="",H57=""),"",I57-H57) | M57: =IF(I57="","⚪ SIN PROPUESTA",IF(F57="","🟢 SOBRE PISO",IF(I57<F57*0.95,"🔴 BAJO PISO",IF(I57>F57*1.05,"🟢 SOBRE PISO","🟡 EN PISO")))) -> 🟢 SOBRE PISO | N57: 7
A58: AV PLUS ZINC | B58: 1 L | D58: 1 | E58: =IF(C58="","",C58/D58) | F58: =IF(E58="","",E58/(1-$B$3)) | G58: =$B$3 -> 0.47 | I58: 9 | J58: =IF(OR(I58="",E58=""),"",(I58-E58)/I58) | K58: =IF(OR(I58="",F58=""),"",(I58-F58)/F58) | L58: =IF(OR(I58="",H58=""),"",I58-H58) | M58: =IF(I58="","⚪ SIN PROPUESTA",IF(F58="","🟢 SOBRE PISO",IF(I58<F58*0.95,"🔴 BAJO PISO",IF(I58>F58*1.05,"🟢 SOBRE PISO","🟡 EN PISO")))) -> 🟢 SOBRE PISO | N58: 1
A59: AV PLUS ZINC | B59: 20 L | C59: 43 | D59: 20 | E59: =IF(C59="","",C59/D59) -> 2.15 | F59: =IF(E59="","",E59/(1-$B$3)) -> 4.0566038 | G59: =$B$3 -> 0.47 | H59: 7.5 | I59: 7.5 | J59: =IF(OR(I59="",E59=""),"",(I59-E59)/I59) -> 0.71333333 | K59: =IF(OR(I59="",F59=""),"",(I59-F59)/F59) -> 0.84883721 | L59: =IF(OR(I59="",H59=""),"",I59-H59) -> 0 | M59: =IF(I59="","⚪ SIN PROPUESTA",IF(F59="","🟢 SOBRE PISO",IF(I59<F59*0.95,"🔴 BAJO PISO",IF(I59>F59*1.05,"🟢 SOBRE PISO","🟡 EN PISO")))) -> 🟢 SOBRE PISO | N59: 3
A60: AV PLUS ZINC | B60: 200 L | C60: 370 | D60: 200 | E60: =IF(C60="","",C60/D60) -> 1.85 | F60: =IF(E60="","",E60/(1-$B$3)) -> 3.490566 | G60: =$B$3 -> 0.47 | I60: 6.8 | J60: =IF(OR(I60="",E60=""),"",(I60-E60)/I60) -> 0.72794118 | K60: =IF(OR(I60="",F60=""),"",(I60-F60)/F60) -> 0.94810811 | L60: =IF(OR(I60="",H60=""),"",I60-H60) | M60: =IF(I60="","⚪ SIN PROPUESTA",IF(F60="","🟢 SOBRE PISO",IF(I60<F60*0.95,"🔴 BAJO PISO",IF(I60>F60*1.05,"🟢 SOBRE PISO","🟡 EN PISO")))) -> 🟢 SOBRE PISO | N60: 4
A61: AV PLUS ZINC | B61: 1000 L | C61: 1780 | D61: 1000 | E61: =IF(C61="","",C61/D61) -> 1.78 | F61: =IF(E61="","",E61/(1-$B$3)) -> 3.3584906 | G61: =$B$3 -> 0.47 | I61: 5 | J61: =IF(OR(I61="",E61=""),"",(I61-E61)/I61) -> 0.644 | K61: =IF(OR(I61="",F61=""),"",(I61-F61)/F61) -> 0.48876404 | L61: =IF(OR(I61="",H61=""),"",I61-H61) | M61: =IF(I61="","⚪ SIN PROPUESTA",IF(F61="","🟢 SOBRE PISO",IF(I61<F61*0.95,"🔴 BAJO PISO",IF(I61>F61*1.05,"🟢 SOBRE PISO","🟡 EN PISO")))) -> 🟢 SOBRE PISO | N61: 7
A62: AV PLUS ZINC MANGANESO | B62: 1 L | D62: 1 | E62: =IF(C62="","",C62/D62) | F62: =IF(E62="","",E62/(1-$B$3)) | G62: =$B$3 -> 0.47 | I62: 8 | J62: =IF(OR(I62="",E62=""),"",(I62-E62)/I62) | K62: =IF(OR(I62="",F62=""),"",(I62-F62)/F62) | L62: =IF(OR(I62="",H62=""),"",I62-H62) | M62: =IF(I62="","⚪ SIN PROPUESTA",IF(F62="","🟢 SOBRE PISO",IF(I62<F62*0.95,"🔴 BAJO PISO",IF(I62>F62*1.05,"🟢 SOBRE PISO","🟡 EN PISO")))) -> 🟢 SOBRE PISO | N62: 1
A63: AV PLUS ZINC MANGANESO | B63: 20 L | C63: 37 | D63: 20 | E63: =IF(C63="","",C63/D63) -> 1.85 | F63: =IF(E63="","",E63/(1-$B$3)) -> 3.490566 | G63: =$B$3 -> 0.47 | H63: 6 | I63: 5.8 | J63: =IF(OR(I63="",E63=""),"",(I63-E63)/I63) -> 0.68103448 | K63: =IF(OR(I63="",F63=""),"",(I63-F63)/F63) -> 0.66162162 | L63: =IF(OR(I63="",H63=""),"",I63-H63) -> -0.2 | M63: =IF(I63="","⚪ SIN PROPUESTA",IF(F63="","🟢 SOBRE PISO",IF(I63<F63*0.95,"🔴 BAJO PISO",IF(I63>F63*1.05,"🟢 SOBRE PISO","🟡 EN PISO")))) -> 🟢 SOBRE PISO | N63: 3
A64: AV PLUS ZINC MANGANESO | B64: 200 L | C64: 313 | D64: 200 | E64: =IF(C64="","",C64/D64) -> 1.565 | F64: =IF(E64="","",E64/(1-$B$3)) -> 2.9528302 | G64: =$B$3 -> 0.47 | I64: 4.5 | J64: =IF(OR(I64="",E64=""),"",(I64-E64)/I64) -> 0.65222222 | K64: =IF(OR(I64="",F64=""),"",(I64-F64)/F64) -> 0.52396166 | L64: =IF(OR(I64="",H64=""),"",I64-H64) | M64: =IF(I64="","⚪ SIN PROPUESTA",IF(F64="","🟢 SOBRE PISO",IF(I64<F64*0.95,"🔴 BAJO PISO",IF(I64>F64*1.05,"🟢 SOBRE PISO","🟡 EN PISO")))) -> 🟢 SOBRE PISO | N64: 4
A65: AV PLUS ZINC MANGANESO | B65: 1000 L | C65: 1500 | D65: 1000 | E65: =IF(C65="","",C65/D65) -> 1.5 | F65: =IF(E65="","",E65/(1-$B$3)) -> 2.8301887 | G65: =$B$3 -> 0.47 | I65: 3 | J65: =IF(OR(I65="",E65=""),"",(I65-E65)/I65) -> 0.5 | K65: =IF(OR(I65="",F65=""),"",(I65-F65)/F65) -> 0.06 | L65: =IF(OR(I65="",H65=""),"",I65-H65) | M65: =IF(I65="","⚪ SIN PROPUESTA",IF(F65="","🟢 SOBRE PISO",IF(I65<F65*0.95,"🔴 BAJO PISO",IF(I65>F65*1.05,"🟢 SOBRE PISO","🟡 EN PISO")))) -> 🟢 SOBRE PISO | N65: 7
A66: AV PLUS BORO | B66: 1 L | D66: 1 | E66: =IF(C66="","",C66/D66) | F66: =IF(E66="","",E66/(1-$B$3)) | G66: =$B$3 -> 0.47 | I66: 5.5 | J66: =IF(OR(I66="",E66=""),"",(I66-E66)/I66) | K66: =IF(OR(I66="",F66=""),"",(I66-F66)/F66) | L66: =IF(OR(I66="",H66=""),"",I66-H66) | M66: =IF(I66="","⚪ SIN PROPUESTA",IF(F66="","🟢 SOBRE PISO",IF(I66<F66*0.95,"🔴 BAJO PISO",IF(I66>F66*1.05,"🟢 SOBRE PISO","🟡 EN PISO")))) -> 🟢 SOBRE PISO | N66: 1
A67: AV PLUS BORO | B67: 20 L | C67: 27 | D67: 20 | E67: =IF(C67="","",C67/D67) -> 1.35 | F67: =IF(E67="","",E67/(1-$B$3)) -> 2.5471698 | G67: =$B$3 -> 0.47 | H67: 5 | I67: 4.5 | J67: =IF(OR(I67="",E67=""),"",(I67-E67)/I67) -> 0.7 | K67: =IF(OR(I67="",F67=""),"",(I67-F67)/F67) -> 0.76666667 | L67: =IF(OR(I67="",H67=""),"",I67-H67) -> -0.5 | M67: =IF(I67="","⚪ SIN PROPUESTA",IF(F67="","🟢 SOBRE PISO",IF(I67<F67*0.95,"🔴 BAJO PISO",IF(I67>F67*1.05,"🟢 SOBRE PISO","🟡 EN PISO")))) -> 🟢 SOBRE PISO | N67: 3
A68: AV PLUS BORO | B68: 200 L | C68: 198 | D68: 200 | E68: =IF(C68="","",C68/D68) -> 0.99 | F68: =IF(E68="","",E68/(1-$B$3)) -> 1.8679245 | G68: =$B$3 -> 0.47 | I68: 3.8 | J68: =IF(OR(I68="",E68=""),"",(I68-E68)/I68) -> 0.73947368 | K68: =IF(OR(I68="",F68=""),"",(I68-F68)/F68) -> 1.0343434 | L68: =IF(OR(I68="",H68=""),"",I68-H68) | M68: =IF(I68="","⚪ SIN PROPUESTA",IF(F68="","🟢 SOBRE PISO",IF(I68<F68*0.95,"🔴 BAJO PISO",IF(I68>F68*1.05,"🟢 SOBRE PISO","🟡 EN PISO")))) -> 🟢 SOBRE PISO | N68: 4
A69: AV PLUS BORO | B69: 1000 L | C69: 915 | D69: 1000 | E69: =IF(C69="","",C69/D69) -> 0.915 | F69: =IF(E69="","",E69/(1-$B$3)) -> 1.7264151 | G69: =$B$3 -> 0.47 | I69: 3 | J69: =IF(OR(I69="",E69=""),"",(I69-E69)/I69) -> 0.695 | K69: =IF(OR(I69="",F69=""),"",(I69-F69)/F69) -> 0.73770492 | L69: =IF(OR(I69="",H69=""),"",I69-H69) | M69: =IF(I69="","⚪ SIN PROPUESTA",IF(F69="","🟢 SOBRE PISO",IF(I69<F69*0.95,"🔴 BAJO PISO",IF(I69>F69*1.05,"🟢 SOBRE PISO","🟡 EN PISO")))) -> 🟢 SOBRE PISO | N69: 7
A70: AV PLUS HIERRO | B70: 1 L | D70: 1 | E70: =IF(C70="","",C70/D70) | F70: =IF(E70="","",E70/(1-$B$3)) | G70: =$B$3 -> 0.47 | I70: 7 | J70: =IF(OR(I70="",E70=""),"",(I70-E70)/I70) | K70: =IF(OR(I70="",F70=""),"",(I70-F70)/F70) | L70: =IF(OR(I70="",H70=""),"",I70-H70) | M70: =IF(I70="","⚪ SIN PROPUESTA",IF(F70="","🟢 SOBRE PISO",IF(I70<F70*0.95,"🔴 BAJO PISO",IF(I70>F70*1.05,"🟢 SOBRE PISO","🟡 EN PISO")))) -> 🟢 SOBRE PISO | N70: 1
A71: AV PLUS HIERRO | B71: 20 L | C71: 27 | D71: 20 | E71: =IF(C71="","",C71/D71) -> 1.35 | F71: =IF(E71="","",E71/(1-$B$3)) -> 2.5471698 | G71: =$B$3 -> 0.47 | I71: 5 | J71: =IF(OR(I71="",E71=""),"",(I71-E71)/I71) -> 0.73 | K71: =IF(OR(I71="",F71=""),"",(I71-F71)/F71) -> 0.96296296 | L71: =IF(OR(I71="",H71=""),"",I71-H71) | M71: =IF(I71="","⚪ SIN PROPUESTA",IF(F71="","🟢 SOBRE PISO",IF(I71<F71*0.95,"🔴 BAJO PISO",IF(I71>F71*1.05,"🟢 SOBRE PISO","🟡 EN PISO")))) -> 🟢 SOBRE PISO | N71: 3
A72: AV PLUS HIERRO | B72: 200 L | C72: 210 | D72: 200 | E72: =IF(C72="","",C72/D72) -> 1.05 | F72: =IF(E72="","",E72/(1-$B$3)) -> 1.9811321 | G72: =$B$3 -> 0.47 | I72: 4 | J72: =IF(OR(I72="",E72=""),"",(I72-E72)/I72) -> 0.7375 | K72: =IF(OR(I72="",F72=""),"",(I72-F72)/F72) -> 1.0190476 | L72: =IF(OR(I72="",H72=""),"",I72-H72) | M72: =IF(I72="","⚪ SIN PROPUESTA",IF(F72="","🟢 SOBRE PISO",IF(I72<F72*0.95,"🔴 BAJO PISO",IF(I72>F72*1.05,"🟢 SOBRE PISO","🟡 EN PISO")))) -> 🟢 SOBRE PISO | N72: 4
A73: AV PLUS HIERRO | B73: 1000 L | C73: 980 | D73: 1000 | E73: =IF(C73="","",C73/D73) -> 0.98 | F73: =IF(E73="","",E73/(1-$B$3)) -> 1.8490566 | G73: =$B$3 -> 0.47 | I73: 3 | J73: =IF(OR(I73="",E73=""),"",(I73-E73)/I73) -> 0.67333333 | K73: =IF(OR(I73="",F73=""),"",(I73-F73)/F73) -> 0.62244898 | L73: =IF(OR(I73="",H73=""),"",I73-H73) | M73: =IF(I73="","⚪ SIN PROPUESTA",IF(F73="","🟢 SOBRE PISO",IF(I73<F73*0.95,"🔴 BAJO PISO",IF(I73>F73*1.05,"🟢 SOBRE PISO","🟡 EN PISO")))) -> 🟢 SOBRE PISO | N73: 7
A74: AV PLUS NUTRI MIX | B74: 1 L | D74: 1 | E74: =IF(C74="","",C74/D74) | F74: =IF(E74="","",E74/(1-$B$3)) | G74: =$B$3 -> 0.47 | I74: 10 | J74: =IF(OR(I74="",E74=""),"",(I74-E74)/I74) | K74: =IF(OR(I74="",F74=""),"",(I74-F74)/F74) | L74: =IF(OR(I74="",H74=""),"",I74-H74) | M74: =IF(I74="","⚪ SIN PROPUESTA",IF(F74="","🟢 SOBRE PISO",IF(I74<F74*0.95,"🔴 BAJO PISO",IF(I74>F74*1.05,"🟢 SOBRE PISO","🟡 EN PISO")))) -> 🟢 SOBRE PISO | N74: 1
A75: AV PLUS NUTRI MIX | B75: 20 L | C75: 45 | D75: 20 | E75: =IF(C75="","",C75/D75) -> 2.25 | F75: =IF(E75="","",E75/(1-$B$3)) -> 4.245283 | G75: =$B$3 -> 0.47 | H75: 8.5 | I75: 8.5 | J75: =IF(OR(I75="",E75=""),"",(I75-E75)/I75) -> 0.73529412 | K75: =IF(OR(I75="",F75=""),"",(I75-F75)/F75) -> 1.0022222 | L75: =IF(OR(I75="",H75=""),"",I75-H75) -> 0 | M75: =IF(I75="","⚪ SIN PROPUESTA",IF(F75="","🟢 SOBRE PISO",IF(I75<F75*0.95,"🔴 BAJO PISO",IF(I75>F75*1.05,"🟢 SOBRE PISO","🟡 EN PISO")))) -> 🟢 SOBRE PISO | N75: 3
A76: AV PLUS NUTRI MIX | B76: 200 L | C76: 387 | D76: 200 | E76: =IF(C76="","",C76/D76) -> 1.935 | F76: =IF(E76="","",E76/(1-$B$3)) -> 3.6509434 | G76: =$B$3 -> 0.47 | I76: 7 | J76: =IF(OR(I76="",E76=""),"",(I76-E76)/I76) -> 0.72357143 | K76: =IF(OR(I76="",F76=""),"",(I76-F76)/F76) -> 0.91731266 | L76: =IF(OR(I76="",H76=""),"",I76-H76) | M76: =IF(I76="","⚪ SIN PROPUESTA",IF(F76="","🟢 SOBRE PISO",IF(I76<F76*0.95,"🔴 BAJO PISO",IF(I76>F76*1.05,"🟢 SOBRE PISO","🟡 EN PISO")))) -> 🟢 SOBRE PISO | N76: 4
A77: AV PLUS NUTRI MIX | B77: 1000 L | C77: 1870 | D77: 1000 | E77: =IF(C77="","",C77/D77) -> 1.87 | F77: =IF(E77="","",E77/(1-$B$3)) -> 3.5283019 | G77: =$B$3 -> 0.47 | I77: 6 | J77: =IF(OR(I77="",E77=""),"",(I77-E77)/I77) -> 0.68833333 | K77: =IF(OR(I77="",F77=""),"",(I77-F77)/F77) -> 0.70053476 | L77: =IF(OR(I77="",H77=""),"",I77-H77) | M77: =IF(I77="","⚪ SIN PROPUESTA",IF(F77="","🟢 SOBRE PISO",IF(I77<F77*0.95,"🔴 BAJO PISO",IF(I77>F77*1.05,"🟢 SOBRE PISO","🟡 EN PISO")))) -> 🟢 SOBRE PISO | N77: 7
A78: AV PLUS NP-MIX | B78: 1 L | D78: 1 | E78: =IF(C78="","",C78/D78) | F78: =IF(E78="","",E78/(1-$B$3)) | G78: =$B$3 -> 0.47 | I78: 10 | J78: =IF(OR(I78="",E78=""),"",(I78-E78)/I78) | K78: =IF(OR(I78="",F78=""),"",(I78-F78)/F78) | L78: =IF(OR(I78="",H78=""),"",I78-H78) | M78: =IF(I78="","⚪ SIN PROPUESTA",IF(F78="","🟢 SOBRE PISO",IF(I78<F78*0.95,"🔴 BAJO PISO",IF(I78>F78*1.05,"🟢 SOBRE PISO","🟡 EN PISO")))) -> 🟢 SOBRE PISO | N78: 1
A79: AV PLUS NP-MIX | B79: 20 L | C79: 57 | D79: 20 | E79: =IF(C79="","",C79/D79) -> 2.85 | F79: =IF(E79="","",E79/(1-$B$3)) -> 5.3773585 | G79: =$B$3 -> 0.47 | I79: 8.5 | J79: =IF(OR(I79="",E79=""),"",(I79-E79)/I79) -> 0.66470588 | K79: =IF(OR(I79="",F79=""),"",(I79-F79)/F79) -> 0.58070175 | L79: =IF(OR(I79="",H79=""),"",I79-H79) | M79: =IF(I79="","⚪ SIN PROPUESTA",IF(F79="","🟢 SOBRE PISO",IF(I79<F79*0.95,"🔴 BAJO PISO",IF(I79>F79*1.05,"🟢 SOBRE PISO","🟡 EN PISO")))) -> 🟢 SOBRE PISO | N79: 3
A80: AV PLUS NP-MIX | B80: 200 L | C80: 512 | D80: 200 | E80: =IF(C80="","",C80/D80) -> 2.56 | F80: =IF(E80="","",E80/(1-$B$3)) -> 4.8301887 | G80: =$B$3 -> 0.47 | I80: 7 | J80: =IF(OR(I80="",E80=""),"",(I80-E80)/I80) -> 0.63428571 | K80: =IF(OR(I80="",F80=""),"",(I80-F80)/F80) -> 0.44921875 | L80: =IF(OR(I80="",H80=""),"",I80-H80) | M80: =IF(I80="","⚪ SIN PROPUESTA",IF(F80="","🟢 SOBRE PISO",IF(I80<F80*0.95,"🔴 BAJO PISO",IF(I80>F80*1.05,"🟢 SOBRE PISO","🟡 EN PISO")))) -> 🟢 SOBRE PISO | N80: 4
A81: AV PLUS NP-MIX | B81: 1000 L | C81: 2500 | D81: 1000 | E81: =IF(C81="","",C81/D81) -> 2.5 | F81: =IF(E81="","",E81/(1-$B$3)) -> 4.7169811 | G81: =$B$3 -> 0.47 | I81: 6 | J81: =IF(OR(I81="",E81=""),"",(I81-E81)/I81) -> 0.58333333 | K81: =IF(OR(I81="",F81=""),"",(I81-F81)/F81) -> 0.272 | L81: =IF(OR(I81="",H81=""),"",I81-H81) | M81: =IF(I81="","⚪ SIN PROPUESTA",IF(F81="","🟢 SOBRE PISO",IF(I81<F81*0.95,"🔴 BAJO PISO",IF(I81>F81*1.05,"🟢 SOBRE PISO","🟡 EN PISO")))) -> 🟢 SOBRE PISO | N81: 7
A82: AV PLUS MICRO MIX | B82: 1 L | D82: 1 | E82: =IF(C82="","",C82/D82) | F82: =IF(E82="","",E82/(1-$B$3)) | G82: =$B$3 -> 0.47 | I82: 8 | J82: =IF(OR(I82="",E82=""),"",(I82-E82)/I82) | K82: =IF(OR(I82="",F82=""),"",(I82-F82)/F82) | L82: =IF(OR(I82="",H82=""),"",I82-H82) | M82: =IF(I82="","⚪ SIN PROPUESTA",IF(F82="","🟢 SOBRE PISO",IF(I82<F82*0.95,"🔴 BAJO PISO",IF(I82>F82*1.05,"🟢 SOBRE PISO","🟡 EN PISO")))) -> 🟢 SOBRE PISO | N82: 1
A83: AV PLUS MICRO MIX | B83: 20 L | C83: 51 | D83: 20 | E83: =IF(C83="","",C83/D83) -> 2.55 | F83: =IF(E83="","",E83/(1-$B$3)) -> 4.8113208 | G83: =$B$3 -> 0.47 | H83: 6.7 | I83: 6.8 | J83: =IF(OR(I83="",E83=""),"",(I83-E83)/I83) -> 0.625 | K83: =IF(OR(I83="",F83=""),"",(I83-F83)/F83) -> 0.41333333 | L83: =IF(OR(I83="",H83=""),"",I83-H83) -> 0.1 | M83: =IF(I83="","⚪ SIN PROPUESTA",IF(F83="","🟢 SOBRE PISO",IF(I83<F83*0.95,"🔴 BAJO PISO",IF(I83>F83*1.05,"🟢 SOBRE PISO","🟡 EN PISO")))) -> 🟢 SOBRE PISO | N83: 3
A84: AV PLUS MICRO MIX | B84: 200 L | C84: 455 | D84: 200 | E84: =IF(C84="","",C84/D84) -> 2.275 | F84: =IF(E84="","",E84/(1-$B$3)) -> 4.2924528 | G84: =$B$3 -> 0.47 | I84: 5 | J84: =IF(OR(I84="",E84=""),"",(I84-E84)/I84) -> 0.545 | K84: =IF(OR(I84="",F84=""),"",(I84-F84)/F84) -> 0.16483516 | L84: =IF(OR(I84="",H84=""),"",I84-H84) | M84: =IF(I84="","⚪ SIN PROPUESTA",IF(F84="","🟢 SOBRE PISO",IF(I84<F84*0.95,"🔴 BAJO PISO",IF(I84>F84*1.05,"🟢 SOBRE PISO","🟡 EN PISO")))) -> 🟢 SOBRE PISO | N84: 4
A85: AV PLUS MICRO MIX | B85: 1000 L | C85: 2200 | D85: 1000 | E85: =IF(C85="","",C85/D85) -> 2.2 | F85: =IF(E85="","",E85/(1-$B$3)) -> 4.1509434 | G85: =$B$3 -> 0.47 | I85: 4.5 | J85: =IF(OR(I85="",E85=""),"",(I85-E85)/I85) -> 0.51111111 | K85: =IF(OR(I85="",F85=""),"",(I85-F85)/F85) -> 0.084090909 | L85: =IF(OR(I85="",H85=""),"",I85-H85) | M85: =IF(I85="","⚪ SIN PROPUESTA",IF(F85="","🟢 SOBRE PISO",IF(I85<F85*0.95,"🔴 BAJO PISO",IF(I85>F85*1.05,"🟢 SOBRE PISO","🟡 EN PISO")))) -> 🟢 SOBRE PISO | N85: 7
A86: AV PLUS MACRO FRUIT | B86: 1 L | D86: 1 | E86: =IF(C86="","",C86/D86) | F86: =IF(E86="","",E86/(1-$B$3)) | G86: =$B$3 -> 0.47 | I86: 10 | J86: =IF(OR(I86="",E86=""),"",(I86-E86)/I86) | K86: =IF(OR(I86="",F86=""),"",(I86-F86)/F86) | L86: =IF(OR(I86="",H86=""),"",I86-H86) | M86: =IF(I86="","⚪ SIN PROPUESTA",IF(F86="","🟢 SOBRE PISO",IF(I86<F86*0.95,"🔴 BAJO PISO",IF(I86>F86*1.05,"🟢 SOBRE PISO","🟡 EN PISO")))) -> 🟢 SOBRE PISO | N86: 1
A87: AV PLUS MACRO FRUIT | B87: 20 L | C87: 48 | D87: 20 | E87: =IF(C87="","",C87/D87) -> 2.4 | F87: =IF(E87="","",E87/(1-$B$3)) -> 4.5283019 | G87: =$B$3 -> 0.47 | I87: 8.5 | J87: =IF(OR(I87="",E87=""),"",(I87-E87)/I87) -> 0.71764706 | K87: =IF(OR(I87="",F87=""),"",(I87-F87)/F87) -> 0.87708333 | L87: =IF(OR(I87="",H87=""),"",I87-H87) | M87: =IF(I87="","⚪ SIN PROPUESTA",IF(F87="","🟢 SOBRE PISO",IF(I87<F87*0.95,"🔴 BAJO PISO",IF(I87>F87*1.05,"🟢 SOBRE PISO","🟡 EN PISO")))) -> 🟢 SOBRE PISO | N87: 3
A88: AV PLUS MACRO FRUIT | B88: 200 L | C88: 380 | D88: 200 | E88: =IF(C88="","",C88/D88) -> 1.9 | F88: =IF(E88="","",E88/(1-$B$3)) -> 3.5849057 | G88: =$B$3 -> 0.47 | I88: 7 | J88: =IF(OR(I88="",E88=""),"",(I88-E88)/I88) -> 0.72857143 | K88: =IF(OR(I88="",F88=""),"",(I88-F88)/F88) -> 0.95263158 | L88: =IF(OR(I88="",H88=""),"",I88-H88) | M88: =IF(I88="","⚪ SIN PROPUESTA",IF(F88="","🟢 SOBRE PISO",IF(I88<F88*0.95,"🔴 BAJO PISO",IF(I88>F88*1.05,"🟢 SOBRE PISO","🟡 EN PISO")))) -> 🟢 SOBRE PISO | N88: 4
A89: AV PLUS MACRO FRUIT | B89: 1000 L | C89: 1780 | D89: 1000 | E89: =IF(C89="","",C89/D89) -> 1.78 | F89: =IF(E89="","",E89/(1-$B$3)) -> 3.3584906 | G89: =$B$3 -> 0.47 | I89: 6 | J89: =IF(OR(I89="",E89=""),"",(I89-E89)/I89) -> 0.70333333 | K89: =IF(OR(I89="",F89=""),"",(I89-F89)/F89) -> 0.78651685 | L89: =IF(OR(I89="",H89=""),"",I89-H89) | M89: =IF(I89="","⚪ SIN PROPUESTA",IF(F89="","🟢 SOBRE PISO",IF(I89<F89*0.95,"🔴 BAJO PISO",IF(I89>F89*1.05,"🟢 SOBRE PISO","🟡 EN PISO")))) -> 🟢 SOBRE PISO | N89: 7
A90: AV MOVE | B90: 1 L | D90: 1 | E90: =IF(C90="","",C90/D90) | F90: =IF(E90="","",E90/(1-$B$3)) | G90: =$B$3 -> 0.47 | I90: 10 | J90: =IF(OR(I90="",E90=""),"",(I90-E90)/I90) | K90: =IF(OR(I90="",F90=""),"",(I90-F90)/F90) | L90: =IF(OR(I90="",H90=""),"",I90-H90) | M90: =IF(I90="","⚪ SIN PROPUESTA",IF(F90="","🟢 SOBRE PISO",IF(I90<F90*0.95,"🔴 BAJO PISO",IF(I90>F90*1.05,"🟢 SOBRE PISO","🟡 EN PISO")))) -> 🟢 SOBRE PISO | N90: 1
A91: AV MOVE | B91: 20 L | C91: 57 | D91: 20 | E91: =IF(C91="","",C91/D91) -> 2.85 | F91: =IF(E91="","",E91/(1-$B$3)) -> 5.3773585 | G91: =$B$3 -> 0.47 | H91: 8.75 | I91: 8.5 | J91: =IF(OR(I91="",E91=""),"",(I91-E91)/I91) -> 0.66470588 | K91: =IF(OR(I91="",F91=""),"",(I91-F91)/F91) -> 0.58070175 | L91: =IF(OR(I91="",H91=""),"",I91-H91) -> -0.25 | M91: =IF(I91="","⚪ SIN PROPUESTA",IF(F91="","🟢 SOBRE PISO",IF(I91<F91*0.95,"🔴 BAJO PISO",IF(I91>F91*1.05,"🟢 SOBRE PISO","🟡 EN PISO")))) -> 🟢 SOBRE PISO | N91: 3
A92: AV MOVE | B92: 200 L | C92: 510 | D92: 200 | E92: =IF(C92="","",C92/D92) -> 2.55 | F92: =IF(E92="","",E92/(1-$B$3)) -> 4.8113208 | G92: =$B$3 -> 0.47 | I92: 7 | J92: =IF(OR(I92="",E92=""),"",(I92-E92)/I92) -> 0.63571429 | K92: =IF(OR(I92="",F92=""),"",(I92-F92)/F92) -> 0.45490196 | L92: =IF(OR(I92="",H92=""),"",I92-H92) | M92: =IF(I92="","⚪ SIN PROPUESTA",IF(F92="","🟢 SOBRE PISO",IF(I92<F92*0.95,"🔴 BAJO PISO",IF(I92>F92*1.05,"🟢 SOBRE PISO","🟡 EN PISO")))) -> 🟢 SOBRE PISO | N92: 4
A93: AV MOVE | B93: 1000 L | C93: 2500 | D93: 1000 | E93: =IF(C93="","",C93/D93) -> 2.5 | F93: =IF(E93="","",E93/(1-$B$3)) -> 4.7169811 | G93: =$B$3 -> 0.47 | I93: 6 | J93: =IF(OR(I93="",E93=""),"",(I93-E93)/I93) -> 0.58333333 | K93: =IF(OR(I93="",F93=""),"",(I93-F93)/F93) -> 0.272 | L93: =IF(OR(I93="",H93=""),"",I93-H93) | M93: =IF(I93="","⚪ SIN PROPUESTA",IF(F93="","🟢 SOBRE PISO",IF(I93<F93*0.95,"🔴 BAJO PISO",IF(I93>F93*1.05,"🟢 SOBRE PISO","🟡 EN PISO")))) -> 🟢 SOBRE PISO | N93: 7
A94: AV BALANCE | B94: 1 L | D94: 1 | E94: =IF(C94="","",C94/D94) | F94: =IF(E94="","",E94/(1-$B$3)) | G94: =$B$3 -> 0.47 | I94: 15 | J94: =IF(OR(I94="",E94=""),"",(I94-E94)/I94) | K94: =IF(OR(I94="",F94=""),"",(I94-F94)/F94) | L94: =IF(OR(I94="",H94=""),"",I94-H94) | M94: =IF(I94="","⚪ SIN PROPUESTA",IF(F94="","🟢 SOBRE PISO",IF(I94<F94*0.95,"🔴 BAJO PISO",IF(I94>F94*1.05,"🟢 SOBRE PISO","🟡 EN PISO")))) -> 🟢 SOBRE PISO | N94: 1
A95: AV BALANCE | B95: 20 L | C95: 58 | D95: 20 | E95: =IF(C95="","",C95/D95) -> 2.9 | F95: =IF(E95="","",E95/(1-$B$3)) -> 5.4716981 | G95: =$B$3 -> 0.47 | I95: 14 | J95: =IF(OR(I95="",E95=""),"",(I95-E95)/I95) -> 0.79285714 | K95: =IF(OR(I95="",F95=""),"",(I95-F95)/F95) -> 1.5586207 | L95: =IF(OR(I95="",H95=""),"",I95-H95) | M95: =IF(I95="","⚪ SIN PROPUESTA",IF(F95="","🟢 SOBRE PISO",IF(I95<F95*0.95,"🔴 BAJO PISO",IF(I95>F95*1.05,"🟢 SOBRE PISO","🟡 EN PISO")))) -> 🟢 SOBRE PISO | N95: 3
A96: AV BALANCE | B96: 200 L | C96: 520 | D96: 200 | E96: =IF(C96="","",C96/D96) -> 2.6 | F96: =IF(E96="","",E96/(1-$B$3)) -> 4.9056604 | G96: =$B$3 -> 0.47 | I96: 13 | J96: =IF(OR(I96="",E96=""),"",(I96-E96)/I96) -> 0.8 | K96: =IF(OR(I96="",F96=""),"",(I96-F96)/F96) -> 1.65 | L96: =IF(OR(I96="",H96=""),"",I96-H96) | M96: =IF(I96="","⚪ SIN PROPUESTA",IF(F96="","🟢 SOBRE PISO",IF(I96<F96*0.95,"🔴 BAJO PISO",IF(I96>F96*1.05,"🟢 SOBRE PISO","🟡 EN PISO")))) -> 🟢 SOBRE PISO | N96: 4
A97: AV BALANCE | B97: 1000 L | C97: 2500 | D97: 1000 | E97: =IF(C97="","",C97/D97) -> 2.5 | F97: =IF(E97="","",E97/(1-$B$3)) -> 4.7169811 | G97: =$B$3 -> 0.47 | I97: 10 | J97: =IF(OR(I97="",E97=""),"",(I97-E97)/I97) -> 0.75 | K97: =IF(OR(I97="",F97=""),"",(I97-F97)/F97) -> 1.12 | L97: =IF(OR(I97="",H97=""),"",I97-H97) | M97: =IF(I97="","⚪ SIN PROPUESTA",IF(F97="","🟢 SOBRE PISO",IF(I97<F97*0.95,"🔴 BAJO PISO",IF(I97>F97*1.05,"🟢 SOBRE PISO","🟡 EN PISO")))) -> 🟢 SOBRE PISO | N97: 7
A98: AV BLOOM | B98: 1 L | D98: 1 | E98: =IF(C98="","",C98/D98) | F98: =IF(E98="","",E98/(1-$B$3)) | G98: =$B$3 -> 0.47 | I98: 11 | J98: =IF(OR(I98="",E98=""),"",(I98-E98)/I98) | K98: =IF(OR(I98="",F98=""),"",(I98-F98)/F98) | L98: =IF(OR(I98="",H98=""),"",I98-H98) | M98: =IF(I98="","⚪ SIN PROPUESTA",IF(F98="","🟢 SOBRE PISO",IF(I98<F98*0.95,"🔴 BAJO PISO",IF(I98>F98*1.05,"🟢 SOBRE PISO","🟡 EN PISO")))) -> 🟢 SOBRE PISO | N98: 1
A99: AV BLOOM | B99: 20 L | C99: 48 | D99: 20 | E99: =IF(C99="","",C99/D99) -> 2.4 | F99: =IF(E99="","",E99/(1-$B$3)) -> 4.5283019 | G99: =$B$3 -> 0.47 | I99: 9 | J99: =IF(OR(I99="",E99=""),"",(I99-E99)/I99) -> 0.73333333 | K99: =IF(OR(I99="",F99=""),"",(I99-F99)/F99) -> 0.9875 | L99: =IF(OR(I99="",H99=""),"",I99-H99) | M99: =IF(I99="","⚪ SIN PROPUESTA",IF(F99="","🟢 SOBRE PISO",IF(I99<F99*0.95,"🔴 BAJO PISO",IF(I99>F99*1.05,"🟢 SOBRE PISO","🟡 EN PISO")))) -> 🟢 SOBRE PISO | N99: 3
A100: AV BLOOM | B100: 200 L | C100: 400 | D100: 200 | E100: =IF(C100="","",C100/D100) -> 2 | F100: =IF(E100="","",E100/(1-$B$3)) -> 3.7735849 | G100: =$B$3 -> 0.47 | I100: 8 | J100: =IF(OR(I100="",E100=""),"",(I100-E100)/I100) -> 0.75 | K100: =IF(OR(I100="",F100=""),"",(I100-F100)/F100) -> 1.12 | L100: =IF(OR(I100="",H100=""),"",I100-H100) | M100: =IF(I100="","⚪ SIN PROPUESTA",IF(F100="","🟢 SOBRE PISO",IF(I100<F100*0.95,"🔴 BAJO PISO",IF(I100>F100*1.05,"🟢 SOBRE PISO","🟡 EN PISO")))) -> 🟢 SOBRE PISO | N100: 4
A101: AV BLOOM | B101: 1000 L | C101: 1930 | D101: 1000 | E101: =IF(C101="","",C101/D101) -> 1.93 | F101: =IF(E101="","",E101/(1-$B$3)) -> 3.6415094 | G101: =$B$3 -> 0.47 | I101: 7 | J101: =IF(OR(I101="",E101=""),"",(I101-E101)/I101) -> 0.72428571 | K101: =IF(OR(I101="",F101=""),"",(I101-F101)/F101) -> 0.92227979 | L101: =IF(OR(I101="",H101=""),"",I101-H101) | M101: =IF(I101="","⚪ SIN PROPUESTA",IF(F101="","🟢 SOBRE PISO",IF(I101<F101*0.95,"🔴 BAJO PISO",IF(I101>F101*1.05,"🟢 SOBRE PISO","🟡 EN PISO")))) -> 🟢 SOBRE PISO | N101: 7
...

Sheet precios piso peru 
B1: LISTA DE PRECIOS PISO — FUERZA COMERCIAL PERÚ 2026
B2: AGROVECA PERÚ S.A.C. | Precios mínimos de venta (USD/Unidad) | Vigencia: Abril 2026 | Aprobado: Gerencia General
B3: ⚠️ Ninguna venta puede realizarse por debajo de estos precios sin autorización escrita de Gerencia General.
B4: PRODUCTO | C4: FORMATO | D4: Precio Piso AV (USD/Unidad) | E4: Precio Piso AV (USD/Unidad)
B5: ='Pricing Piso Peru'!A6 -> AV HUMIC ROOT | C5: ='Pricing Piso Peru'!B6 -> 1 L | D5: ='Pricing Piso Peru'!I6 -> 4.2 | E5: ='Pricing Piso Peru'!M6 -> 🟢 SOBRE PISO
B6: ='Pricing Piso Peru'!A7 -> AV HUMIC ROOT | C6: ='Pricing Piso Peru'!B7 -> 20 L | D6: ='Pricing Piso Peru'!I7 -> 3.5 | E6: ='Pricing Piso Peru'!M7 -> 🟢 SOBRE PISO
B7: ='Pricing Piso Peru'!A8 -> AV HUMIC ROOT | C7: ='Pricing Piso Peru'!B8 -> 200 L | D7: ='Pricing Piso Peru'!I8 -> 3 | E7: ='Pricing Piso Peru'!M8 -> 🟢 SOBRE PISO
B8: ='Pricing Piso Peru'!A9 -> AV HUMIC ROOT | C8: ='Pricing Piso Peru'!B9 -> 1000 L | D8: ='Pricing Piso Peru'!I9 -> 2.5 | E8: ='Pricing Piso Peru'!M9 -> 🟢 SOBRE PISO
B9: ='Pricing Piso Peru'!A10 -> AV MAX FULVIC 45% | C9: ='Pricing Piso Peru'!B10 -> 1 L | D9: ='Pricing Piso Peru'!I10 -> 4.2 | E9: ='Pricing Piso Peru'!M10 -> 🟢 SOBRE PISO
B10: ='Pricing Piso Peru'!A11 -> AV MAX FULVIC 45% | C10: ='Pricing Piso Peru'!B11 -> 20 L | D10: ='Pricing Piso Peru'!I11 -> 3 | E10: ='Pricing Piso Peru'!M11 -> 🟡 EN PISO
B11: ='Pricing Piso Peru'!A12 -> AV MAX FULVIC 45% | C11: ='Pricing Piso Peru'!B12 -> 200 L | D11: ='Pricing Piso Peru'!I12 -> 2.5 | E11: ='Pricing Piso Peru'!M12 -> 🟢 SOBRE PISO
B12: ='Pricing Piso Peru'!A13 -> AV MAX FULVIC 45% | C12: ='Pricing Piso Peru'!B13 -> 1000 L | D12: ='Pricing Piso Peru'!I13 -> 2.2 | E12: ='Pricing Piso Peru'!M13 -> 🟡 EN PISO
B13: ='Pricing Piso Peru'!A14 -> AV AMIN | C13: ='Pricing Piso Peru'!B14 -> 1 L | D13: ='Pricing Piso Peru'!I14 -> 5 | E13: ='Pricing Piso Peru'!M14 -> 🟢 SOBRE PISO
B14: ='Pricing Piso Peru'!A15 -> AV AMIN | C14: ='Pricing Piso Peru'!B15 -> 20 L | D14: ='Pricing Piso Peru'!I15 -> 4.2 | E14: ='Pricing Piso Peru'!M15 -> 🟢 SOBRE PISO
B15: ='Pricing Piso Peru'!A16 -> AV AMIN | C15: ='Pricing Piso Peru'!B16 -> 200 L | D15: ='Pricing Piso Peru'!I16 -> 3.5 | E15: ='Pricing Piso Peru'!M16 -> 🟢 SOBRE PISO
B16: ='Pricing Piso Peru'!A17 -> AV AMIN | C16: ='Pricing Piso Peru'!B17 -> 1000 L | D16: ='Pricing Piso Peru'!I17 -> 3 | E16: ='Pricing Piso Peru'!M17 -> 🟢 SOBRE PISO
... B108: ='Pricing Piso Peru'!A109 -> AV BIOSOLARIS | C108: ='Pricing Piso Peru'!B109 -> 1000 L | D108: ='Pricing Piso Peru'!I109 -> 14 | E108: ='Pricing Piso Peru'!M109 -> 🟢 SOBRE PISO
